Workbook

Sheet TABLERO
A1: 📊 TABLERO DE CONTROL FINANCIERO - NEUROTEA + FAMILIA
A3: Mes seleccionado: | B3: Enero 2026 | D3: Fecha de hoy: | E3: =TODAY()
A5: ═══ 🚨 SUPERVIVENCIA FINANCIERA ═══ | G5: ═══ 📅 LIQUIDEZ SEMANAL ═══
A6: Indicador | B6: Valor | C6: Meta | D6: Estado | G6: Concepto | H6: Cant. | I6: Monto | J6: Acumulado | K6: Estado
A7: 💰 Caja disponible TOTAL ✏️ | B7: 0 | C7: 3 meses gastos | D7: =IF(B7=0,"⚪ Sin datos",IF(B8>=90,"🟢 OK",IF(B8>=30,"🟡 ALERTA","🔴 CRÍTICO"))) | G7: Caja disponible | I7: =B7 | J7: =I7
A8: ⏱️ Días de oxígeno | B8: =IF(B15=0,0,ROUND(B7/B15*30,0)) | C8: ≥ 90 días | D8: =IF(B8=0,"⚪ Sin datos",IF(B8>=90,"🟢 OK",IF(B8>=30,"🟡 ALERTA","🔴 CRÍTICO"))) | G8: 🔴 Atrasados | H8: ✏️ | I8: 0 | J8: =J7-I8 | K8: =IF(I8=0,"🟢",IF(J8>=0,"🟡 Pagar","🔴 Deuda"))
A9: 📋 Gastos pendientes mes | B9: =IFERROR(INDIRECT("'"&B3&"'!C73"),0)+IFERROR(INDIRECT("'"&B3&"'!I65"),0) | C9: Cubrir con caja | D9: =IF(B9=0,"🟢 OK",IF(B9<=B7,"🟢 Cubierto","🔴 No alcanza")) | G9: 📅 Esta semana | H9: ✏️ | I9: 0 | J9: =J8-I9 | K9: =IF(J9>=0,"🟢 Alcanza","🔴 Falta")
A10: ⚠️ Préstamo NT → Familia | B10: =IFERROR(INDIRECT("'"&B3&"'!D6"),0) | C10: 0 (ideal) | D10: =IF(B10=0,"🟢 SANO","🔴 FUGA") | G10: 📅 Próxima semana | H10: ✏️ | I10: 0 | J10: =J9-I10 | K10: =IF(J10>=0,"🟢 Alcanza","🔴 Falta")
G11: SALDO FINAL | J11: =J10 | K11: =IF(J11>=0,"🟢 OK","🔴 DÉFICIT")
A13: ═══ 💵 FLUJO DEL MES ═══ | G13: ═══ 💳 SITUACIÓN DE DEUDAS ═══
A14: Indicador | B14: Familia | C14: NeuroTEA | D14: Total | E14: Estado | G14: Indicador | H14: Valor | K14: Estado
A15: 📈 Ingresos | B15: =IFERROR(INDIRECT("'"&$B$3&"'!D26"),0) | C15: =IFERROR(INDIRECT("'"&$B$3&"'!I15"),0) | D15: =B15+C15 | E15: =IF(D15=0,"⚪",IF(D15>0,"🟢","🔴")) | G15: Deuda TOTAL | H15: =IFERROR(DEUDAS!E28,0) | K15: =IF(H15=0,"🟢","🟡 Activa")
A16: 📉 Egresos | B16: =IFERROR(INDIRECT("'"&$B$3&"'!C72"),0)+IFERROR(INDIRECT("'"&$B$3&"'!C73"),0) | C16: =IFERROR(INDIRECT("'"&$B$3&"'!I64"),0)+IFERROR(INDIRECT("'"&$B$3&"'!I65"),0) | D16: =B16+C16 | E16: =IF(D16=0,"⚪",IF(D16<=D15,"🟢","🔴")) | G16: Cuotas mensuales | H16: =IFERROR(DEUDAS!F28,0) | K16: =IF(H16=0,"🟢",IF(H16<=B17,"🟢 Cubierto","🔴 Excede"))
A17: 📊 Balance | B17: =B15-B16 | C17: =C15-C16 | D17: =D15-D16 | E17: =IF(D17=0,"⚪",IF(D17>0,"🟢 GANASTE","🔴 PERDISTE")) | G17: IPS al día ✏️ | H17: SÍ | K17: =IF(H17="SÍ","🟢","🔴 URGENTE")
G18: IVA al día ✏️ | H18: SÍ | K18: =IF(H18="SÍ","🟢","🔴 URGENTE")
A20: ═══ 🏥 SALUD FINANCIERA NEUROTEA ═══ | G20: ═══ 🛡️ FONDO DE RESERVA ═══
A21: Concepto | B21: % Ideal | C21: Monto Ideal | D21: Monto Real | E21: Estado | G21: Reserva Familiar ✏️ | H21: 0 | K21: =IF(H21=0,"🔴 Sin fondo","🟢")
A22: Gastos Operativos | B22: =Configuración!B20 | C22: =C15*Configuración!B20 | D22: =C16 | E22: =IF(C15=0,"-",IF(D22<=C22,"🟢","🔴")) | G22: Reserva NeuroTEA ✏️ | H22: 0 | K22: =IF(H22=0,"🔴 Sin fondo","🟢")
A23: Compensación dueño | B23: =Configuración!B23 | C23: =C15*Configuración!B23 | D23: 0 | E23: =IF(D23>=C23,"🟢","🔴") | G23: Meta (3 meses gastos) | H23: =D16*3
A24: Fondo emergencia | B24: =Configuración!B24 | C24: =C15*Configuración!B24 | D24: 0 | E24: =IF(D24>=C24,"🟢","🔴") | G24: % Meta alcanzado | H24: =IF(H23=0,0,(H21+H22)/H23) | K24: =IF(H24>=1,"🟢 META",IF(H24>=0.5,"🟡 Avanzando","🔴 Bajo"))
A25: Inversión | B25: =Configuración!B25 | C25: =C15*Configuración!B25 | D25: 0 | E25: =IF(D25>=C25,"🟢","🔴")
A26: Imprevistos | B26: =Configuración!B26 | C26: =C15*Configuración!B26 | D26: 0 | E26: =IF(D26>=C26,"🟢","🔴") | G26: ═══ 📋 ACCIONES DE LA SEMANA ═══
A27: % Gastos / Ingreso NT: | B27: =IF(C15=0,0,D22/C15) | C27: DIAGNÓSTICO: | D27: =IF(C15=0,"⚪ Sin datos",IF(B27<=Configuración!B20,"🟢 CLÍNICA SANA",IF(B27<=1,"🟡 REVISAR","🔴 CRÍTICA"))) | G27: Fecha revisión ✏️
G28: 1.
G29: 2.
G30: 3.
G31: 4.
G32: 5.
A35: ═══ 📊 CUMPLIMIENTO PRESUPUESTO 2026 ═══
B36: ENE | C36: FEB | D36: MAR | E36: ABR | F36: MAY | G36: JUN | H36: JUL | I36: AGO | J36: SEP | K36: OCT | L36: NOV | M36: DIC | N36: TEND.
A37: ► FAMILIA
A38: Ingresos | B38: =IFERROR(INDIRECT("'Enero 2026'!D26")/PRESUPUESTO!B14,"-") | C38: =IFERROR(INDIRECT("'Febrero 2026'!D26")/PRESUPUESTO!C14,"-") | D38: =IFERROR(INDIRECT("'Marzo 2026'!D26")/PRESUPUESTO!D14,"-") | E38: =IFERROR(INDIRECT("'Abril 2026'!D26")/PRESUPUESTO!E14,"-") | F38: =IFERROR(INDIRECT("'Mayo 2026'!D26")/PRESUPUESTO!F14,"-") | G38: =IFERROR(INDIRECT("'Junio 2026'!D26")/PRESUPUESTO!G14,"-") | H38: =IFERROR(INDIRECT("'Julio 2026'!D26")/PRESUPUESTO!H14,"-") | I38: =IFERROR(INDIRECT("'Agosto 2026'!D26")/PRESUPUESTO!I14,"-") | J38: =IFERROR(INDIRECT("'Septiembre 2026'!D26")/PRESUPUESTO!J14,"-") | K38: =IFERROR(INDIRECT("'Octubre 2026'!D26")/PRESUPUESTO!K14,"-") | L38: =IFERROR(INDIRECT("'Noviembre 2026'!D26")/PRESUPUESTO!L14,"-") | M38: =IFERROR(INDIRECT("'Diciembre 2026'!D26")/PRESUPUESTO!M14,"-")
A39: Egresos | B39: =IFERROR((INDIRECT("'Enero 2026'!C72")+INDIRECT("'Enero 2026'!C73"))/PRESUPUESTO!B50,"-") | C39: =IFERROR((INDIRECT("'Febrero 2026'!C72")+INDIRECT("'Febrero 2026'!C73"))/PRESUPUESTO!C50,"-") | D39: =IFERROR((INDIRECT("'Marzo 2026'!C72")+INDIRECT("'Marzo 2026'!C73"))/PRESUPUESTO!D50,"-") | E39: =IFERROR((INDIRECT("'Abril 2026'!C72")+INDIRECT("'Abril 2026'!C73"))/PRESUPUESTO!E50,"-") | F39: =IFERROR((INDIRECT("'Mayo 2026'!C72")+INDIRECT("'Mayo 2026'!C73"))/PRESUPUESTO!F50,"-") | G39: =IFERROR((INDIRECT("'Junio 2026'!C72")+INDIRECT("'Junio 2026'!C73"))/PRESUPUESTO!G50,"-") | H39: =IFERROR((INDIRECT("'Julio 2026'!C72")+INDIRECT("'Julio 2026'!C73"))/PRESUPUESTO!H50,"-") | I39: =IFERROR((INDIRECT("'Agosto 2026'!C72")+INDIRECT("'Agosto 2026'!C73"))/PRESUPUESTO!I50,"-") | J39: =IFERROR((INDIRECT("'Septiembre 2026'!C72")+INDIRECT("'Septiembre 2026'!C73"))/PRESUPUESTO!J50,"-") | K39: =IFERROR((INDIRECT("'Octubre 2026'!C72")+INDIRECT("'Octubre 2026'!C73"))/PRESUPUESTO!K50,"-") | L39: =IFERROR((INDIRECT("'Noviembre 2026'!C72")+INDIRECT("'Noviembre 2026'!C73"))/PRESUPUESTO!L50,"-") | M39: =IFERROR((INDIRECT("'Diciembre 2026'!C72")+INDIRECT("'Diciembre 2026'!C73"))/PRESUPUESTO!M50,"-")
A40: Balance | B40: =IF(OR(C38="-",C39="-"),"-",IF(AND(C38>=1,C39<=1),"🟢",IF(AND(C38>=0.95,C39<=1.05),"🟡","🔴"))) | C40: =IF(OR(D38="-",D39="-"),"-",IF(AND(D38>=1,D39<=1),"🟢",IF(AND(D38>=0.95,D39<=1.05),"🟡","🔴"))) | D40: =IF(OR(E38="-",E39="-"),"-",IF(AND(E38>=1,E39<=1),"🟢",IF(AND(E38>=0.95,E39<=1.05),"🟡","🔴"))) | E40: =IF(OR(F38="-",F39="-"),"-",IF(AND(F38>=1,F39<=1),"🟢",IF(AND(F38>=0.95,F39<=1.05),"🟡","🔴"))) | F40: =IF(OR(G38="-",G39="-"),"-",IF(AND(G38>=1,G39<=1),"🟢",IF(AND(G38>=0.95,G39<=1.05),"🟡","🔴"))) | G40: =IF(OR(H38="-",H39="-"),"-",IF(AND(H38>=1,H39<=1),"🟢",IF(AND(H38>=0.95,H39<=1.05),"🟡","🔴"))) | H40: =IF(OR(I38="-",I39="-"),"-",IF(AND(I38>=1,I39<=1),"🟢",IF(AND(I38>=0.95,I39<=1.05),"🟡","🔴"))) | I40: =IF(OR(J38="-",J39="-"),"-",IF(AND(J38>=1,J39<=1),"🟢",IF(AND(J38>=0.95,J39<=1.05),"🟡","🔴"))) | ... M40: =IF(OR(N38="-",N39="-"),"-",IF(AND(N38>=1,N39<=1),"🟢",IF(AND(N38>=0.95,N39<=1.05),"🟡","🔴")))
A41: ► NEUROTEA
A42: Ingresos | B42: =IFERROR(INDIRECT("'Enero 2026'!I15")/PRESUPUESTO!B59,"-") | C42: =IFERROR(INDIRECT("'Febrero 2026'!I15")/PRESUPUESTO!C59,"-") | D42: =IFERROR(INDIRECT("'Marzo 2026'!I15")/PRESUPUESTO!D59,"-") | E42: =IFERROR(INDIRECT("'Abril 2026'!I15")/PRESUPUESTO!E59,"-") | F42: =IFERROR(INDIRECT("'Mayo 2026'!I15")/PRESUPUESTO!F59,"-") | G42: =IFERROR(INDIRECT("'Junio 2026'!I15")/PRESUPUESTO!G59,"-") | H42: =IFERROR(INDIRECT("'Julio 2026'!I15")/PRESUPUESTO!H59,"-") | I42: =IFERROR(INDIRECT("'Agosto 2026'!I15")/PRESUPUESTO!I59,"-") | J42: =IFERROR(INDIRECT("'Septiembre 2026'!I15")/PRESUPUESTO!J59,"-") | K42: =IFERROR(INDIRECT("'Octubre 2026'!I15")/PRESUPUESTO!K59,"-") | L42: =IFERROR(INDIRECT("'Noviembre 2026'!I15")/PRESUPUESTO!L59,"-") | M42: =IFERROR(INDIRECT("'Diciembre 2026'!I15")/PRESUPUESTO!M59,"-")
A43: Egresos | B43: =IFERROR((INDIRECT("'Enero 2026'!I64")+INDIRECT("'Enero 2026'!I65"))/PRESUPUESTO!B91,"-") | C43: =IFERROR((INDIRECT("'Febrero 2026'!I64")+INDIRECT("'Febrero 2026'!I65"))/PRESUPUESTO!C91,"-") | D43: =IFERROR((INDIRECT("'Marzo 2026'!I64")+INDIRECT("'Marzo 2026'!I65"))/PRESUPUESTO!D91,"-") | E43: =IFERROR((INDIRECT("'Abril 2026'!I64")+INDIRECT("'Abril 2026'!I65"))/PRESUPUESTO!E91,"-") | F43: =IFERROR((INDIRECT("'Mayo 2026'!I64")+INDIRECT("'Mayo 2026'!I65"))/PRESUPUESTO!F91,"-") | G43: =IFERROR((INDIRECT("'Junio 2026'!I64")+INDIRECT("'Junio 2026'!I65"))/PRESUPUESTO!G91,"-") | H43: =IFERROR((INDIRECT("'Julio 2026'!I64")+INDIRECT("'Julio 2026'!I65"))/PRESUPUESTO!H91,"-") | I43: =IFERROR((INDIRECT("'Agosto 2026'!I64")+INDIRECT("'Agosto 2026'!I65"))/PRESUPUESTO!I91,"-") | J43: =IFERROR((INDIRECT("'Septiembre 2026'!I64")+INDIRECT("'Septiembre 2026'!I65"))/PRESUPUESTO!J91,"-") | K43: =IFERROR((INDIRECT("'Octubre 2026'!I64")+INDIRECT("'Octubre 2026'!I65"))/PRESUPUESTO!K91,"-") | L43: =IFERROR((INDIRECT("'Noviembre 2026'!I64")+INDIRECT("'Noviembre 2026'!I65"))/PRESUPUESTO!L91,"-") | M43: =IFERROR((INDIRECT("'Diciembre 2026'!I64")+INDIRECT("'Diciembre 2026'!I65"))/PRESUPUESTO!M91,"-")
A44: Balance | B44: =IF(OR(C42="-",C43="-"),"-",IF(AND(C42>=1,C43<=1),"🟢",IF(AND(C42>=0.95,C43<=1.05),"🟡","🔴"))) | C44: =IF(OR(D42="-",D43="-"),"-",IF(AND(D42>=1,D43<=1),"🟢",IF(AND(D42>=0.95,D43<=1.05),"🟡","🔴"))) | D44: =IF(OR(E42="-",E43="-"),"-",IF(AND(E42>=1,E43<=1),"🟢",IF(AND(E42>=0.95,E43<=1.05),"🟡","🔴"))) | E44: =IF(OR(F42="-",F43="-"),"-",IF(AND(F42>=1,F43<=1),"🟢",IF(AND(F42>=0.95,F43<=1.05),"🟡","🔴"))) | F44: =IF(OR(G42="-",G43="-"),"-",IF(AND(G42>=1,G43<=1),"🟢",IF(AND(G42>=0.95,G43<=1.05),"🟡","🔴"))) | G44: =IF(OR(H42="-",H43="-"),"-",IF(AND(H42>=1,H43<=1),"🟢",IF(AND(H42>=0.95,H43<=1.05),"🟡","🔴"))) | H44: =IF(OR(I42="-",I43="-"),"-",IF(AND(I42>=1,I43<=1),"🟢",IF(AND(I42>=0.95,I43<=1.05),"🟡","🔴"))) | I44: =IF(OR(J42="-",J43="-"),"-",IF(AND(J42>=1,J43<=1),"🟢",IF(AND(J42>=0.95,J43<=1.05),"🟡","🔴"))) | ... M44: =IF(OR(N42="-",N43="-"),"-",IF(AND(N42>=1,N43<=1),"🟢",IF(AND(N42>=0.95,N43<=1.05),"🟡","🔴")))
A46: Leyenda: Ingresos 🟢≥100% 🟡95-99% 🔴<95% | Egresos 🟢≤100% 🟡101-105% 🔴>105% | Balance: combina ambos

Sheet PRESUPUESTO
A1: 📊 PRESUPUESTO ANUAL 2026
A2: Cargar los montos previstos para cada mes. El sistema comparará automáticamente con los gastos reales.
A4: CONCEPTO | B4: ENE | C4: FEB | D4: MAR | E4: ABR | F4: MAY | G4: JUN | H4: JUL | I4: AGO | J4: SEP | K4: OCT | L4: NOV | M4: DIC | N4: TOTAL AÑO
A5: ═══ PRESUPUESTO FAMILIA ═══
A6: ► INGRESOS FAMILIA
A7: Salario Marco | B7: 0 | C7: 0 | D7: 0 | E7: 0 | F7: 0 | G7: 0 | H7: 0 | I7: 0 | J7: 0 | K7: 0 | L7: 0 | M7: 0 | N7: =SUM(B7:M7)
A8: Vacaciones Marco | B8: 0 | C8: 0 | D8: 0 | E8: 0 | F8: 0 | G8: 0 | H8: 0 | I8: 0 | J8: 0 | K8: 0 | L8: 0 | M8: 0 | N8: =SUM(B8:M8)
A9: Aguinaldo Marco | B9: 0 | C9: 0 | D9: 0 | E9: 0 | F9: 0 | G9: 0 | H9: 0 | I9: 0 | J9: 0 | K9: 0 | L9: 0 | M9: 0 | N9: =SUM(B9:M9)
A10: Viático Marco | B10: 0 | C10: 0 | D10: 0 | E10: 0 | F10: 0 | G10: 0 | H10: 0 | I10: 0 | J10: 0 | K10: 0 | L10: 0 | M10: 0 | N10: =SUM(B10:M10)
A11: Animador Bíblico | B11: 0 | C11: 0 | D11: 0 | E11: 0 | F11: 0 | G11: 0 | H11: 0 | I11: 0 | J11: 0 | K11: 0 | L11: 0 | M11: 0 | N11: =SUM(B11:M11)
A12: Otros Ingresos Marco | B12: 0 | C12: 0 | D12: 0 | E12: 0 | F12: 0 | G12: 0 | H12: 0 | I12: 0 | J12: 0 | K12: 0 | L12: 0 | M12: 0 | N12: =SUM(B12:M12)
A13: Honorarios Clara | B13: 0 | C13: 0 | D13: 0 | E13: 0 | F13: 0 | G13: 0 | H13: 0 | I13: 0 | J13: 0 | K13: 0 | L13: 0 | M13: 0 | N13: =SUM(B13:M13)
A14: TOTAL INGRESOS FAMILIA | B14: =SUM(B7:B13) | C14: =SUM(C7:C13) | D14: =SUM(D7:D13) | E14: =SUM(E7:E13) | F14: =SUM(F7:F13) | G14: =SUM(G7:G13) | H14: =SUM(H7:H13) | I14: =SUM(I7:I13) | ... N14: =SUM(N7:N13)
A15: ► EGRESOS FAMILIA - GASTOS FIJOS
A16: Salario Lili Doméstico | B16: 0 | C16: 0 | D16: 0 | E16: 0 | F16: 0 | G16: 0 | H16: 0 | I16: 0 | J16: 0 | K16: 0 | L16: 0 | M16: 0 | N16: =SUM(B16:M16)
A17: Salario Laura Doméstico | B17: 0 | C17: 0 | D17: 0 | E17: 0 | F17: 0 | G17: 0 | H17: 0 | I17: 0 | J17: 0 | K17: 0 | L17: 0 | M17: 0 | N17: =SUM(B17:M17)
A18: Escuela Fabián y Brenda | B18: 0 | C18: 0 | D18: 0 | E18: 0 | F18: 0 | G18: 0 | H18: 0 | I18: 0 | J18: 0 | K18: 0 | L18: 0 | M18: 0 | N18: =SUM(B18:M18)
A19: Robótica Niños | B19: 0 | C19: 0 | D19: 0 | E19: 0 | F19: 0 | G19: 0 | H19: 0 | I19: 0 | J19: 0 | K19: 0 | L19: 0 | M19: 0 | N19: =SUM(B19:M19)
A20: ANDE Casa | B20: 0 | C20: 0 | D20: 0 | E20: 0 | F20: 0 | G20: 0 | H20: 0 | I20: 0 | J20: 0 | K20: 0 | L20: 0 | M20: 0 | N20: =SUM(B20:M20)
A21: Expensa Casa | B21: 0 | C21: 0 | D21: 0 | E21: 0 | F21: 0 | G21: 0 | H21: 0 | I21: 0 | J21: 0 | K21: 0 | L21: 0 | M21: 0 | N21: =SUM(B21:M21)
A22: Cajubi Marco | B22: 0 | C22: 0 | D22: 0 | E22: 0 | F22: 0 | G22: 0 | H22: 0 | I22: 0 | J22: 0 | K22: 0 | L22: 0 | M22: 0 | N22: =SUM(B22:M22)
A23: Mutual Marco | B23: 0 | C23: 0 | D23: 0 | E23: 0 | F23: 0 | G23: 0 | H23: 0 | I23: 0 | J23: 0 | K23: 0 | L23: 0 | M23: 0 | N23: =SUM(B23:M23)
A24: Ña Luisa | B24: 0 | C24: 0 | D24: 0 | E24: 0 | F24: 0 | G24: 0 | H24: 0 | I24: 0 | J24: 0 | K24: 0 | L24: 0 | M24: 0 | N24: =SUM(B24:M24)
A25: Seguro Médico Papá y Mamá | B25: 0 | C25: 0 | D25: 0 | E25: 0 | F25: 0 | G25: 0 | H25: 0 | I25: 0 | J25: 0 | K25: 0 | L25: 0 | M25: 0 | N25: =SUM(B25:M25)
A26: ► EGRESOS FAMILIA - CUOTAS Y PRÉSTAMOS
A27: Auto Laura Cuota | B27: 0 | C27: 0 | D27: 0 | E27: 0 | F27: 0 | G27: 0 | H27: 0 | I27: 0 | J27: 0 | K27: 0 | L27: 0 | M27: 0 | N27: =SUM(B27:M27)
A28: Coop. Universitaria Clara | B28: 0 | C28: 0 | D28: 0 | E28: 0 | F28: 0 | G28: 0 | H28: 0 | I28: 0 | J28: 0 | K28: 0 | L28: 0 | M28: 0 | N28: =SUM(B28:M28)
A29: Coomecipar Clara | B29: 0 | C29: 0 | D29: 0 | E29: 0 | F29: 0 | G29: 0 | H29: 0 | I29: 0 | J29: 0 | K29: 0 | L29: 0 | M29: 0 | N29: =SUM(B29:M29)
A30: Tarjeta Cred. Coomecipar | B30: 0 | C30: 0 | D30: 0 | E30: 0 | F30: 0 | G30: 0 | H30: 0 | I30: 0 | J30: 0 | K30: 0 | L30: 0 | M30: 0 | N30: =SUM(B30:M30)
A31: Solar Préstamo 1 | B31: 0 | C31: 0 | D31: 0 | E31: 0 | F31: 0 | G31: 0 | H31: 0 | I31: 0 | J31: 0 | K31: 0 | L31: 0 | M31: 0 | N31: =SUM(B31:M31)
A32: Solar Préstamo 2 | B32: 0 | C32: 0 | D32: 0 | E32: 0 | F32: 0 | G32: 0 | H32: 0 | I32: 0 | J32: 0 | K32: 0 | L32: 0 | M32: 0 | N32: =SUM(B32:M32)
A33: Préstamo Lizzi Sueldos | B33: 0 | C33: 0 | D33: 0 | E33: 0 | F33: 0 | G33: 0 | H33: 0 | I33: 0 | J33: 0 | K33: 0 | L33: 0 | M33: 0 | N33: =SUM(B33:M33)
A34: Show Congelador | B34: 0 | C34: 0 | D34: 0 | E34: 0 | F34: 0 | G34: 0 | H34: 0 | I34: 0 | J34: 0 | K34: 0 | L34: 0 | M34: 0 | N34: =SUM(B34:M34)
A35: Olier Heladera | B35: 0 | C35: 0 | D35: 0 | E35: 0 | F35: 0 | G35: 0 | H35: 0 | I35: 0 | J35: 0 | K35: 0 | L35: 0 | M35: 0 | N35: =SUM(B35:M35)
A36: ► EGRESOS FAMILIA - SUSCRIPCIONES
A37: Giganet | B37: 0 | C37: 0 | D37: 0 | E37: 0 | F37: 0 | G37: 0 | H37: 0 | I37: 0 | J37: 0 | K37: 0 | L37: 0 | M37: 0 | N37: =SUM(B37:M37)
A38: Tigo Internet/Celulares | B38: 0 | C38: 0 | D38: 0 | E38: 0 | F38: 0 | G38: 0 | H38: 0 | I38: 0 | J38: 0 | K38: 0 | L38: 0 | M38: 0 | N38: =SUM(B38:M38)
A39: Tigo Familiar | B39: 0 | C39: 0 | D39: 0 | E39: 0 | F39: 0 | G39: 0 | H39: 0 | I39: 0 | J39: 0 | K39: 0 | L39: 0 | M39: 0 | N39: =SUM(B39:M39)
A40: Google One | B40: 0 | C40: 0 | D40: 0 | E40: 0 | F40: 0 | G40: 0 | H40: 0 | I40: 0 | J40: 0 | K40: 0 | L40: 0 | M40: 0 | N40: =SUM(B40:M40)
A41: ChatGPT | B41: 0 | C41: 0 | D41: 0 | E41: 0 | F41: 0 | G41: 0 | H41: 0 | I41: 0 | J41: 0 | K41: 0 | L41: 0 | M41: 0 | N41: =SUM(B41:M41)
A42: Claude Marco | B42: 0 | C42: 0 | D42: 0 | E42: 0 | F42: 0 | G42: 0 | H42: 0 | I42: 0 | J42: 0 | K42: 0 | L42: 0 | M42: 0 | N42: =SUM(B42:M42)
A43: Claude Clara | B43: 0 | C43: 0 | D43: 0 | E43: 0 | F43: 0 | G43: 0 | H43: 0 | I43: 0 | J43: 0 | K43: 0 | L43: 0 | M43: 0 | N43: =SUM(B43:M43)
A44: iLovePDF | B44: 0 | C44: 0 | D44: 0 | E44: 0 | F44: 0 | G44: 0 | H44: 0 | I44: 0 | J44: 0 | K44: 0 | L44: 0 | M44: 0 | N44: =SUM(B44:M44)
A45: ► EGRESOS FAMILIA - VARIABLES
A46: Alimentación | B46: 0 | C46: 0 | D46: 0 | E46: 0 | F46: 0 | G46: 0 | H46: 0 | I46: 0 | J46: 0 | K46: 0 | L46: 0 | M46: 0 | N46: =SUM(B46:M46)
A47: Combustible | B47: 0 | C47: 0 | D47: 0 | E47: 0 | F47: 0 | G47: 0 | H47: 0 | I47: 0 | J47: 0 | K47: 0 | L47: 0 | M47: 0 | N47: =SUM(B47:M47)
A48: Salud y Medicamentos | B48: 0 | C48: 0 | D48: 0 | E48: 0 | F48: 0 | G48: 0 | H48: 0 | I48: 0 | J48: 0 | K48: 0 | L48: 0 | M48: 0 | N48: =SUM(B48:M48)
A49: Gastos Varios Familia | B49: 0 | C49: 0 | D49: 0 | E49: 0 | F49: 0 | G49: 0 | H49: 0 | I49: 0 | J49: 0 | K49: 0 | L49: 0 | M49: 0 | N49: =SUM(B49:M49)
A50: TOTAL EGRESOS FAMILIA | B50: =SUM(B16:B49) | C50: =SUM(C16:C49) | D50: =SUM(D16:D49) | E50: =SUM(E16:E49) | F50: =SUM(F16:F49) | G50: =SUM(G16:G49) | H50: =SUM(H16:H49) | I50: =SUM(I16:I49) | ... N50: =SUM(N16:N49)
A51: BALANCE FAMILIA (Ingresos - Egresos) | B51: =B14-B50 | C51: =C14-C50 | D51: =D14-D50 | E51: =E14-E50 | F51: =F14-F50 | G51: =G14-G50 | H51: =H14-H50 | I51: =I14-I50 | ... N51: =N14-N50
A53: ═══ PRESUPUESTO NEUROTEA ═══
A54: ► INGRESOS NEUROTEA
A55: Sesiones Individuales | B55: 0 | C55: 0 | D55: 0 | E55: 0 | F55: 0 | G55: 0 | H55: 0 | I55: 0 | J55: 0 | K55: 0 | L55: 0 | M55: 0 | N55: =SUM(B55:M55)
A56: Paquetes de Sesiones | B56: 0 | C56: 0 | D56: 0 | E56: 0 | F56: 0 | G56: 0 | H56: 0 | I56: 0 | J56: 0 | K56: 0 | L56: 0 | M56: 0 | N56: =SUM(B56:M56)
A57: Evaluaciones | B57: 0 | C57: 0 | D57: 0 | E57: 0 | F57: 0 | G57: 0 | H57: 0 | I57: 0 | J57: 0 | K57: 0 | L57: 0 | M57: 0 | N57: =SUM(B57:M57)
A58: Otros Ingresos NT | B58: 0 | C58: 0 | D58: 0 | E58: 0 | F58: 0 | G58: 0 | H58: 0 | I58: 0 | J58: 0 | K58: 0 | L58: 0 | M58: 0 | N58: =SUM(B58:M58)
A59: TOTAL INGRESOS NEUROTEA | B59: =SUM(B55:B58) | C59: =SUM(C55:C58) | D59: =SUM(D55:D58) | E59: =SUM(E55:E58) | F59: =SUM(F55:F58) | G59: =SUM(G55:G58) | H59: =SUM(H55:H58) | I59: =SUM(I55:I58) | ... N59: =SUM(N55:N58)
A60: ► EGRESOS NT - GASTOS FIJOS
A61: Alquiler 1 (Principal) | B61: 0 | C61: 0 | D61: 0 | E61: 0 | F61: 0 | G61: 0 | H61: 0 | I61: 0 | J61: 0 | K61: 0 | L61: 0 | M61: 0 | N61: =SUM(B61:M61)
A62: Alquiler 2 (Secundario) | B62: 0 | C62: 0 | D62: 0 | E62: 0 | F62: 0 | G62: 0 | H62: 0 | I62: 0 | J62: 0 | K62: 0 | L62: 0 | M62: 0 | N62: =SUM(B62:M62)
A63: Limpieza NeuroTEA | B63: 0 | C63: 0 | D63: 0 | E63: 0 | F63: 0 | G63: 0 | H63: 0 | I63: 0 | J63: 0 | K63: 0 | L63: 0 | M63: 0 | N63: =SUM(B63:M63)
A64: ► EGRESOS NT - SUELDOS Y HONORARIOS
A65: Sueldo Aracely | B65: 0 | C65: 0 | D65: 0 | E65: 0 | F65: 0 | G65: 0 | H65: 0 | I65: 0 | J65: 0 | K65: 0 | L65: 0 | M65: 0 | N65: =SUM(B65:M65)
A66: Sueldo Fátima | B66: 0 | C66: 0 | D66: 0 | E66: 0 | F66: 0 | G66: 0 | H66: 0 | I66: 0 | J66: 0 | K66: 0 | L66: 0 | M66: 0 | N66: =SUM(B66:M66)
A67: Honorario Contador | B67: 0 | C67: 0 | D67: 0 | E67: 0 | F67: 0 | G67: 0 | H67: 0 | I67: 0 | J67: 0 | K67: 0 | L67: 0 | M67: 0 | N67: =SUM(B67:M67)
A68: Salario Administrador | B68: 0 | C68: 0 | D68: 0 | E68: 0 | F68: 0 | G68: 0 | H68: 0 | I68: 0 | J68: 0 | K68: 0 | L68: 0 | M68: 0 | N68: =SUM(B68:M68)
A69: Honorario Mant. Sistema | B69: 0 | C69: 0 | D69: 0 | E69: 0 | F69: 0 | G69: 0 | H69: 0 | I69: 0 | J69: 0 | K69: 0 | L69: 0 | M69: 0 | N69: =SUM(B69:M69)
A70: ► EGRESOS NT - TELEFONÍA E INTERNET
A71: Celular Tigo NeuroTEA | B71: 0 | C71: 0 | D71: 0 | E71: 0 | F71: 0 | G71: 0 | H71: 0 | I71: 0 | J71: 0 | K71: 0 | L71: 0 | M71: 0 | N71: =SUM(B71:M71)
A72: Celular Tigo Sistema | B72: 0 | C72: 0 | D72: 0 | E72: 0 | F72: 0 | G72: 0 | H72: 0 | I72: 0 | J72: 0 | K72: 0 | L72: 0 | M72: 0 | N72: =SUM(B72:M72)
A73: WhatsFlow | B73: 0 | C73: 0 | D73: 0 | E73: 0 | F73: 0 | G73: 0 | H73: 0 | I73: 0 | J73: 0 | K73: 0 | L73: 0 | M73: 0 | N73: =SUM(B73:M73)
A74: Internet NeuroTEA | B74: 0 | C74: 0 | D74: 0 | E74: 0 | F74: 0 | G74: 0 | H74: 0 | I74: 0 | J74: 0 | K74: 0 | L74: 0 | M74: 0 | N74: =SUM(B74:M74)
A75: ► EGRESOS NT - IMPUESTOS
A76: IVA | B76: 0 | C76: 0 | D76: 0 | E76: 0 | F76: 0 | G76: 0 | H76: 0 | I76: 0 | J76: 0 | K76: 0 | L76: 0 | M76: 0 | N76: =SUM(B76:M76)
A77: IPS | B77: 0 | C77: 0 | D77: 0 | E77: 0 | F77: 0 | G77: 0 | H77: 0 | I77: 0 | J77: 0 | K77: 0 | L77: 0 | M77: 0 | N77: =SUM(B77:M77)
A78: ► EGRESOS NT - EVENTOS
A79: Día del Niño NT | B79: 0 | C79: 0 | D79: 0 | E79: 0 | F79: 0 | G79: 0 | H79: 0 | I79: 0 | J79: 0 | K79: 0 | L79: 0 | M79: 0 | N79: =SUM(B79:M79)
A80: San Juan NT | B80: 0 | C80: 0 | D80: 0 | E80: 0 | F80: 0 | G80: 0 | H80: 0 | I80: 0 | J80: 0 | K80: 0 | L80: 0 | M80: 0 | N80: =SUM(B80:M80)
A81: Día del Autismo NT | B81: 0 | C81: 0 | D81: 0 | E81: 0 | F81: 0 | G81: 0 | H81: 0 | I81: 0 | J81: 0 | K81: 0 | L81: 0 | M81: 0 | N81: =SUM(B81:M81)
A82: Clausura Padres NT | B82: 0 | C82: 0 | D82: 0 | E82: 0 | F82: 0 | G82: 0 | H82: 0 | I82: 0 | J82: 0 | K82: 0 | L82: 0 | M82: 0 | N82: =SUM(B82:M82)
A83: Navidad Papá Noel NT | B83: 0 | C83: 0 | D83: 0 | E83: 0 | F83: 0 | G83: 0 | H83: 0 | I83: 0 | J83: 0 | K83: 0 | L83: 0 | M83: 0 | N83: =SUM(B83:M83)
A84: Cena Fin de Año NT | B84: 0 | C84: 0 | D84: 0 | E84: 0 | F84: 0 | G84: 0 | H84: 0 | I84: 0 | J84: 0 | K84: 0 | L84: 0 | M84: 0 | N84: =SUM(B84:M84)
A85: ► EGRESOS NT - VARIABLES
A86: Insumos NT | B86: 0 | C86: 0 | D86: 0 | E86: 0 | F86: 0 | G86: 0 | H86: 0 | I86: 0 | J86: 0 | K86: 0 | L86: 0 | M86: 0 | N86: =SUM(B86:M86)
A87: Papelería NT | B87: 0 | C87: 0 | D87: 0 | E87: 0 | F87: 0 | G87: 0 | H87: 0 | I87: 0 | J87: 0 | K87: 0 | L87: 0 | M87: 0 | N87: =SUM(B87:M87)
A88: Mantenimiento NT | B88: 0 | C88: 0 | D88: 0 | E88: 0 | F88: 0 | G88: 0 | H88: 0 | I88: 0 | J88: 0 | K88: 0 | L88: 0 | M88: 0 | N88: =SUM(B88:M88)
A89: Gastos Cursos NT | B89: 0 | C89: 0 | D89: 0 | E89: 0 | F89: 0 | G89: 0 | H89: 0 | I89: 0 | J89: 0 | K89: 0 | L89: 0 | M89: 0 | N89: =SUM(B89:M89)
A90: Gastos Varios NT | B90: 0 | C90: 0 | D90: 0 | E90: 0 | F90: 0 | G90: 0 | H90: 0 | I90: 0 | J90: 0 | K90: 0 | L90: 0 | M90: 0 | N90: =SUM(B90:M90)
A91: TOTAL EGRESOS NEUROTEA | B91: =SUM(B61:B90) | C91: =SUM(C61:C90) | D91: =SUM(D61:D90) | E91: =SUM(E61:E90) | F91: =SUM(F61:F90) | G91: =SUM(G61:G90) | H91: =SUM(H61:H90) | I91: =SUM(I61:I90) | ... N91: =SUM(N61:N90)
A92: BALANCE NEUROTEA (Ingresos - Egresos) | B92: =B59-B91 | C92: =C59-C91 | D92: =D59-D91 | E92: =E59-E91 | F92: =F59-F91 | G92: =G59-G91 | H92: =H59-H91 | I92: =I59-I91 | ... N92: =N59-N91
A94: BALANCE TOTAL CONSOLIDADO | B94: =B51+B92 | C94: =C51+C92 | D94: =D51+D92 | E94: =E51+E92 | F94: =F51+F92 | G94: =G51+G92 | H94: =H51+H92 | I94: =I51+I92 | ... N94: =N51+N92

Sheet DIAGNÓSTICO
A1: 📋 DIAGNÓSTICO INICIAL - Completar una sola vez
A3: Fecha del diagnóstico:
A5: ═══ 💰 CAJA DISPONIBLE HOY ═══
A6: Cuenta | B6: Saldo actual | C6: Notas
A7: Atlas (NeuroTEA) | B7: 0 | C7: Cuenta de la clínica
A8: ITAU Marco | B8: 0 | C8: Cuenta personal Marco
A9: ITAU Clara | B9: 0 | C9: Cuenta personal Clara
A10: UENO Clara | B10: 0 | C10: Cuenta secundaria Clara
A11: Coop. Univ. Marco | B11: 0 | C11: Cooperativa
A12: Caja NT | B12: 0 | C12: Efectivo en la clínica
A13: Efectivo en mano | B13: 0 | C13: Efectivo personal
A14: TOTAL CAJA DISPONIBLE: | B14: =SUM(B7:B13)
A16: ═══ 📉 GASTOS MENSUALES ESENCIALES ═══
A17: Concepto | B17: Monto mensual
A18: Gastos fijos Familia (salarios, escuela, servicios) | B18: 0
A19: Cuotas y préstamos Familia | B19: 0
A20: Gastos fijos NeuroTEA (alquiler, sueldos) | B20: 0
A21: IPS + IVA | B21: 0
A22: Gastos personales mínimos (comida, transporte) | B22: 0
A23: TOTAL GASTOS MENSUALES: | B23: =SUM(B18:B22)
A25: ═══ ⏱️ DÍAS DE OXÍGENO ═══
A26: Gasto diario promedio: | B26: =B23/30
A27: DÍAS QUE PODÉS OPERAR: | B27: =IF(B26=0,0,ROUND(B14/B26,0)) | C27: =IF(B27>=90,"🟢 ESTABLE",IF(B27>=30,"🟡 ALERTA","🔴 EMERGENCIA"))

Sheet DEUDAS
A1: 📋 REGISTRO DE DEUDAS - Ordenar por prioridad de pago
A3: ⚠️ PRIORIDAD: 1=IPS/Impuestos, 2=Salarios, 3=Alquiler/Servicios, 4=Proveedores, 5=Bancos/Tarjetas, 6=Familiares
A5: Prior. | B5: Acreedor | C5: Tipo | D5: Detalle | E5: Monto Total | F5: Cuota Mensual | G5: Cuotas Pend. | H5: Estado
A6: 1 | B6: IPS | C6: Impuesto | D6: Aportes patronales | E6: 0 | F6: 0 | G6: 0 | H6: Pendiente
A7: 1 | B7: SET (IVA) | C7: Impuesto | D7: IVA mensual | E7: 0 | F7: 0 | G7: 0 | H7: Pendiente
A8: 2 | B8: Aracely | C8: Salario | D8: Sueldo secretaria | E8: 0 | F8: 0 | G8: 1 | H8: Pendiente
A9: 2 | B9: Fátima | C9: Salario | D9: Sueldo secretaria | E9: 0 | F9: 0 | G9: 1 | H9: Pendiente
A10: 3 | B10: Alquiler local | C10: Alquiler | D10: Local NeuroTEA | E10: 0 | F10: 0 | G10: 1 | H10: Pendiente
A11: 4 | B11: Contador | C11: Servicio | D11: Honorarios | E11: 0 | F11: 0 | G11: 0 | H11: Pendiente
A12: 5 | B12: Solar Préstamo 1 | C12: Préstamo | E12: 0 | F12: 0 | G12: 0 | H12: Pendiente
A13: 5 | B13: Solar Préstamo 2 | C13: Préstamo | E13: 0 | F13: 0 | G13: 0 | H13: Pendiente
A14: 5 | B14: Coop. Universitaria | C14: Préstamo | E14: 0 | F14: 0 | G14: 0 | H14: Pendiente
A15: 5 | B15: Coomecipar Clara | C15: Préstamo | E15: 0 | F15: 0 | G15: 0 | H15: Pendiente
A16: 5 | B16: Tarjeta Coomecipar | C16: Tarjeta | E16: 0 | F16: 0 | G16: 0 | H16: Pendiente
A17: 5 | B17: Auto Laura | C17: Préstamo | D17: Cuota vehículo | E17: 0 | F17: 0 | G17: 0 | H17: Pendiente
A18: 6 | B18: Préstamo Lizzi | C18: Familiar | D18: Sueldos | E18: 0 | F18: 0 | G18: 0 | H18: Pendiente
A19: 6 | B19: Show Congelador | C19: Familiar | E19: 0 | F19: 0 | G19: 0 | H19: Pendiente
A20: 6 | B20: Olier Heladera | C20: Familiar | E20: 0 | F20: 0 | G20: 0 | H20: Pendiente
A28: TOTALES: | E28: =SUM(E6:E25) | F28: =SUM(F6:F25)
A30: ═══ 📊 RESUMEN POR PRIORIDAD ═══
A31: Prioridad 1 (IPS/Impuestos) | B31: =SUMIF(A6:A25,1,F6:F25) | C31: 🔴 Pagar PRIMERO
A32: Prioridad 2 (Salarios) | B32: =SUMIF(A6:A25,2,F6:F25) | C32: 🔴 Pagar SEGUNDO
A33: Prioridad 3 (Alquiler/Servicios) | B33: =SUMIF(A6:A25,3,F6:F25) | C33: 🟡 Pagar TERCERO
A34: Prioridad 4 (Proveedores) | B34: =SUMIF(A6:A25,4,F6:F25) | C34: 🟡 Negociar plazos
A35: Prioridad 5 (Bancos/Tarjetas) | B35: =SUMIF(A6:A25,5,F6:F25) | C35: 🟢 Refinanciar si es necesario
A36: Prioridad 6 (Familiares) | B36: =SUMIF(A6:A25,6,F6:F25) | C36: 🟢 Más flexible

Sheet Configuración
A1: ⚙️ CONFIGURACIÓN
A3: Cat. Familiar | B3: Cat. NeuroTEA | C3: Eventos NT | D3: Eventos NT | E3: Cat. Ingresos | F3: Tipos | G3: Estados | H3: Cuentas
A4: Combustible | B4: Insumos NT | C4: Día del Niño NT | D4: Atlas (NeuroTEA) | E4: Salario Mensual | F4: Ingreso NT | G4: Ninguno | H4: Atlas (NeuroTEA)
A5: Supermercado | B5: Papelería NT | C5: San Juan NT | D5: ITAU Marco | E5: Vacaciones | F5: Ingreso Marco | G5: Pendiente | H5: ITAU Marco
A6: Farmacia | B6: Mantenimiento NT | C6: Día del Autismo NT | D6: ITAU Clara | E6: Aguinaldo | F6: Ingreso Clara | G6: Pagado | H6: ITAU Clara
A7: Recreación | B7: Gastos Cursos NT | C7: Clausura Padres NT | D7: UENO Clara | E7: Viático | F7: Egreso NT | G7: Cancelado | H7: UENO Clara
A8: Gastos Varios | B8: Gastos Varios NT | C8: Navidad Papá Noel NT | D8: Coop. Univ. Marco | E8: Animador Bíblico | F8: Egreso Familiar | H8: Coop. Univ. Marco
A9: Reserva Fam 1 | B9: Reserva NT 1 | C9: Cena Fin de Año NT | D9: Efectivo | E9: Otros Ocasionales | F9: Préstamo NT → Familia | H9: Efectivo
A10: Reserva Fam 2 | B10: Reserva NT 2 | C10: Evento Reserva 1 | D10: Caja NT | E10: Honorarios Diarios | F10: Devolución Familia → NT | H10: Caja NT
A11: Reserva Fam 3 | B11: Reserva NT 3 | C11: Evento Reserva 2 | E11: Sesiones Terapia
A14: 📌 Para agregar categoría, renombrá una 'Reserva'.
A16: 📊 PARÁMETROS DE SALUD FINANCIERA NT
A18: Parámetro | B18: Valor | C18: Descripción
A19: % Ganancia Objetivo | B19: 0.07 | C19: ✏️ Editar para ajustar umbrales
A20: % Gastos Máximo | B20: =1-B19 | C20: Calculado automáticamente
A22: Subdivisión de la Ganancia:
A23: Compensación dueño | B23: =B19/4 | C23: Utilidad adicional al sueldo fijo
A24: Fondo emergencia | B24: =B19/4 | C24: Reserva para imprevistos
A25: Inversión | B25: =B19/4 | C25: Crecimiento y mejoras
A26: Imprevistos/Desvío | B26: =B19/4 | C26: Colchón adicional
A28: Umbrales de Diagnóstico:
A29: 🟢 Clínica Sana | B29: =B20 | C29: Gastos ≤ este valor
A30: 🟡 Revisar Gastos | B30: 100% | C30: Gastos entre verde y 100%
A31: 🔴 Situación Crítica | B31: >100% | C31: Pérdida operativa

Sheet Ing-Egr Enero 2026
A1: 📋 REGISTRO DE MOVIMIENTOS - ENERO 2026
A3: Fecha | B3: Tipo | C3: Categoría | D3: Descripción | E3: Ingreso | F3: Egreso | G3: Cuenta | H3: Notas
A104: TOTALES | E104: =SUM(E4:E103) | F104: =SUM(F4:F103)
A106: 📊 RESUMEN DEL MES
A107: INGRESOS: | C107: =SUMIF(B4:B103,"Ingreso NT",E4:E103)
A108: Ingreso NT: | C108: =SUMIF(B4:B103,"Ingreso NT",E4:E103)
A109: Ingreso Marco: | C109: =SUMIF(B4:B103,"Ingreso Marco",E4:E103)
A110: Ingreso Clara: | C110: =SUMIF(B4:B103,"Ingreso Clara",E4:E103)
A111: Devolución Fam → NT: | C111: =SUMIF(B4:B103,"Devolución Familia → NT",E4:E103)
A112: TOTAL INGRESOS: | C112: =SUM(C108:C111)
A113: EGRESOS:
A114: EGRESOS: | C114: =SUMIF(B4:B103,"Egreso NT",F4:F103)
A115: Egreso NT: | C115: =SUMIF(B4:B103,"Egreso NT",F4:F103)
A116: Egreso Familiar: | C116: =SUMIF(B4:B103,"Egreso Familiar",F4:F103)
A117: Préstamo NT → Fam: | C117: =SUMIF(B4:B103,"Préstamo NT → Familia",F4:F103)
A118: TOTAL EGRESOS: | C118: =SUM(C115:C117)
A120: SALDO PRÉSTAMO NT → FAM: | C120: =C117-C111
A121: (Prestado - Devuelto)

Sheet Enero 2026
A1: 📊 CONTROL FINANCIERO - ENERO 2026
A3: TOTAL INGRESOS | D3: GASTOS PAGADOS | G3: GASTOS PENDIENTES | J3: BALANCE
A4: =D26+J12 | D4: =D65+I58 | G4: =D66+I59 | J4: =A4-D4-G4
A6: ⚠️ PRÉSTAMO NT → FAMILIA | D6: =SUMIF('Ing-Egr Enero 2026'!B4:B103,"Préstamo NT → Familia",'Ing-Egr Enero 2026'!F4:F103)-SUMIF('Ing-Egr Enero 2026'!B4:B103,"Devolución Familia → NT",'Ing-Egr Enero 2026'!E4:E103) | F6: Estado: | G6: =IF(D6=0,"🟢 SANO","🔴 FUGA") | I6: (Ideal = 0)
A8: 💵 INGRESOS FAMILIA | G8: 💵 INGRESOS NEUROTEA
A9: MARCO ITAIPU | C9: Fecha | D9: Monto | G9: Ingreso del Mes | J9: Monto
A10: Salario Mensual | D10: =SUMIFS('Ing-Egr Enero 2026'!E4:E103,'Ing-Egr Enero 2026'!B4:B103,"Ingreso Marco",'Ing-Egr Enero 2026'!C4:C103,A10) | G10: (Suma desde pestaña Ing-Egr Enero) | J10: =SUMIF('Ing-Egr Enero 2026'!B4:B103,"Ingreso NT",'Ing-Egr Enero 2026'!E4:E103)
A11: Vacaciones | D11: =SUMIFS('Ing-Egr Enero 2026'!E4:E103,'Ing-Egr Enero 2026'!B4:B103,"Ingreso Marco",'Ing-Egr Enero 2026'!C4:C103,A11)
A12: Aguinaldo | D12: =SUMIFS('Ing-Egr Enero 2026'!E4:E103,'Ing-Egr Enero 2026'!B4:B103,"Ingreso Marco",'Ing-Egr Enero 2026'!C4:C103,A12) | G12: ═══ TOTAL INGRESOS NT ═══ | J12: =J10
A13: Viático | D13: =SUMIFS('Ing-Egr Enero 2026'!E4:E103,'Ing-Egr Enero 2026'!B4:B103,"Ingreso Marco",'Ing-Egr Enero 2026'!C4:C103,A13)
A14: Animador Bíblico | D14: =SUMIFS('Ing-Egr Enero 2026'!E4:E103,'Ing-Egr Enero 2026'!B4:B103,"Ingreso Marco",'Ing-Egr Enero 2026'!C4:C103,A14)
A15: Otros Ocasionales | D15: =SUMIFS('Ing-Egr Enero 2026'!E4:E103,'Ing-Egr Enero 2026'!B4:B103,"Ingreso Marco",'Ing-Egr Enero 2026'!C4:C103,A15) | I15: =J12
A16: TOTAL MARCO | D16: =SUM(D10:D15)
A17: CLARA | C17: Fecha | D17: Monto
A18: Honorarios Diarios | D18: =SUMIF('Ing-Egr Enero 2026'!B4:B103,"Ingreso Clara",'Ing-Egr Enero 2026'!E4:E103)
A19: TOTAL CLARA | D19: =D18
A20: DESDE NEUROTEA | D20: Monto
A21: Salario Admin Marco | D21: 0
A22: Ganancia NT → Familia | D22: 0
A23: Préstamo NT (automático) | D23: =D6
A24: TOTAL DESDE NT | D24: =SUM(D21:D23)
A26: ═══ TOTAL INGRESOS FAMILIA ═══ | D26: =D16+D19+D24
A28: 📉 GASTOS FAMILIARES | G28: 📉 GASTOS NEUROTEA
A29: Detalle | B29: Estado | C29: Monto | D29: Venc. | G29: Detalle | H29: Estado | I29: Monto | J29: Venc.
A30: ► GASTOS FIJOS ✏️ | G30: ► GASTOS FIJOS ✏️
A31: Salario Lili Doméstico | B31: Ninguno | G31: Alquiler 1 (Principal) | H31: Ninguno | I31: 0
A32: Salario Laura Doméstico | B32: Ninguno | G32: Alquiler 2 (Secundario) | H32: Ninguno | I32: 0
A33: Escuela Fabián y Brenda | B33: Ninguno | G33: Limpieza NeuroTEA | H33: Ninguno | I33: 0
A34: Robótica Niños | B34: Ninguno | G34: ► SUELDOS Y HONORARIOS ✏️
A35: ANDE Casa | B35: Ninguno | G35: Sueldo Aracely | H35: Ninguno | I35: 0
A36: Expensa Casa | B36: Ninguno | G36: Sueldo Fátima | H36: Ninguno | I36: 0
A37: Cajubi Marco | B37: Ninguno | G37: Honorario Contador | H37: Ninguno | I37: 0
A38: Mutual Marco | B38: Ninguno | G38: Salario Administrador | H38: Ninguno | I38: 0
A39: Ña Luisa | B39: Ninguno | G39: Honorario Mant. Sistema | H39: Ninguno | I39: 0
A40: Seguro Médico Papá y Mamá | B40: Ninguno | G40: ► TELEFONÍA E INTERNET ✏️
A41: ► CUOTAS Y PRÉSTAMOS ✏️ | G41: Celular Tigo NeuroTEA | H41: Ninguno | I41: 0
A42: Auto Laura Cuota | B42: Ninguno | G42: Celular Tigo Sistema | H42: Ninguno | I42: 0
A43: Coop. Universitaria Clara | B43: Ninguno | G43: WhatsFlow | H43: Ninguno | I43: 0
A44: Coomecipar Clara | B44: Ninguno | G44: Internet NeuroTEA | H44: Ninguno | I44: 0
A45: Tarjeta Cred. Coomecipar | B45: Ninguno | G45: ► IMPUESTOS ✏️
A46: Solar Préstamo 1 | B46: Ninguno | G46: IVA | H46: Ninguno | I46: 0
A47: Solar Préstamo 2 | B47: Ninguno | G47: ► EVENTOS NT ✏️
A48: Préstamo Lizzi Sueldos | B48: Ninguno | G48: Día del Niño NT | H48: Ninguno | I48: 0
A49: Show Congelador | B49: Ninguno | G49: San Juan NT | H49: Ninguno | I49: 0
A50: Olier Heladera | B50: Ninguno | G50: Día del Autismo NT | H50: Ninguno | I50: 0
A51: ► SUSCRIPCIONES E INTERNET ✏️ | G51: Clausura Padres NT | H51: Ninguno | I51: 0
A52: Giganet | B52: Ninguno | G52: Navidad Papá Noel NT | H52: Ninguno | I52: 0
A53: Tigo Internet/Celulares | B53: Ninguno | G53: Cena Fin de Año NT | H53: Ninguno | I53: 0
A54: Tigo Familiar | B54: Ninguno | G54: ► GASTOS VARIABLES NT 🔗
A55: Google One | B55: Ninguno | G55: Insumos NT | H55: Ninguno | I55: =SUMIFS('Ing-Egr Enero 2026'!F4:F103,'Ing-Egr Enero 2026'!B4:B103,"Egreso NT",'Ing-Egr Enero 2026'!C4:C103,G55)
A56: ChatGPT | B56: Ninguno | G56: Papelería NT | H56: Ninguno | I56: =SUMIFS('Ing-Egr Enero 2026'!F4:F103,'Ing-Egr Enero 2026'!B4:B103,"Egreso NT",'Ing-Egr Enero 2026'!C4:C103,G56)
A57: Claude Marco | B57: Ninguno | G57: Mantenimiento NT | H57: Ninguno | I57: =SUMIFS('Ing-Egr Enero 2026'!F4:F103,'Ing-Egr Enero 2026'!B4:B103,"Egreso NT",'Ing-Egr Enero 2026'!C4:C103,G57)
A58: Claude Clara | B58: Ninguno | G58: Gastos Cursos NT | H58: Ninguno | I58: =SUMIFS('Ing-Egr Enero 2026'!F4:F103,'Ing-Egr Enero 2026'!B4:B103,"Egreso NT",'Ing-Egr Enero 2026'!C4:C103,G58)
A59: iLovePDF | B59: Ninguno | G59: Gastos Varios NT | H59: Ninguno | I59: =SUMIFS('Ing-Egr Enero 2026'!F4:F103,'Ing-Egr Enero 2026'!B4:B103,"Egreso NT",'Ing-Egr Enero 2026'!C4:C103,G59)
A60: Scribd | B60: Ninguno | G60: Reserva NT 1 | H60: Ninguno | I60: =SUMIFS('Ing-Egr Enero 2026'!F4:F103,'Ing-Egr Enero 2026'!B4:B103,"Egreso NT",'Ing-Egr Enero 2026'!C4:C103,G60)
A61: Netflix | B61: Ninguno | G61: Reserva NT 2 | H61: Ninguno | I61: =SUMIFS('Ing-Egr Enero 2026'!F4:F103,'Ing-Egr Enero 2026'!B4:B103,"Egreso NT",'Ing-Egr Enero 2026'!C4:C103,G61)
A62: ► GASTOS VARIABLES 🔗 | G62: Reserva NT 3 | H62: Ninguno | I62: =SUMIFS('Ing-Egr Enero 2026'!F4:F103,'Ing-Egr Enero 2026'!B4:B103,"Egreso NT",'Ing-Egr Enero 2026'!C4:C103,G62)
A63: Combustible | B63: Ninguno | C63: =SUMIFS('Ing-Egr Enero 2026'!F4:F103,'Ing-Egr Enero 2026'!B4:B103,"Egreso Familiar",'Ing-Egr Enero 2026'!C4:C103,A63)
A64: Supermercado | B64: Ninguno | C64: =SUMIFS('Ing-Egr Enero 2026'!F4:F103,'Ing-Egr Enero 2026'!B4:B103,"Egreso Familiar",'Ing-Egr Enero 2026'!C4:C103,A64) | G64: TOTAL NT PAGADOS | I64: =SUMIF(H30:H62,"Pagado",I30:I62)
A65: Farmacia | B65: Ninguno | C65: =SUMIFS('Ing-Egr Enero 2026'!F4:F103,'Ing-Egr Enero 2026'!B4:B103,"Egreso Familiar",'Ing-Egr Enero 2026'!C4:C103,A65) | D65: =C72 | G65: TOTAL NT PENDIENTES | I65: =SUMIF(H30:H62,"Pendiente",I30:I62)
A66: Recreación | B66: Ninguno | C66: =SUMIFS('Ing-Egr Enero 2026'!F4:F103,'Ing-Egr Enero 2026'!B4:B103,"Egreso Familiar",'Ing-Egr Enero 2026'!C4:C103,A66) | D66: =C73
A67: Gastos Varios | B67: Ninguno | C67: =SUMIFS('Ing-Egr Enero 2026'!F4:F103,'Ing-Egr Enero 2026'!B4:B103,"Egreso Familiar",'Ing-Egr Enero 2026'!C4:C103,A67) | G67: 📊 SALUD FINANCIERA NEUROTEA
A68: Reserva Fam 1 | B68: Ninguno | C68: =SUMIFS('Ing-Egr Enero 2026'!F4:F103,'Ing-Egr Enero 2026'!B4:B103,"Egreso Familiar",'Ing-Egr Enero 2026'!C4:C103,A68) | G68: Concepto | H68: % Ideal | I68: Monto Ideal | J68: Monto Real | K68: Estado
A69: Reserva Fam 2 | B69: Ninguno | C69: =SUMIFS('Ing-Egr Enero 2026'!F4:F103,'Ing-Egr Enero 2026'!B4:B103,"Egreso Familiar",'Ing-Egr Enero 2026'!C4:C103,A69) | G69: Gastos Operativos (máx 75%) | H69: 0.75 | I69: =J12*0.75 | J69: =I64+I65 | K69: =IF(J12=0,"-",IF(J69/J12<=0.75,"🟢 OK",IF(J69/J12<=0.9,"🟡 PRECAUCIÓN","🔴 ALARMA")))
A70: Reserva Fam 3 | B70: Ninguno | C70: =SUMIFS('Ing-Egr Enero 2026'!F4:F103,'Ing-Egr Enero 2026'!B4:B103,"Egreso Familiar",'Ing-Egr Enero 2026'!C4:C103,A70) | G70: Ganancia (10%) | H70: 0.1 | I70: =J12*0.1 | J70: =D22 | K70: =IF(J70>=I70,"🟢","🔴")
G71: Inversiones (5%) | H71: 0.05 | I71: =J12*0.05 | J71: 0 | K71: =IF(J71>=I71,"🟢","🔴")
A72: TOTAL FAM. PAGADOS | C72: =SUMIF(B30:B70,"Pagado",C30:C70) | G72: Imprevistos (5%) | H72: 0.05 | I72: =J12*0.05 | J72: 0 | K72: =IF(J72>=I72,"🟢","🔴")
A73: TOTAL FAM. PENDIENTES | C73: =SUMIF(B30:B70,"Pendiente",C30:C70) | G73: Desvío Imprevisto (5%) | H73: 0.05 | I73: =J12*0.05 | J73: 0 | K73: =IF(J73>=I73,"🟢","🔴")
G74: TOTAL | H74: =SUM(H69:H73) | I74: =SUM(I69:I73) | J74: =SUM(J69:J73)
G76: % GASTOS SOBRE INGRESO: | J76: =IF(J12=0,0,J69/J12)
G77: DIAGNÓSTICO: | J77: =IF(J12=0,"Sin datos",IF(J69/J12<=0.75,"🟢 CLÍNICA SANA",IF(J69/J12<=0.9,"🟡 REVISAR GASTOS","🔴 SITUACIÓN CRÍTICA")))

Sheet Ing-Egr Febrero 2026
A1: 📋 REGISTRO DE MOVIMIENTOS - FEBRERO 2026
A3: Fecha | B3: Tipo | C3: Categoría | D3: Descripción | E3: Ingreso | F3: Egreso | G3: Cuenta | H3: Notas
A104: TOTALES | E104: =SUM(E4:E103) | F104: =SUM(F4:F103)
A106: 📊 RESUMEN DEL MES
A107: INGRESOS: | C107: =SUMIF(B4:B103,"Ingreso NT",E4:E103)
A108: Ingreso NT: | C108: =SUMIF(B4:B103,"Ingreso NT",E4:E103)
A109: Ingreso Marco: | C109: =SUMIF(B4:B103,"Ingreso Marco",E4:E103)
A110: Ingreso Clara: | C110: =SUMIF(B4:B103,"Ingreso Clara",E4:E103)
A111: Devolución Fam → NT: | C111: =SUMIF(B4:B103,"Devolución Familia → NT",E4:E103)
A112: TOTAL INGRESOS: | C112: =SUM(C108:C111)
A113: EGRESOS:
A114: EGRESOS: | C114: =SUMIF(B4:B103,"Egreso NT",F4:F103)
A115: Egreso NT: | C115: =SUMIF(B4:B103,"Egreso NT",F4:F103)
A116: Egreso Familiar: | C116: =SUMIF(B4:B103,"Egreso Familiar",F4:F103)
A117: Préstamo NT → Fam: | C117: =SUMIF(B4:B103,"Préstamo NT → Familia",F4:F103)
A118: TOTAL EGRESOS: | C118: =SUM(C115:C117)
A120: SALDO PRÉSTAMO NT → FAM: | C120: =C117-C111
A121: (Prestado - Devuelto)

Sheet Febrero 2026
A1: 📊 CONTROL FINANCIERO - FEBRERO 2026
A3: TOTAL INGRESOS | D3: GASTOS PAGADOS | G3: GASTOS PENDIENTES | J3: BALANCE
A4: =D26+J12 | D4: =D65+I58 | G4: =D66+I59 | J4: =A4-D4-G4
A6: ⚠️ PRÉSTAMO NT → FAMILIA | D6: =SUMIF('Ing-Egr Febrero 2026'!B4:B103,"Préstamo NT → Familia",'Ing-Egr Febrero 2026'!F4:F103)-SUMIF('Ing-Egr Febrero 2026'!B4:B103,"Devolución Familia → NT",'Ing-Egr Febrero 2026'!E4:E103) | F6: Estado: | G6: =IF(D6=0,"🟢 SANO","🔴 FUGA") | I6: (Ideal = 0)
A8: 💵 INGRESOS FAMILIA | G8: 💵 INGRESOS NEUROTEA
A9: MARCO ITAIPU | C9: Fecha | D9: Monto | G9: Ingreso del Mes | J9: Monto
A10: Salario Mensual | D10: =SUMIFS('Ing-Egr Febrero 2026'!E4:E103,'Ing-Egr Febrero 2026'!B4:B103,"Ingreso Marco",'Ing-Egr Febrero 2026'!C4:C103,A10) | G10: (Suma desde pestaña Ing-Egr Febrero) | J10: =SUMIF('Ing-Egr Febrero 2026'!B4:B103,"Ingreso NT",'Ing-Egr Febrero 2026'!E4:E103)
A11: Vacaciones | D11: =SUMIFS('Ing-Egr Febrero 2026'!E4:E103,'Ing-Egr Febrero 2026'!B4:B103,"Ingreso Marco",'Ing-Egr Febrero 2026'!C4:C103,A11)
A12: Aguinaldo | D12: =SUMIFS('Ing-Egr Febrero 2026'!E4:E103,'Ing-Egr Febrero 2026'!B4:B103,"Ingreso Marco",'Ing-Egr Febrero 2026'!C4:C103,A12) | G12: ═══ TOTAL INGRESOS NT ═══ | J12: =J10
A13: Viático | D13: =SUMIFS('Ing-Egr Febrero 2026'!E4:E103,'Ing-Egr Febrero 2026'!B4:B103,"Ingreso Marco",'Ing-Egr Febrero 2026'!C4:C103,A13)
A14: Animador Bíblico | D14: =SUMIFS('Ing-Egr Febrero 2026'!E4:E103,'Ing-Egr Febrero 2026'!B4:B103,"Ingreso Marco",'Ing-Egr Febrero 2026'!C4:C103,A14)
A15: Otros Ocasionales | D15: =SUMIFS('Ing-Egr Febrero 2026'!E4:E103,'Ing-Egr Febrero 2026'!B4:B103,"Ingreso Marco",'Ing-Egr Febrero 2026'!C4:C103,A15) | I15: =J12
A16: TOTAL MARCO | D16: =SUM(D10:D15)
A17: CLARA | C17: Fecha | D17: Monto
A18: Honorarios Diarios | D18: =SUMIF('Ing-Egr Febrero 2026'!B4:B103,"Ingreso Clara",'Ing-Egr Febrero 2026'!E4:E103)
A19: TOTAL CLARA | D19: =D18
A20: DESDE NEUROTEA | D20: Monto
A21: Salario Admin Marco | D21: 0
A22: Ganancia NT → Familia | D22: 0
A23: Préstamo NT (automático) | D23: =D6
A24: TOTAL DESDE NT | D24: =SUM(D21:D23)
A26: ═══ TOTAL INGRESOS FAMILIA ═══ | D26: =D16+D19+D24
A28: 📉 GASTOS FAMILIARES | G28: 📉 GASTOS NEUROTEA
A29: Detalle | B29: Estado | C29: Monto | D29: Venc. | G29: Detalle | H29: Estado | I29: Monto | J29: Venc.
A30: ► GASTOS FIJOS ✏️ | G30: ► GASTOS FIJOS ✏️
A31: Salario Lili Doméstico | B31: Ninguno | G31: Alquiler 1 (Principal) | H31: Ninguno | I31: 0
A32: Salario Laura Doméstico | B32: Ninguno | G32: Alquiler 2 (Secundario) | H32: Ninguno | I32: 0
A33: Escuela Fabián y Brenda | B33: Ninguno | G33: Limpieza NeuroTEA | H33: Ninguno | I33: 0
A34: Robótica Niños | B34: Ninguno | G34: ► SUELDOS Y HONORARIOS ✏️
A35: ANDE Casa | B35: Ninguno | G35: Sueldo Aracely | H35: Ninguno | I35: 0
A36: Expensa Casa | B36: Ninguno | G36: Sueldo Fátima | H36: Ninguno | I36: 0
A37: Cajubi Marco | B37: Ninguno | G37: Honorario Contador | H37: Ninguno | I37: 0
A38: Mutual Marco | B38: Ninguno | G38: Salario Administrador | H38: Ninguno | I38: 0
A39: Ña Luisa | B39: Ninguno | G39: Honorario Mant. Sistema | H39: Ninguno | I39: 0
A40: Seguro Médico Papá y Mamá | B40: Ninguno | G40: ► TELEFONÍA E INTERNET ✏️
A41: ► CUOTAS Y PRÉSTAMOS ✏️ | G41: Celular Tigo NeuroTEA | H41: Ninguno | I41: 0
A42: Auto Laura Cuota | B42: Ninguno | G42: Celular Tigo Sistema | H42: Ninguno | I42: 0
A43: Coop. Universitaria Clara | B43: Ninguno | G43: WhatsFlow | H43: Ninguno | I43: 0
A44: Coomecipar Clara | B44: Ninguno | G44: Internet NeuroTEA | H44: Ninguno | I44: 0
A45: Tarjeta Cred. Coomecipar | B45: Ninguno | G45: ► IMPUESTOS ✏️
A46: Solar Préstamo 1 | B46: Ninguno | G46: IVA | H46: Ninguno | I46: 0
A47: Solar Préstamo 2 | B47: Ninguno | G47: ► EVENTOS NT ✏️
A48: Préstamo Lizzi Sueldos | B48: Ninguno | G48: Día del Niño NT | H48: Ninguno | I48: 0
A49: Show Congelador | B49: Ninguno | G49: San Juan NT | H49: Ninguno | I49: 0
A50: Olier Heladera | B50: Ninguno | G50: Día del Autismo NT | H50: Ninguno | I50: 0
A51: ► SUSCRIPCIONES E INTERNET ✏️ | G51: Clausura Padres NT | H51: Ninguno | I51: 0
A52: Giganet | B52: Ninguno | G52: Navidad Papá Noel NT | H52: Ninguno | I52: 0
A53: Tigo Internet/Celulares | B53: Ninguno | G53: Cena Fin de Año NT | H53: Ninguno | I53: 0
A54: Tigo Familiar | B54: Ninguno | G54: ► GASTOS VARIABLES NT 🔗
A55: Google One | B55: Ninguno | G55: Insumos NT | H55: Ninguno | I55: =SUMIFS('Ing-Egr Febrero 2026'!F4:F103,'Ing-Egr Febrero 2026'!B4:B103,"Egreso NT",'Ing-Egr Febrero 2026'!C4:C103,G55)
A56: ChatGPT | B56: Ninguno | G56: Papelería NT | H56: Ninguno | I56: =SUMIFS('Ing-Egr Febrero 2026'!F4:F103,'Ing-Egr Febrero 2026'!B4:B103,"Egreso NT",'Ing-Egr Febrero 2026'!C4:C103,G56)
A57: Claude Marco | B57: Ninguno | G57: Mantenimiento NT | H57: Ninguno | I57: =SUMIFS('Ing-Egr Febrero 2026'!F4:F103,'Ing-Egr Febrero 2026'!B4:B103,"Egreso NT",'Ing-Egr Febrero 2026'!C4:C103,G57)
A58: Claude Clara | B58: Ninguno | G58: Gastos Cursos NT | H58: Ninguno | I58: =SUMIFS('Ing-Egr Febrero 2026'!F4:F103,'Ing-Egr Febrero 2026'!B4:B103,"Egreso NT",'Ing-Egr Febrero 2026'!C4:C103,G58)
A59: iLovePDF | B59: Ninguno | G59: Gastos Varios NT | H59: Ninguno | I59: =SUMIFS('Ing-Egr Febrero 2026'!F4:F103,'Ing-Egr Febrero 2026'!B4:B103,"Egreso NT",'Ing-Egr Febrero 2026'!C4:C103,G59)
A60: Scribd | B60: Ninguno | G60: Reserva NT 1 | H60: Ninguno | I60: =SUMIFS('Ing-Egr Febrero 2026'!F4:F103,'Ing-Egr Febrero 2026'!B4:B103,"Egreso NT",'Ing-Egr Febrero 2026'!C4:C103,G60)
A61: Netflix | B61: Ninguno | G61: Reserva NT 2 | H61: Ninguno | I61: =SUMIFS('Ing-Egr Febrero 2026'!F4:F103,'Ing-Egr Febrero 2026'!B4:B103,"Egreso NT",'Ing-Egr Febrero 2026'!C4:C103,G61)
A62: ► GASTOS VARIABLES 🔗 | G62: Reserva NT 3 | H62: Ninguno | I62: =SUMIFS('Ing-Egr Febrero 2026'!F4:F103,'Ing-Egr Febrero 2026'!B4:B103,"Egreso NT",'Ing-Egr Febrero 2026'!C4:C103,G62)
A63: Combustible | B63: Ninguno | C63: =SUMIFS('Ing-Egr Febrero 2026'!F4:F103,'Ing-Egr Febrero 2026'!B4:B103,"Egreso Familiar",'Ing-Egr Febrero 2026'!C4:C103,A63)
A64: Supermercado | B64: Ninguno | C64: =SUMIFS('Ing-Egr Febrero 2026'!F4:F103,'Ing-Egr Febrero 2026'!B4:B103,"Egreso Familiar",'Ing-Egr Febrero 2026'!C4:C103,A64) | G64: TOTAL NT PAGADOS | I64: =SUMIF(H30:H62,"Pagado",I30:I62)
A65: Farmacia | B65: Ninguno | C65: =SUMIFS('Ing-Egr Febrero 2026'!F4:F103,'Ing-Egr Febrero 2026'!B4:B103,"Egreso Familiar",'Ing-Egr Febrero 2026'!C4:C103,A65) | D65: =C72 | G65: TOTAL NT PENDIENTES | I65: =SUMIF(H30:H62,"Pendiente",I30:I62)
A66: Recreación | B66: Ninguno | C66: =SUMIFS('Ing-Egr Febrero 2026'!F4:F103,'Ing-Egr Febrero 2026'!B4:B103,"Egreso Familiar",'Ing-Egr Febrero 2026'!C4:C103,A66) | D66: =C73
A67: Gastos Varios | B67: Ninguno | C67: =SUMIFS('Ing-Egr Febrero 2026'!F4:F103,'Ing-Egr Febrero 2026'!B4:B103,"Egreso Familiar",'Ing-Egr Febrero 2026'!C4:C103,A67) | G67: 📊 SALUD FINANCIERA NEUROTEA
A68: Reserva Fam 1 | B68: Ninguno | C68: =SUMIFS('Ing-Egr Febrero 2026'!F4:F103,'Ing-Egr Febrero 2026'!B4:B103,"Egreso Familiar",'Ing-Egr Febrero 2026'!C4:C103,A68) | G68: Concepto | H68: % Ideal | I68: Monto Ideal | J68: Monto Real | K68: Estado
A69: Reserva Fam 2 | B69: Ninguno | C69: =SUMIFS('Ing-Egr Febrero 2026'!F4:F103,'Ing-Egr Febrero 2026'!B4:B103,"Egreso Familiar",'Ing-Egr Febrero 2026'!C4:C103,A69) | G69: Gastos Operativos (máx 75%) | H69: 0.75 | I69: =J12*0.75 | J69: =I64+I65 | K69: =IF(J12=0,"-",IF(J69/J12<=0.75,"🟢 OK",IF(J69/J12<=0.9,"🟡 PRECAUCIÓN","🔴 ALARMA")))
A70: Reserva Fam 3 | B70: Ninguno | C70: =SUMIFS('Ing-Egr Febrero 2026'!F4:F103,'Ing-Egr Febrero 2026'!B4:B103,"Egreso Familiar",'Ing-Egr Febrero 2026'!C4:C103,A70) | G70: Ganancia (10%) | H70: 0.1 | I70: =J12*0.1 | J70: =D22 | K70: =IF(J70>=I70,"🟢","🔴")
G71: Inversiones (5%) | H71: 0.05 | I71: =J12*0.05 | J71: 0 | K71: =IF(J71>=I71,"🟢","🔴")
A72: TOTAL FAM. PAGADOS | C72: =SUMIF(B30:B70,"Pagado",C30:C70) | G72: Imprevistos (5%) | H72: 0.05 | I72: =J12*0.05 | J72: 0 | K72: =IF(J72>=I72,"🟢","🔴")
A73: TOTAL FAM. PENDIENTES | C73: =SUMIF(B30:B70,"Pendiente",C30:C70) | G73: Desvío Imprevisto (5%) | H73: 0.05 | I73: =J12*0.05 | J73: 0 | K73: =IF(J73>=I73,"🟢","🔴")
G74: TOTAL | H74: =SUM(H69:H73) | I74: =SUM(I69:I73) | J74: =SUM(J69:J73)
G76: % GASTOS SOBRE INGRESO: | J76: =IF(J12=0,0,J69/J12)
G77: DIAGNÓSTICO: | J77: =IF(J12=0,"Sin datos",IF(J69/J12<=0.75,"🟢 CLÍNICA SANA",IF(J69/J12<=0.9,"🟡 REVISAR GASTOS","🔴 SITUACIÓN CRÍTICA")))

Sheet Ing-Egr Marzo 2026
A1: 📋 REGISTRO DE MOVIMIENTOS - MARZO 2026
A3: Fecha | B3: Tipo | C3: Categoría | D3: Descripción | E3: Ingreso | F3: Egreso | G3: Cuenta | H3: Notas
A104: TOTALES | E104: =SUM(E4:E103) | F104: =SUM(F4:F103)
A106: 📊 RESUMEN DEL MES
A107: INGRESOS: | C107: =SUMIF(B4:B103,"Ingreso NT",E4:E103)
A108: Ingreso NT: | C108: =SUMIF(B4:B103,"Ingreso NT",E4:E103)
A109: Ingreso Marco: | C109: =SUMIF(B4:B103,"Ingreso Marco",E4:E103)
A110: Ingreso Clara: | C110: =SUMIF(B4:B103,"Ingreso Clara",E4:E103)
A111: Devolución Fam → NT: | C111: =SUMIF(B4:B103,"Devolución Familia → NT",E4:E103)
A112: TOTAL INGRESOS: | C112: =SUM(C108:C111)
A113: EGRESOS:
A114: EGRESOS: | C114: =SUMIF(B4:B103,"Egreso NT",F4:F103)
A115: Egreso NT: | C115: =SUMIF(B4:B103,"Egreso NT",F4:F103)
A116: Egreso Familiar: | C116: =SUMIF(B4:B103,"Egreso Familiar",F4:F103)
A117: Préstamo NT → Fam: | C117: =SUMIF(B4:B103,"Préstamo NT → Familia",F4:F103)
A118: TOTAL EGRESOS: | C118: =SUM(C115:C117)
A120: SALDO PRÉSTAMO NT → FAM: | C120: =C117-C111
A121: (Prestado - Devuelto)

Sheet Marzo 2026
A1: 📊 CONTROL FINANCIERO - MARZO 2026
A3: TOTAL INGRESOS | D3: GASTOS PAGADOS | G3: GASTOS PENDIENTES | J3: BALANCE
A4: =D26+J12 | D4: =D65+I58 | G4: =D66+I59 | J4: =A4-D4-G4
A6: ⚠️ PRÉSTAMO NT → FAMILIA | D6: =SUMIF('Ing-Egr Marzo 2026'!B4:B103,"Préstamo NT → Familia",'Ing-Egr Marzo 2026'!F4:F103)-SUMIF('Ing-Egr Marzo 2026'!B4:B103,"Devolución Familia → NT",'Ing-Egr Marzo 2026'!E4:E103) | F6: Estado: | G6: =IF(D6=0,"🟢 SANO","🔴 FUGA") | I6: (Ideal = 0)
A8: 💵 INGRESOS FAMILIA | G8: 💵 INGRESOS NEUROTEA
A9: MARCO ITAIPU | C9: Fecha | D9: Monto | G9: Ingreso del Mes | J9: Monto
A10: Salario Mensual | D10: =SUMIFS('Ing-Egr Marzo 2026'!E4:E103,'Ing-Egr Marzo 2026'!B4:B103,"Ingreso Marco",'Ing-Egr Marzo 2026'!C4:C103,A10) | G10: (Suma desde pestaña Ing-Egr Marzo) | J10: =SUMIF('Ing-Egr Marzo 2026'!B4:B103,"Ingreso NT",'Ing-Egr Marzo 2026'!E4:E103)
A11: Vacaciones | D11: =SUMIFS('Ing-Egr Marzo 2026'!E4:E103,'Ing-Egr Marzo 2026'!B4:B103,"Ingreso Marco",'Ing-Egr Marzo 2026'!C4:C103,A11)
A12: Aguinaldo | D12: =SUMIFS('Ing-Egr Marzo 2026'!E4:E103,'Ing-Egr Marzo 2026'!B4:B103,"Ingreso Marco",'Ing-Egr Marzo 2026'!C4:C103,A12) | G12: ═══ TOTAL INGRESOS NT ═══ | J12: =J10
A13: Viático | D13: =SUMIFS('Ing-Egr Marzo 2026'!E4:E103,'Ing-Egr Marzo 2026'!B4:B103,"Ingreso Marco",'Ing-Egr Marzo 2026'!C4:C103,A13)
A14: Animador Bíblico | D14: =SUMIFS('Ing-Egr Marzo 2026'!E4:E103,'Ing-Egr Marzo 2026'!B4:B103,"Ingreso Marco",'Ing-Egr Marzo 2026'!C4:C103,A14)
A15: Otros Ocasionales | D15: =SUMIFS('Ing-Egr Marzo 2026'!E4:E103,'Ing-Egr Marzo 2026'!B4:B103,"Ingreso Marco",'Ing-Egr Marzo 2026'!C4:C103,A15) | I15: =J12
A16: TOTAL MARCO | D16: =SUM(D10:D15)
A17: CLARA | C17: Fecha | D17: Monto
A18: Honorarios Diarios | D18: =SUMIF('Ing-Egr Marzo 2026'!B4:B103,"Ingreso Clara",'Ing-Egr Marzo 2026'!E4:E103)
A19: TOTAL CLARA | D19: =D18
A20: DESDE NEUROTEA | D20: Monto
A21: Salario Admin Marco | D21: 0
A22: Ganancia NT → Familia | D22: 0
A23: Préstamo NT (automático) | D23: =D6
A24: TOTAL DESDE NT | D24: =SUM(D21:D23)
A26: ═══ TOTAL INGRESOS FAMILIA ═══ | D26: =D16+D19+D24
A28: 📉 GASTOS FAMILIARES | G28: 📉 GASTOS NEUROTEA
A29: Detalle | B29: Estado | C29: Monto | D29: Venc. | G29: Detalle | H29: Estado | I29: Monto | J29: Venc.
A30: ► GASTOS FIJOS ✏️ | G30: ► GASTOS FIJOS ✏️
A31: Salario Lili Doméstico | B31: Ninguno | G31: Alquiler 1 (Principal) | H31: Ninguno | I31: 0
A32: Salario Laura Doméstico | B32: Ninguno | G32: Alquiler 2 (Secundario) | H32: Ninguno | I32: 0
A33: Escuela Fabián y Brenda | B33: Ninguno | G33: Limpieza NeuroTEA | H33: Ninguno | I33: 0
A34: Robótica Niños | B34: Ninguno | G34: ► SUELDOS Y HONORARIOS ✏️
A35: ANDE Casa | B35: Ninguno | G35: Sueldo Aracely | H35: Ninguno | I35: 0
A36: Expensa Casa | B36: Ninguno | G36: Sueldo Fátima | H36: Ninguno | I36: 0
A37: Cajubi Marco | B37: Ninguno | G37: Honorario Contador | H37: Ninguno | I37: 0
A38: Mutual Marco | B38: Ninguno | G38: Salario Administrador | H38: Ninguno | I38: 0
A39: Ña Luisa | B39: Ninguno | G39: Honorario Mant. Sistema | H39: Ninguno | I39: 0
A40: Seguro Médico Papá y Mamá | B40: Ninguno | G40: ► TELEFONÍA E INTERNET ✏️
A41: ► CUOTAS Y PRÉSTAMOS ✏️ | G41: Celular Tigo NeuroTEA | H41: Ninguno | I41: 0
A42: Auto Laura Cuota | B42: Ninguno | G42: Celular Tigo Sistema | H42: Ninguno | I42: 0
A43: Coop. Universitaria Clara | B43: Ninguno | G43: WhatsFlow | H43: Ninguno | I43: 0
A44: Coomecipar Clara | B44: Ninguno | G44: Internet NeuroTEA | H44: Ninguno | I44: 0
A45: Tarjeta Cred. Coomecipar | B45: Ninguno | G45: ► IMPUESTOS ✏️
A46: Solar Préstamo 1 | B46: Ninguno | G46: IVA | H46: Ninguno | I46: 0
A47: Solar Préstamo 2 | B47: Ninguno | G47: ► EVENTOS NT ✏️
A48: Préstamo Lizzi Sueldos | B48: Ninguno | G48: Día del Niño NT | H48: Ninguno | I48: 0
A49: Show Congelador | B49: Ninguno | G49: San Juan NT | H49: Ninguno | I49: 0
A50: Olier Heladera | B50: Ninguno | G50: Día del Autismo NT | H50: Ninguno | I50: 0
A51: ► SUSCRIPCIONES E INTERNET ✏️ | G51: Clausura Padres NT | H51: Ninguno | I51: 0
A52: Giganet | B52: Ninguno | G52: Navidad Papá Noel NT | H52: Ninguno | I52: 0
A53: Tigo Internet/Celulares | B53: Ninguno | G53: Cena Fin de Año NT | H53: Ninguno | I53: 0
A54: Tigo Familiar | B54: Ninguno | G54: ► GASTOS VARIABLES NT 🔗
A55: Google One | B55: Ninguno | G55: Insumos NT | H55: Ninguno | I55: =SUMIFS('Ing-Egr Marzo 2026'!F4:F103,'Ing-Egr Marzo 2026'!B4:B103,"Egreso NT",'Ing-Egr Marzo 2026'!C4:C103,G55)
A56: ChatGPT | B56: Ninguno | G56: Papelería NT | H56: Ninguno | I56: =SUMIFS('Ing-Egr Marzo 2026'!F4:F103,'Ing-Egr Marzo 2026'!B4:B103,"Egreso NT",'Ing-Egr Marzo 2026'!C4:C103,G56)
A57: Claude Marco | B57: Ninguno | G57: Mantenimiento NT | H57: Ninguno | I57: =SUMIFS('Ing-Egr Marzo 2026'!F4:F103,'Ing-Egr Marzo 2026'!B4:B103,"Egreso NT",'Ing-Egr Marzo 2026'!C4:C103,G57)
A58: Claude Clara | B58: Ninguno | G58: Gastos Cursos NT | H58: Ninguno | I58: =SUMIFS('Ing-Egr Marzo 2026'!F4:F103,'Ing-Egr Marzo 2026'!B4:B103,"Egreso NT",'Ing-Egr Marzo 2026'!C4:C103,G58)
A59: iLovePDF | B59: Ninguno | G59: Gastos Varios NT | H59: Ninguno | I59: =SUMIFS('Ing-Egr Marzo 2026'!F4:F103,'Ing-Egr Marzo 2026'!B4:B103,"Egreso NT",'Ing-Egr Marzo 2026'!C4:C103,G59)
A60: Scribd | B60: Ninguno | G60: Reserva NT 1 | H60: Ninguno | I60: =SUMIFS('Ing-Egr Marzo 2026'!F4:F103,'Ing-Egr Marzo 2026'!B4:B103,"Egreso NT",'Ing-Egr Marzo 2026'!C4:C103,G60)
A61: Netflix | B61: Ninguno | G61: Reserva NT 2 | H61: Ninguno | I61: =SUMIFS('Ing-Egr Marzo 2026'!F4:F103,'Ing-Egr Marzo 2026'!B4:B103,"Egreso NT",'Ing-Egr Marzo 2026'!C4:C103,G61)
A62: ► GASTOS VARIABLES 🔗 | G62: Reserva NT 3 | H62: Ninguno | I62: =SUMIFS('Ing-Egr Marzo 2026'!F4:F103,'Ing-Egr Marzo 2026'!B4:B103,"Egreso NT",'Ing-Egr Marzo 2026'!C4:C103,G62)
A63: Combustible | B63: Ninguno | C63: =SUMIFS('Ing-Egr Marzo 2026'!F4:F103,'Ing-Egr Marzo 2026'!B4:B103,"Egreso Familiar",'Ing-Egr Marzo 2026'!C4:C103,A63)
A64: Supermercado | B64: Ninguno | C64: =SUMIFS('Ing-Egr Marzo 2026'!F4:F103,'Ing-Egr Marzo 2026'!B4:B103,"Egreso Familiar",'Ing-Egr Marzo 2026'!C4:C103,A64) | G64: TOTAL NT PAGADOS | I64: =SUMIF(H30:H62,"Pagado",I30:I62)
A65: Farmacia | B65: Ninguno | C65: =SUMIFS('Ing-Egr Marzo 2026'!F4:F103,'Ing-Egr Marzo 2026'!B4:B103,"Egreso Familiar",'Ing-Egr Marzo 2026'!C4:C103,A65) | D65: =C72 | G65: TOTAL NT PENDIENTES | I65: =SUMIF(H30:H62,"Pendiente",I30:I62)
A66: Recreación | B66: Ninguno | C66: =SUMIFS('Ing-Egr Marzo 2026'!F4:F103,'Ing-Egr Marzo 2026'!B4:B103,"Egreso Familiar",'Ing-Egr Marzo 2026'!C4:C103,A66) | D66: =C73
A67: Gastos Varios | B67: Ninguno | C67: =SUMIFS('Ing-Egr Marzo 2026'!F4:F103,'Ing-Egr Marzo 2026'!B4:B103,"Egreso Familiar",'Ing-Egr Marzo 2026'!C4:C103,A67) | G67: 📊 SALUD FINANCIERA NEUROTEA
A68: Reserva Fam 1 | B68: Ninguno | C68: =SUMIFS('Ing-Egr Marzo 2026'!F4:F103,'Ing-Egr Marzo 2026'!B4:B103,"Egreso Familiar",'Ing-Egr Marzo 2026'!C4:C103,A68) | G68: Concepto | H68: % Ideal | I68: Monto Ideal | J68: Monto Real | K68: Estado
A69: Reserva Fam 2 | B69: Ninguno | C69: =SUMIFS('Ing-Egr Marzo 2026'!F4:F103,'Ing-Egr Marzo 2026'!B4:B103,"Egreso Familiar",'Ing-Egr Marzo 2026'!C4:C103,A69) | G69: Gastos Operativos (máx 75%) | H69: 0.75 | I69: =J12*0.75 | J69: =I64+I65 | K69: =IF(J12=0,"-",IF(J69/J12<=0.75,"🟢 OK",IF(J69/J12<=0.9,"🟡 PRECAUCIÓN","🔴 ALARMA")))
A70: Reserva Fam 3 | B70: Ninguno | C70: =SUMIFS('Ing-Egr Marzo 2026'!F4:F103,'Ing-Egr Marzo 2026'!B4:B103,"Egreso Familiar",'Ing-Egr Marzo 2026'!C4:C103,A70) | G70: Ganancia (10%) | H70: 0.1 | I70: =J12*0.1 | J70: =D22 | K70: =IF(J70>=I70,"🟢","🔴")
G71: Inversiones (5%) | H71: 0.05 | I71: =J12*0.05 | J71: 0 | K71: =IF(J71>=I71,"🟢","🔴")
A72: TOTAL FAM. PAGADOS | C72: =SUMIF(B30:B70,"Pagado",C30:C70) | G72: Imprevistos (5%) | H72: 0.05 | I72: =J12*0.05 | J72: 0 | K72: =IF(J72>=I72,"🟢","🔴")
A73: TOTAL FAM. PENDIENTES | C73: =SUMIF(B30:B70,"Pendiente",C30:C70) | G73: Desvío Imprevisto (5%) | H73: 0.05 | I73: =J12*0.05 | J73: 0 | K73: =IF(J73>=I73,"🟢","🔴")
G74: TOTAL | H74: =SUM(H69:H73) | I74: =SUM(I69:I73) | J74: =SUM(J69:J73)
G76: % GASTOS SOBRE INGRESO: | J76: =IF(J12=0,0,J69/J12)
G77: DIAGNÓSTICO: | J77: =IF(J12=0,"Sin datos",IF(J69/J12<=0.75,"🟢 CLÍNICA SANA",IF(J69/J12<=0.9,"🟡 REVISAR GASTOS","🔴 SITUACIÓN CRÍTICA")))

Sheet Ing-Egr Abril 2026
A1: 📋 REGISTRO DE MOVIMIENTOS - ABRIL 2026
A3: Fecha | B3: Tipo | C3: Categoría | D3: Descripción | E3: Ingreso | F3: Egreso | G3: Cuenta | H3: Notas
A104: TOTALES | E104: =SUM(E4:E103) | F104: =SUM(F4:F103)
A106: 📊 RESUMEN DEL MES
A107: INGRESOS: | C107: =SUMIF(B4:B103,"Ingreso NT",E4:E103)
A108: Ingreso NT: | C108: =SUMIF(B4:B103,"Ingreso NT",E4:E103)
A109: Ingreso Marco: | C109: =SUMIF(B4:B103,"Ingreso Marco",E4:E103)
A110: Ingreso Clara: | C110: =SUMIF(B4:B103,"Ingreso Clara",E4:E103)
A111: Devolución Fam → NT: | C111: =SUMIF(B4:B103,"Devolución Familia → NT",E4:E103)
A112: TOTAL INGRESOS: | C112: =SUM(C108:C111)
A113: EGRESOS:
A114: EGRESOS: | C114: =SUMIF(B4:B103,"Egreso NT",F4:F103)
A115: Egreso NT: | C115: =SUMIF(B4:B103,"Egreso NT",F4:F103)
A116: Egreso Familiar: | C116: =SUMIF(B4:B103,"Egreso Familiar",F4:F103)
A117: Préstamo NT → Fam: | C117: =SUMIF(B4:B103,"Préstamo NT → Familia",F4:F103)
A118: TOTAL EGRESOS: | C118: =SUM(C115:C117)
A120: SALDO PRÉSTAMO NT → FAM: | C120: =C117-C111
A121: (Prestado - Devuelto)

Sheet Abril 2026
A1: 📊 CONTROL FINANCIERO - ABRIL 2026
A3: TOTAL INGRESOS | D3: GASTOS PAGADOS | G3: GASTOS PENDIENTES | J3: BALANCE
A4: =D26+J12 | D4: =D65+I58 | G4: =D66+I59 | J4: =A4-D4-G4
A6: ⚠️ PRÉSTAMO NT → FAMILIA | D6: =SUMIF('Ing-Egr Abril 2026'!B4:B103,"Préstamo NT → Familia",'Ing-Egr Abril 2026'!F4:F103)-SUMIF('Ing-Egr Abril 2026'!B4:B103,"Devolución Familia → NT",'Ing-Egr Abril 2026'!E4:E103) | F6: Estado: | G6: =IF(D6=0,"🟢 SANO","🔴 FUGA") | I6: (Ideal = 0)
A8: 💵 INGRESOS FAMILIA | G8: 💵 INGRESOS NEUROTEA
A9: MARCO ITAIPU | C9: Fecha | D9: Monto | G9: Ingreso del Mes | J9: Monto
A10: Salario Mensual | D10: =SUMIFS('Ing-Egr Abril 2026'!E4:E103,'Ing-Egr Abril 2026'!B4:B103,"Ingreso Marco",'Ing-Egr Abril 2026'!C4:C103,A10) | G10: (Suma desde pestaña Ing-Egr Abril) | J10: =SUMIF('Ing-Egr Abril 2026'!B4:B103,"Ingreso NT",'Ing-Egr Abril 2026'!E4:E103)
A11: Vacaciones | D11: =SUMIFS('Ing-Egr Abril 2026'!E4:E103,'Ing-Egr Abril 2026'!B4:B103,"Ingreso Marco",'Ing-Egr Abril 2026'!C4:C103,A11)
A12: Aguinaldo | D12: =SUMIFS('Ing-Egr Abril 2026'!E4:E103,'Ing-Egr Abril 2026'!B4:B103,"Ingreso Marco",'Ing-Egr Abril 2026'!C4:C103,A12) | G12: ═══ TOTAL INGRESOS NT ═══ | J12: =J10
A13: Viático | D13: =SUMIFS('Ing-Egr Abril 2026'!E4:E103,'Ing-Egr Abril 2026'!B4:B103,"Ingreso Marco",'Ing-Egr Abril 2026'!C4:C103,A13)
A14: Animador Bíblico | D14: =SUMIFS('Ing-Egr Abril 2026'!E4:E103,'Ing-Egr Abril 2026'!B4:B103,"Ingreso Marco",'Ing-Egr Abril 2026'!C4:C103,A14)
A15: Otros Ocasionales | D15: =SUMIFS('Ing-Egr Abril 2026'!E4:E103,'Ing-Egr Abril 2026'!B4:B103,"Ingreso Marco",'Ing-Egr Abril 2026'!C4:C103,A15) | I15: =J12
A16: TOTAL MARCO | D16: =SUM(D10:D15)
A17: CLARA | C17: Fecha | D17: Monto
A18: Honorarios Diarios | D18: =SUMIF('Ing-Egr Abril 2026'!B4:B103,"Ingreso Clara",'Ing-Egr Abril 2026'!E4:E103)
A19: TOTAL CLARA | D19: =D18
A20: DESDE NEUROTEA | D20: Monto
A21: Salario Admin Marco | D21: 0
A22: Ganancia NT → Familia | D22: 0
A23: Préstamo NT (automático) | D23: =D6
A24: TOTAL DESDE NT | D24: =SUM(D21:D23)
A26: ═══ TOTAL INGRESOS FAMILIA ═══ | D26: =D16+D19+D24
A28: 📉 GASTOS FAMILIARES | G28: 📉 GASTOS NEUROTEA
A29: Detalle | B29: Estado | C29: Monto | D29: Venc. | G29: Detalle | H29: Estado | I29: Monto | J29: Venc.
A30: ► GASTOS FIJOS ✏️ | G30: ► GASTOS FIJOS ✏️
A31: Salario Lili Doméstico | B31: Ninguno | G31: Alquiler 1 (Principal) | H31: Ninguno | I31: 0
A32: Salario Laura Doméstico | B32: Ninguno | G32: Alquiler 2 (Secundario) | H32: Ninguno | I32: 0
A33: Escuela Fabián y Brenda | B33: Ninguno | G33: Limpieza NeuroTEA | H33: Ninguno | I33: 0
A34: Robótica Niños | B34: Ninguno | G34: ► SUELDOS Y HONORARIOS ✏️
A35: ANDE Casa | B35: Ninguno | G35: Sueldo Aracely | H35: Ninguno | I35: 0
A36: Expensa Casa | B36: Ninguno | G36: Sueldo Fátima | H36: Ninguno | I36: 0
A37: Cajubi Marco | B37: Ninguno | G37: Honorario Contador | H37: Ninguno | I37: 0
A38: Mutual Marco | B38: Ninguno | G38: Salario Administrador | H38: Ninguno | I38: 0
A39: Ña Luisa | B39: Ninguno | G39: Honorario Mant. Sistema | H39: Ninguno | I39: 0
A40: Seguro Médico Papá y Mamá | B40: Ninguno | G40: ► TELEFONÍA E INTERNET ✏️
A41: ► CUOTAS Y PRÉSTAMOS ✏️ | G41: Celular Tigo NeuroTEA | H41: Ninguno | I41: 0
A42: Auto Laura Cuota | B42: Ninguno | G42: Celular Tigo Sistema | H42: Ninguno | I42: 0
A43: Coop. Universitaria Clara | B43: Ninguno | G43: WhatsFlow | H43: Ninguno | I43: 0
A44: Coomecipar Clara | B44: Ninguno | G44: Internet NeuroTEA | H44: Ninguno | I44: 0
A45: Tarjeta Cred. Coomecipar | B45: Ninguno | G45: ► IMPUESTOS ✏️
A46: Solar Préstamo 1 | B46: Ninguno | G46: IVA | H46: Ninguno | I46: 0
A47: Solar Préstamo 2 | B47: Ninguno | G47: ► EVENTOS NT ✏️
A48: Préstamo Lizzi Sueldos | B48: Ninguno | G48: Día del Niño NT | H48: Ninguno | I48: 0
A49: Show Congelador | B49: Ninguno | G49: San Juan NT | H49: Ninguno | I49: 0
A50: Olier Heladera | B50: Ninguno | G50: Día del Autismo NT | H50: Ninguno | I50: 0
A51: ► SUSCRIPCIONES E INTERNET ✏️ | G51: Clausura Padres NT | H51: Ninguno | I51: 0
A52: Giganet | B52: Ninguno | G52: Navidad Papá Noel NT | H52: Ninguno | I52: 0
A53: Tigo Internet/Celulares | B53: Ninguno | G53: Cena Fin de Año NT | H53: Ninguno | I53: 0
A54: Tigo Familiar | B54: Ninguno | G54: ► GASTOS VARIABLES NT 🔗
A55: Google One | B55: Ninguno | G55: Insumos NT | H55: Ninguno | I55: =SUMIFS('Ing-Egr Abril 2026'!F4:F103,'Ing-Egr Abril 2026'!B4:B103,"Egreso NT",'Ing-Egr Abril 2026'!C4:C103,G55)
A56: ChatGPT | B56: Ninguno | G56: Papelería NT | H56: Ninguno | I56: =SUMIFS('Ing-Egr Abril 2026'!F4:F103,'Ing-Egr Abril 2026'!B4:B103,"Egreso NT",'Ing-Egr Abril 2026'!C4:C103,G56)
A57: Claude Marco | B57: Ninguno | G57: Mantenimiento NT | H57: Ninguno | I57: =SUMIFS('Ing-Egr Abril 2026'!F4:F103,'Ing-Egr Abril 2026'!B4:B103,"Egreso NT",'Ing-Egr Abril 2026'!C4:C103,G57)
A58: Claude Clara | B58: Ninguno | G58: Gastos Cursos NT | H58: Ninguno | I58: =SUMIFS('Ing-Egr Abril 2026'!F4:F103,'Ing-Egr Abril 2026'!B4:B103,"Egreso NT",'Ing-Egr Abril 2026'!C4:C103,G58)
A59: iLovePDF | B59: Ninguno | G59: Gastos Varios NT | H59: Ninguno | I59: =SUMIFS('Ing-Egr Abril 2026'!F4:F103,'Ing-Egr Abril 2026'!B4:B103,"Egreso NT",'Ing-Egr Abril 2026'!C4:C103,G59)
A60: Scribd | B60: Ninguno | G60: Reserva NT 1 | H60: Ninguno | I60: =SUMIFS('Ing-Egr Abril 2026'!F4:F103,'Ing-Egr Abril 2026'!B4:B103,"Egreso NT",'Ing-Egr Abril 2026'!C4:C103,G60)
A61: Netflix | B61: Ninguno | G61: Reserva NT 2 | H61: Ninguno | I61: =SUMIFS('Ing-Egr Abril 2026'!F4:F103,'Ing-Egr Abril 2026'!B4:B103,"Egreso NT",'Ing-Egr Abril 2026'!C4:C103,G61)
A62: ► GASTOS VARIABLES 🔗 | G62: Reserva NT 3 | H62: Ninguno | I62: =SUMIFS('Ing-Egr Abril 2026'!F4:F103,'Ing-Egr Abril 2026'!B4:B103,"Egreso NT",'Ing-Egr Abril 2026'!C4:C103,G62)
A63: Combustible | B63: Ninguno | C63: =SUMIFS('Ing-Egr Abril 2026'!F4:F103,'Ing-Egr Abril 2026'!B4:B103,"Egreso Familiar",'Ing-Egr Abril 2026'!C4:C103,A63)
A64: Supermercado | B64: Ninguno | C64: =SUMIFS('Ing-Egr Abril 2026'!F4:F103,'Ing-Egr Abril 2026'!B4:B103,"Egreso Familiar",'Ing-Egr Abril 2026'!C4:C103,A64) | G64: TOTAL NT PAGADOS | I64: =SUMIF(H30:H62,"Pagado",I30:I62)
A65: Farmacia | B65: Ninguno | C65: =SUMIFS('Ing-Egr Abril 2026'!F4:F103,'Ing-Egr Abril 2026'!B4:B103,"Egreso Familiar",'Ing-Egr Abril 2026'!C4:C103,A65) | D65: =C72 | G65: TOTAL NT PENDIENTES | I65: =SUMIF(H30:H62,"Pendiente",I30:I62)
A66: Recreación | B66: Ninguno | C66: =SUMIFS('Ing-Egr Abril 2026'!F4:F103,'Ing-Egr Abril 2026'!B4:B103,"Egreso Familiar",'Ing-Egr Abril 2026'!C4:C103,A66) | D66: =C73
A67: Gastos Varios | B67: Ninguno | C67: =SUMIFS('Ing-Egr Abril 2026'!F4:F103,'Ing-Egr Abril 2026'!B4:B103,"Egreso Familiar",'Ing-Egr Abril 2026'!C4:C103,A67) | G67: 📊 SALUD FINANCIERA NEUROTEA
A68: Reserva Fam 1 | B68: Ninguno | C68: =SUMIFS('Ing-Egr Abril 2026'!F4:F103,'Ing-Egr Abril 2026'!B4:B103,"Egreso Familiar",'Ing-Egr Abril 2026'!C4:C103,A68) | G68: Concepto | H68: % Ideal | I68: Monto Ideal | J68: Monto Real | K68: Estado
A69: Reserva Fam 2 | B69: Ninguno | C69: =SUMIFS('Ing-Egr Abril 2026'!F4:F103,'Ing-Egr Abril 2026'!B4:B103,"Egreso Familiar",'Ing-Egr Abril 2026'!C4:C103,A69) | G69: Gastos Operativos (máx 75%) | H69: 0.75 | I69: =J12*0.75 | J69: =I64+I65 | K69: =IF(J12=0,"-",IF(J69/J12<=0.75,"🟢 OK",IF(J69/J12<=0.9,"🟡 PRECAUCIÓN","🔴 ALARMA")))
A70: Reserva Fam 3 | B70: Ninguno | C70: =SUMIFS('Ing-Egr Abril 2026'!F4:F103,'Ing-Egr Abril 2026'!B4:B103,"Egreso Familiar",'Ing-Egr Abril 2026'!C4:C103,A70) | G70: Ganancia (10%) | H70: 0.1 | I70: =J12*0.1 | J70: =D22 | K70: =IF(J70>=I70,"🟢","🔴")
G71: Inversiones (5%) | H71: 0.05 | I71: =J12*0.05 | J71: 0 | K71: =IF(J71>=I71,"🟢","🔴")
A72: TOTAL FAM. PAGADOS | C72: =SUMIF(B30:B70,"Pagado",C30:C70) | G72: Imprevistos (5%) | H72: 0.05 | I72: =J12*0.05 | J72: 0 | K72: =IF(J72>=I72,"🟢","🔴")
A73: TOTAL FAM. PENDIENTES | C73: =SUMIF(B30:B70,"Pendiente",C30:C70) | G73: Desvío Imprevisto (5%) | H73: 0.05 | I73: =J12*0.05 | J73: 0 | K73: =IF(J73>=I73,"🟢","🔴")
G74: TOTAL | H74: =SUM(H69:H73) | I74: =SUM(I69:I73) | J74: =SUM(J69:J73)
G76: % GASTOS SOBRE INGRESO: | J76: =IF(J12=0,0,J69/J12)
G77: DIAGNÓSTICO: | J77: =IF(J12=0,"Sin datos",IF(J69/J12<=0.75,"🟢 CLÍNICA SANA",IF(J69/J12<=0.9,"🟡 REVISAR GASTOS","🔴 SITUACIÓN CRÍTICA")))

Sheet Ing-Egr Mayo 2026
A1: 📋 REGISTRO DE MOVIMIENTOS - MAYO 2026
A3: Fecha | B3: Tipo | C3: Categoría | D3: Descripción | E3: Ingreso | F3: Egreso | G3: Cuenta | H3: Notas
A104: TOTALES | E104: =SUM(E4:E103) | F104: =SUM(F4:F103)
A106: 📊 RESUMEN DEL MES
A107: INGRESOS: | C107: =SUMIF(B4:B103,"Ingreso NT",E4:E103)
A108: Ingreso NT: | C108: =SUMIF(B4:B103,"Ingreso NT",E4:E103)
A109: Ingreso Marco: | C109: =SUMIF(B4:B103,"Ingreso Marco",E4:E103)
A110: Ingreso Clara: | C110: =SUMIF(B4:B103,"Ingreso Clara",E4:E103)
A111: Devolución Fam → NT: | C111: =SUMIF(B4:B103,"Devolución Familia → NT",E4:E103)
A112: TOTAL INGRESOS: | C112: =SUM(C108:C111)
A113: EGRESOS:
A114: EGRESOS: | C114: =SUMIF(B4:B103,"Egreso NT",F4:F103)
A115: Egreso NT: | C115: =SUMIF(B4:B103,"Egreso NT",F4:F103)
A116: Egreso Familiar: | C116: =SUMIF(B4:B103,"Egreso Familiar",F4:F103)
A117: Préstamo NT → Fam: | C117: =SUMIF(B4:B103,"Préstamo NT → Familia",F4:F103)
A118: TOTAL EGRESOS: | C118: =SUM(C115:C117)
A120: SALDO PRÉSTAMO NT → FAM: | C120: =C117-C111
A121: (Prestado - Devuelto)

Sheet Mayo 2026
A1: 📊 CONTROL FINANCIERO - MAYO 2026
A3: TOTAL INGRESOS | D3: GASTOS PAGADOS | G3: GASTOS PENDIENTES | J3: BALANCE
A4: =D26+J12 | D4: =D65+I58 | G4: =D66+I59 | J4: =A4-D4-G4
A6: ⚠️ PRÉSTAMO NT → FAMILIA | D6: =SUMIF('Ing-Egr Mayo 2026'!B4:B103,"Préstamo NT → Familia",'Ing-Egr Mayo 2026'!F4:F103)-SUMIF('Ing-Egr Mayo 2026'!B4:B103,"Devolución Familia → NT",'Ing-Egr Mayo 2026'!E4:E103) | F6: Estado: | G6: =IF(D6=0,"🟢 SANO","🔴 FUGA") | I6: (Ideal = 0)
A8: 💵 INGRESOS FAMILIA | G8: 💵 INGRESOS NEUROTEA
A9: MARCO ITAIPU | C9: Fecha | D9: Monto | G9: Ingreso del Mes | J9: Monto
A10: Salario Mensual | D10: =SUMIFS('Ing-Egr Mayo 2026'!E4:E103,'Ing-Egr Mayo 2026'!B4:B103,"Ingreso Marco",'Ing-Egr Mayo 2026'!C4:C103,A10) | G10: (Suma desde pestaña Ing-Egr Mayo) | J10: =SUMIF('Ing-Egr Mayo 2026'!B4:B103,"Ingreso NT",'Ing-Egr Mayo 2026'!E4:E103)
A11: Vacaciones | D11: =SUMIFS('Ing-Egr Mayo 2026'!E4:E103,'Ing-Egr Mayo 2026'!B4:B103,"Ingreso Marco",'Ing-Egr Mayo 2026'!C4:C103,A11)
A12: Aguinaldo | D12: =SUMIFS('Ing-Egr Mayo 2026'!E4:E103,'Ing-Egr Mayo 2026'!B4:B103,"Ingreso Marco",'Ing-Egr Mayo 2026'!C4:C103,A12) | G12: ═══ TOTAL INGRESOS NT ═══ | J12: =J10
A13: Viático | D13: =SUMIFS('Ing-Egr Mayo 2026'!E4:E103,'Ing-Egr Mayo 2026'!B4:B103,"Ingreso Marco",'Ing-Egr Mayo 2026'!C4:C103,A13)
A14: Animador Bíblico | D14: =SUMIFS('Ing-Egr Mayo 2026'!E4:E103,'Ing-Egr Mayo 2026'!B4:B103,"Ingreso Marco",'Ing-Egr Mayo 2026'!C4:C103,A14)
A15: Otros Ocasionales | D15: =SUMIFS('Ing-Egr Mayo 2026'!E4:E103,'Ing-Egr Mayo 2026'!B4:B103,"Ingreso Marco",'Ing-Egr Mayo 2026'!C4:C103,A15) | I15: =J12
A16: TOTAL MARCO | D16: =SUM(D10:D15)
A17: CLARA | C17: Fecha | D17: Monto
A18: Honorarios Diarios | D18: =SUMIF('Ing-Egr Mayo 2026'!B4:B103,"Ingreso Clara",'Ing-Egr Mayo 2026'!E4:E103)
A19: TOTAL CLARA | D19: =D18
A20: DESDE NEUROTEA | D20: Monto
A21: Salario Admin Marco | D21: 0
A22: Ganancia NT → Familia | D22: 0
A23: Préstamo NT (automático) | D23: =D6
A24: TOTAL DESDE NT | D24: =SUM(D21:D23)
A26: ═══ TOTAL INGRESOS FAMILIA ═══ | D26: =D16+D19+D24
A28: 📉 GASTOS FAMILIARES | G28: 📉 GASTOS NEUROTEA
A29: Detalle | B29: Estado | C29: Monto | D29: Venc. | G29: Detalle | H29: Estado | I29: Monto | J29: Venc.
A30: ► GASTOS FIJOS ✏️ | G30: ► GASTOS FIJOS ✏️
A31: Salario Lili Doméstico | B31: Ninguno | G31: Alquiler 1 (Principal) | H31: Ninguno | I31: 0
A32: Salario Laura Doméstico | B32: Ninguno | G32: Alquiler 2 (Secundario) | H32: Ninguno | I32: 0
A33: Escuela Fabián y Brenda | B33: Ninguno | G33: Limpieza NeuroTEA | H33: Ninguno | I33: 0
A34: Robótica Niños | B34: Ninguno | G34: ► SUELDOS Y HONORARIOS ✏️
A35: ANDE Casa | B35: Ninguno | G35: Sueldo Aracely | H35: Ninguno | I35: 0
A36: Expensa Casa | B36: Ninguno | G36: Sueldo Fátima | H36: Ninguno | I36: 0
A37: Cajubi Marco | B37: Ninguno | G37: Honorario Contador | H37: Ninguno | I37: 0
A38: Mutual Marco | B38: Ninguno | G38: Salario Administrador | H38: Ninguno | I38: 0
A39: Ña Luisa | B39: Ninguno | G39: Honorario Mant. Sistema | H39: Ninguno | I39: 0
A40: Seguro Médico Papá y Mamá | B40: Ninguno | G40: ► TELEFONÍA E INTERNET ✏️
A41: ► CUOTAS Y PRÉSTAMOS ✏️ | G41: Celular Tigo NeuroTEA | H41: Ninguno | I41: 0
A42: Auto Laura Cuota | B42: Ninguno | G42: Celular Tigo Sistema | H42: Ninguno | I42: 0
A43: Coop. Universitaria Clara | B43: Ninguno | G43: WhatsFlow | H43: Ninguno | I43: 0
A44: Coomecipar Clara | B44: Ninguno | G44: Internet NeuroTEA | H44: Ninguno | I44: 0
A45: Tarjeta Cred. Coomecipar | B45: Ninguno | G45: ► IMPUESTOS ✏️
A46: Solar Préstamo 1 | B46: Ninguno | G46: IVA | H46: Ninguno | I46: 0
A47: Solar Préstamo 2 | B47: Ninguno | G47: ► EVENTOS NT ✏️
A48: Préstamo Lizzi Sueldos | B48: Ninguno | G48: Día del Niño NT | H48: Ninguno | I48: 0
A49: Show Congelador | B49: Ninguno | G49: San Juan NT | H49: Ninguno | I49: 0
A50: Olier Heladera | B50: Ninguno | G50: Día del Autismo NT | H50: Ninguno | I50: 0
A51: ► SUSCRIPCIONES E INTERNET ✏️ | G51: Clausura Padres NT | H51: Ninguno | I51: 0
A52: Giganet | B52: Ninguno | G52: Navidad Papá Noel NT | H52: Ninguno | I52: 0
A53: Tigo Internet/Celulares | B53: Ninguno | G53: Cena Fin de Año NT | H53: Ninguno | I53: 0
A54: Tigo Familiar | B54: Ninguno | G54: ► GASTOS VARIABLES NT 🔗
A55: Google One | B55: Ninguno | G55: Insumos NT | H55: Ninguno | I55: =SUMIFS('Ing-Egr Mayo 2026'!F4:F103,'Ing-Egr Mayo 2026'!B4:B103,"Egreso NT",'Ing-Egr Mayo 2026'!C4:C103,G55)
A56: ChatGPT | B56: Ninguno | G56: Papelería NT | H56: Ninguno | I56: =SUMIFS('Ing-Egr Mayo 2026'!F4:F103,'Ing-Egr Mayo 2026'!B4:B103,"Egreso NT",'Ing-Egr Mayo 2026'!C4:C103,G56)
A57: Claude Marco | B57: Ninguno | G57: Mantenimiento NT | H57: Ninguno | I57: =SUMIFS('Ing-Egr Mayo 2026'!F4:F103,'Ing-Egr Mayo 2026'!B4:B103,"Egreso NT",'Ing-Egr Mayo 2026'!C4:C103,G57)
A58: Claude Clara | B58: Ninguno | G58: Gastos Cursos NT | H58: Ninguno | I58: =SUMIFS('Ing-Egr Mayo 2026'!F4:F103,'Ing-Egr Mayo 2026'!B4:B103,"Egreso NT",'Ing-Egr Mayo 2026'!C4:C103,G58)
A59: iLovePDF | B59: Ninguno | G59: Gastos Varios NT | H59: Ninguno | I59: =SUMIFS('Ing-Egr Mayo 2026'!F4:F103,'Ing-Egr Mayo 2026'!B4:B103,"Egreso NT",'Ing-Egr Mayo 2026'!C4:C103,G59)
A60: Scribd | B60: Ninguno | G60: Reserva NT 1 | H60: Ninguno | I60: =SUMIFS('Ing-Egr Mayo 2026'!F4:F103,'Ing-Egr Mayo 2026'!B4:B103,"Egreso NT",'Ing-Egr Mayo 2026'!C4:C103,G60)
A61: Netflix | B61: Ninguno | G61: Reserva NT 2 | H61: Ninguno | I61: =SUMIFS('Ing-Egr Mayo 2026'!F4:F103,'Ing-Egr Mayo 2026'!B4:B103,"Egreso NT",'Ing-Egr Mayo 2026'!C4:C103,G61)
A62: ► GASTOS VARIABLES 🔗 | G62: Reserva NT 3 | H62: Ninguno | I62: =SUMIFS('Ing-Egr Mayo 2026'!F4:F103,'Ing-Egr Mayo 2026'!B4:B103,"Egreso NT",'Ing-Egr Mayo 2026'!C4:C103,G62)
A63: Combustible | B63: Ninguno | C63: =SUMIFS('Ing-Egr Mayo 2026'!F4:F103,'Ing-Egr Mayo 2026'!B4:B103,"Egreso Familiar",'Ing-Egr Mayo 2026'!C4:C103,A63)
A64: Supermercado | B64: Ninguno | C64: =SUMIFS('Ing-Egr Mayo 2026'!F4:F103,'Ing-Egr Mayo 2026'!B4:B103,"Egreso Familiar",'Ing-Egr Mayo 2026'!C4:C103,A64) | G64: TOTAL NT PAGADOS | I64: =SUMIF(H30:H62,"Pagado",I30:I62)
A65: Farmacia | B65: Ninguno | C65: =SUMIFS('Ing-Egr Mayo 2026'!F4:F103,'Ing-Egr Mayo 2026'!B4:B103,"Egreso Familiar",'Ing-Egr Mayo 2026'!C4:C103,A65) | D65: =C72 | G65: TOTAL NT PENDIENTES | I65: =SUMIF(H30:H62,"Pendiente",I30:I62)
A66: Recreación | B66: Ninguno | C66: =SUMIFS('Ing-Egr Mayo 2026'!F4:F103,'Ing-Egr Mayo 2026'!B4:B103,"Egreso Familiar",'Ing-Egr Mayo 2026'!C4:C103,A66) | D66: =C73
A67: Gastos Varios | B67: Ninguno | C67: =SUMIFS('Ing-Egr Mayo 2026'!F4:F103,'Ing-Egr Mayo 2026'!B4:B103,"Egreso Familiar",'Ing-Egr Mayo 2026'!C4:C103,A67) | G67: 📊 SALUD FINANCIERA NEUROTEA
A68: Reserva Fam 1 | B68: Ninguno | C68: =SUMIFS('Ing-Egr Mayo 2026'!F4:F103,'Ing-Egr Mayo 2026'!B4:B103,"Egreso Familiar",'Ing-Egr Mayo 2026'!C4:C103,A68) | G68: Concepto | H68: % Ideal | I68: Monto Ideal | J68: Monto Real | K68: Estado
A69: Reserva Fam 2 | B69: Ninguno | C69: =SUMIFS('Ing-Egr Mayo 2026'!F4:F103,'Ing-Egr Mayo 2026'!B4:B103,"Egreso Familiar",'Ing-Egr Mayo 2026'!C4:C103,A69) | G69: Gastos Operativos (máx 75%) | H69: 0.75 | I69: =J12*0.75 | J69: =I64+I65 | K69: =IF(J12=0,"-",IF(J69/J12<=0.75,"🟢 OK",IF(J69/J12<=0.9,"🟡 PRECAUCIÓN","🔴 ALARMA")))
A70: Reserva Fam 3 | B70: Ninguno | C70: =SUMIFS('Ing-Egr Mayo 2026'!F4:F103,'Ing-Egr Mayo 2026'!B4:B103,"Egreso Familiar",'Ing-Egr Mayo 2026'!C4:C103,A70) | G70: Ganancia (10%) | H70: 0.1 | I70: =J12*0.1 | J70: =D22 | K70: =IF(J70>=I70,"🟢","🔴")
G71: Inversiones (5%) | H71: 0.05 | I71: =J12*0.05 | J71: 0 | K71: =IF(J71>=I71,"🟢","🔴")
A72: TOTAL FAM. PAGADOS | C72: =SUMIF(B30:B70,"Pagado",C30:C70) | G72: Imprevistos (5%) | H72: 0.05 | I72: =J12*0.05 | J72: 0 | K72: =IF(J72>=I72,"🟢","🔴")
A73: TOTAL FAM. PENDIENTES | C73: =SUMIF(B30:B70,"Pendiente",C30:C70) | G73: Desvío Imprevisto (5%) | H73: 0.05 | I73: =J12*0.05 | J73: 0 | K73: =IF(J73>=I73,"🟢","🔴")
G74: TOTAL | H74: =SUM(H69:H73) | I74: =SUM(I69:I73) | J74: =SUM(J69:J73)
G76: % GASTOS SOBRE INGRESO: | J76: =IF(J12=0,0,J69/J12)
G77: DIAGNÓSTICO: | J77: =IF(J12=0,"Sin datos",IF(J69/J12<=0.75,"🟢 CLÍNICA SANA",IF(J69/J12<=0.9,"🟡 REVISAR GASTOS","🔴 SITUACIÓN CRÍTICA")))

Sheet Ing-Egr Junio 2026
A1: 📋 REGISTRO DE MOVIMIENTOS - JUNIO 2026
A3: Fecha | B3: Tipo | C3: Categoría | D3: Descripción | E3: Ingreso | F3: Egreso | G3: Cuenta | H3: Notas
A104: TOTALES | E104: =SUM(E4:E103) | F104: =SUM(F4:F103)
A106: 📊 RESUMEN DEL MES
A107: INGRESOS: | C107: =SUMIF(B4:B103,"Ingreso NT",E4:E103)
A108: Ingreso NT: | C108: =SUMIF(B4:B103,"Ingreso NT",E4:E103)
A109: Ingreso Marco: | C109: =SUMIF(B4:B103,"Ingreso Marco",E4:E103)
A110: Ingreso Clara: | C110: =SUMIF(B4:B103,"Ingreso Clara",E4:E103)
A111: Devolución Fam → NT: | C111: =SUMIF(B4:B103,"Devolución Familia → NT",E4:E103)
A112: TOTAL INGRESOS: | C112: =SUM(C108:C111)
A113: EGRESOS:
A114: EGRESOS: | C114: =SUMIF(B4:B103,"Egreso NT",F4:F103)
A115: Egreso NT: | C115: =SUMIF(B4:B103,"Egreso NT",F4:F103)
A116: Egreso Familiar: | C116: =SUMIF(B4:B103,"Egreso Familiar",F4:F103)
A117: Préstamo NT → Fam: | C117: =SUMIF(B4:B103,"Préstamo NT → Familia",F4:F103)
A118: TOTAL EGRESOS: | C118: =SUM(C115:C117)
A120: SALDO PRÉSTAMO NT → FAM: | C120: =C117-C111
A121: (Prestado - Devuelto)

Sheet Junio 2026
A1: 📊 CONTROL FINANCIERO - JUNIO 2026
A3: TOTAL INGRESOS | D3: GASTOS PAGADOS | G3: GASTOS PENDIENTES | J3: BALANCE
A4: =D26+J12 | D4: =D65+I58 | G4: =D66+I59 | J4: =A4-D4-G4
A6: ⚠️ PRÉSTAMO NT → FAMILIA | D6: =SUMIF('Ing-Egr Junio 2026'!B4:B103,"Préstamo NT → Familia",'Ing-Egr Junio 2026'!F4:F103)-SUMIF('Ing-Egr Junio 2026'!B4:B103,"Devolución Familia → NT",'Ing-Egr Junio 2026'!E4:E103) | F6: Estado: | G6: =IF(D6=0,"🟢 SANO","🔴 FUGA") | I6: (Ideal = 0)
A8: 💵 INGRESOS FAMILIA | G8: 💵 INGRESOS NEUROTEA
A9: MARCO ITAIPU | C9: Fecha | D9: Monto | G9: Ingreso del Mes | J9: Monto
A10: Salario Mensual | D10: =SUMIFS('Ing-Egr Junio 2026'!E4:E103,'Ing-Egr Junio 2026'!B4:B103,"Ingreso Marco",'Ing-Egr Junio 2026'!C4:C103,A10) | G10: (Suma desde pestaña Ing-Egr Junio) | J10: =SUMIF('Ing-Egr Junio 2026'!B4:B103,"Ingreso NT",'Ing-Egr Junio 2026'!E4:E103)
A11: Vacaciones | D11: =SUMIFS('Ing-Egr Junio 2026'!E4:E103,'Ing-Egr Junio 2026'!B4:B103,"Ingreso Marco",'Ing-Egr Junio 2026'!C4:C103,A11)
A12: Aguinaldo | D12: =SUMIFS('Ing-Egr Junio 2026'!E4:E103,'Ing-Egr Junio 2026'!B4:B103,"Ingreso Marco",'Ing-Egr Junio 2026'!C4:C103,A12) | G12: ═══ TOTAL INGRESOS NT ═══ | J12: =J10
A13: Viático | D13: =SUMIFS('Ing-Egr Junio 2026'!E4:E103,'Ing-Egr Junio 2026'!B4:B103,"Ingreso Marco",'Ing-Egr Junio 2026'!C4:C103,A13)
A14: Animador Bíblico | D14: =SUMIFS('Ing-Egr Junio 2026'!E4:E103,'Ing-Egr Junio 2026'!B4:B103,"Ingreso Marco",'Ing-Egr Junio 2026'!C4:C103,A14)
A15: Otros Ocasionales | D15: =SUMIFS('Ing-Egr Junio 2026'!E4:E103,'Ing-Egr Junio 2026'!B4:B103,"Ingreso Marco",'Ing-Egr Junio 2026'!C4:C103,A15) | I15: =J12
A16: TOTAL MARCO | D16: =SUM(D10:D15)
A17: CLARA | C17: Fecha | D17: Monto
A18: Honorarios Diarios | D18: =SUMIF('Ing-Egr Junio 2026'!B4:B103,"Ingreso Clara",'Ing-Egr Junio 2026'!E4:E103)
A19: TOTAL CLARA | D19: =D18
A20: DESDE NEUROTEA | D20: Monto
A21: Salario Admin Marco | D21: 0
A22: Ganancia NT → Familia | D22: 0
A23: Préstamo NT (automático) | D23: =D6
A24: TOTAL DESDE NT | D24: =SUM(D21:D23)
A26: ═══ TOTAL INGRESOS FAMILIA ═══ | D26: =D16+D19+D24
A28: 📉 GASTOS FAMILIARES | G28: 📉 GASTOS NEUROTEA
A29: Detalle | B29: Estado | C29: Monto | D29: Venc. | G29: Detalle | H29: Estado | I29: Monto | J29: Venc.
A30: ► GASTOS FIJOS ✏️ | G30: ► GASTOS FIJOS ✏️
A31: Salario Lili Doméstico | B31: Ninguno | G31: Alquiler 1 (Principal) | H31: Ninguno | I31: 0
A32: Salario Laura Doméstico | B32: Ninguno | G32: Alquiler 2 (Secundario) | H32: Ninguno | I32: 0
A33: Escuela Fabián y Brenda | B33: Ninguno | G33: Limpieza NeuroTEA | H33: Ninguno | I33: 0
A34: Robótica Niños | B34: Ninguno | G34: ► SUELDOS Y HONORARIOS ✏️
A35: ANDE Casa | B35: Ninguno | G35: Sueldo Aracely | H35: Ninguno | I35: 0
A36: Expensa Casa | B36: Ninguno | G36: Sueldo Fátima | H36: Ninguno | I36: 0
A37: Cajubi Marco | B37: Ninguno | G37: Honorario Contador | H37: Ninguno | I37: 0
A38: Mutual Marco | B38: Ninguno | G38: Salario Administrador | H38: Ninguno | I38: 0
A39: Ña Luisa | B39: Ninguno | G39: Honorario Mant. Sistema | H39: Ninguno | I39: 0
A40: Seguro Médico Papá y Mamá | B40: Ninguno | G40: ► TELEFONÍA E INTERNET ✏️
A41: ► CUOTAS Y PRÉSTAMOS ✏️ | G41: Celular Tigo NeuroTEA | H41: Ninguno | I41: 0
A42: Auto Laura Cuota | B42: Ninguno | G42: Celular Tigo Sistema | H42: Ninguno | I42: 0
A43: Coop. Universitaria Clara | B43: Ninguno | G43: WhatsFlow | H43: Ninguno | I43: 0
A44: Coomecipar Clara | B44: Ninguno | G44: Internet NeuroTEA | H44: Ninguno | I44: 0
A45: Tarjeta Cred. Coomecipar | B45: Ninguno | G45: ► IMPUESTOS ✏️
A46: Solar Préstamo 1 | B46: Ninguno | G46: IVA | H46: Ninguno | I46: 0
A47: Solar Préstamo 2 | B47: Ninguno | G47: ► EVENTOS NT ✏️
A48: Préstamo Lizzi Sueldos | B48: Ninguno | G48: Día del Niño NT | H48: Ninguno | I48: 0
A49: Show Congelador | B49: Ninguno | G49: San Juan NT | H49: Ninguno | I49: 0
A50: Olier Heladera | B50: Ninguno | G50: Día del Autismo NT | H50: Ninguno | I50: 0
A51: ► SUSCRIPCIONES E INTERNET ✏️ | G51: Clausura Padres NT | H51: Ninguno | I51: 0
A52: Giganet | B52: Ninguno | G52: Navidad Papá Noel NT | H52: Ninguno | I52: 0
A53: Tigo Internet/Celulares | B53: Ninguno | G53: Cena Fin de Año NT | H53: Ninguno | I53: 0
A54: Tigo Familiar | B54: Ninguno | G54: ► GASTOS VARIABLES NT 🔗
A55: Google One | B55: Ninguno | G55: Insumos NT | H55: Ninguno | I55: =SUMIFS('Ing-Egr Junio 2026'!F4:F103,'Ing-Egr Junio 2026'!B4:B103,"Egreso NT",'Ing-Egr Junio 2026'!C4:C103,G55)
A56: ChatGPT | B56: Ninguno | G56: Papelería NT | H56: Ninguno | I56: =SUMIFS('Ing-Egr Junio 2026'!F4:F103,'Ing-Egr Junio 2026'!B4:B103,"Egreso NT",'Ing-Egr Junio 2026'!C4:C103,G56)
A57: Claude Marco | B57: Ninguno | G57: Mantenimiento NT | H57: Ninguno | I57: =SUMIFS('Ing-Egr Junio 2026'!F4:F103,'Ing-Egr Junio 2026'!B4:B103,"Egreso NT",'Ing-Egr Junio 2026'!C4:C103,G57)
A58: Claude Clara | B58: Ninguno | G58: Gastos Cursos NT | H58: Ninguno | I58: =SUMIFS('Ing-Egr Junio 2026'!F4:F103,'Ing-Egr Junio 2026'!B4:B103,"Egreso NT",'Ing-Egr Junio 2026'!C4:C103,G58)
A59: iLovePDF | B59: Ninguno | G59: Gastos Varios NT | H59: Ninguno | I59: =SUMIFS('Ing-Egr Junio 2026'!F4:F103,'Ing-Egr Junio 2026'!B4:B103,"Egreso NT",'Ing-Egr Junio 2026'!C4:C103,G59)
A60: Scribd | B60: Ninguno | G60: Reserva NT 1 | H60: Ninguno | I60: =SUMIFS('Ing-Egr Junio 2026'!F4:F103,'Ing-Egr Junio 2026'!B4:B103,"Egreso NT",'Ing-Egr Junio 2026'!C4:C103,G60)
A61: Netflix | B61: Ninguno | G61: Reserva NT 2 | H61: Ninguno | I61: =SUMIFS('Ing-Egr Junio 2026'!F4:F103,'Ing-Egr Junio 2026'!B4:B103,"Egreso NT",'Ing-Egr Junio 2026'!C4:C103,G61)
A62: ► GASTOS VARIABLES 🔗 | G62: Reserva NT 3 | H62: Ninguno | I62: =SUMIFS('Ing-Egr Junio 2026'!F4:F103,'Ing-Egr Junio 2026'!B4:B103,"Egreso NT",'Ing-Egr Junio 2026'!C4:C103,G62)
A63: Combustible | B63: Ninguno | C63: =SUMIFS('Ing-Egr Junio 2026'!F4:F103,'Ing-Egr Junio 2026'!B4:B103,"Egreso Familiar",'Ing-Egr Junio 2026'!C4:C103,A63)
A64: Supermercado | B64: Ninguno | C64: =SUMIFS('Ing-Egr Junio 2026'!F4:F103,'Ing-Egr Junio 2026'!B4:B103,"Egreso Familiar",'Ing-Egr Junio 2026'!C4:C103,A64) | G64: TOTAL NT PAGADOS | I64: =SUMIF(H30:H62,"Pagado",I30:I62)
A65: Farmacia | B65: Ninguno | C65: =SUMIFS('Ing-Egr Junio 2026'!F4:F103,'Ing-Egr Junio 2026'!B4:B103,"Egreso Familiar",'Ing-Egr Junio 2026'!C4:C103,A65) | D65: =C72 | G65: TOTAL NT PENDIENTES | I65: =SUMIF(H30:H62,"Pendiente",I30:I62)
A66: Recreación | B66: Ninguno | C66: =SUMIFS('Ing-Egr Junio 2026'!F4:F103,'Ing-Egr Junio 2026'!B4:B103,"Egreso Familiar",'Ing-Egr Junio 2026'!C4:C103,A66) | D66: =C73
A67: Gastos Varios | B67: Ninguno | C67: =SUMIFS('Ing-Egr Junio 2026'!F4:F103,'Ing-Egr Junio 2026'!B4:B103,"Egreso Familiar",'Ing-Egr Junio 2026'!C4:C103,A67) | G67: 📊 SALUD FINANCIERA NEUROTEA
A68: Reserva Fam 1 | B68: Ninguno | C68: =SUMIFS('Ing-Egr Junio 2026'!F4:F103,'Ing-Egr Junio 2026'!B4:B103,"Egreso Familiar",'Ing-Egr Junio 2026'!C4:C103,A68) | G68: Concepto | H68: % Ideal | I68: Monto Ideal | J68: Monto Real | K68: Estado
A69: Reserva Fam 2 | B69: Ninguno | C69: =SUMIFS('Ing-Egr Junio 2026'!F4:F103,'Ing-Egr Junio 2026'!B4:B103,"Egreso Familiar",'Ing-Egr Junio 2026'!C4:C103,A69) | G69: Gastos Operativos (máx 75%) | H69: 0.75 | I69: =J12*0.75 | J69: =I64+I65 | K69: =IF(J12=0,"-",IF(J69/J12<=0.75,"🟢 OK",IF(J69/J12<=0.9,"🟡 PRECAUCIÓN","🔴 ALARMA")))
A70: Reserva Fam 3 | B70: Ninguno | C70: =SUMIFS('Ing-Egr Junio 2026'!F4:F103,'Ing-Egr Junio 2026'!B4:B103,"Egreso Familiar",'Ing-Egr Junio 2026'!C4:C103,A70) | G70: Ganancia (10%) | H70: 0.1 | I70: =J12*0.1 | J70: =D22 | K70: =IF(J70>=I70,"🟢","🔴")
G71: Inversiones (5%) | H71: 0.05 | I71: =J12*0.05 | J71: 0 | K71: =IF(J71>=I71,"🟢","🔴")
A72: TOTAL FAM. PAGADOS | C72: =SUMIF(B30:B70,"Pagado",C30:C70) | G72: Imprevistos (5%) | H72: 0.05 | I72: =J12*0.05 | J72: 0 | K72: =IF(J72>=I72,"🟢","🔴")
A73: TOTAL FAM. PENDIENTES | C73: =SUMIF(B30:B70,"Pendiente",C30:C70) | G73: Desvío Imprevisto (5%) | H73: 0.05 | I73: =J12*0.05 | J73: 0 | K73: =IF(J73>=I73,"🟢","🔴")
G74: TOTAL | H74: =SUM(H69:H73) | I74: =SUM(I69:I73) | J74: =SUM(J69:J73)
G76: % GASTOS SOBRE INGRESO: | J76: =IF(J12=0,0,J69/J12)
G77: DIAGNÓSTICO: | J77: =IF(J12=0,"Sin datos",IF(J69/J12<=0.75,"🟢 CLÍNICA SANA",IF(J69/J12<=0.9,"🟡 REVISAR GASTOS","🔴 SITUACIÓN CRÍTICA")))

Sheet Ing-Egr Julio 2026
A1: 📋 REGISTRO DE MOVIMIENTOS - JULIO 2026
A3: Fecha | B3: Tipo | C3: Categoría | D3: Descripción | E3: Ingreso | F3: Egreso | G3: Cuenta | H3: Notas
A104: TOTALES | E104: =SUM(E4:E103) | F104: =SUM(F4:F103)
A106: 📊 RESUMEN DEL MES
A107: INGRESOS: | C107: =SUMIF(B4:B103,"Ingreso NT",E4:E103)
A108: Ingreso NT: | C108: =SUMIF(B4:B103,"Ingreso NT",E4:E103)
A109: Ingreso Marco: | C109: =SUMIF(B4:B103,"Ingreso Marco",E4:E103)
A110: Ingreso Clara: | C110: =SUMIF(B4:B103,"Ingreso Clara",E4:E103)
A111: Devolución Fam → NT: | C111: =SUMIF(B4:B103,"Devolución Familia → NT",E4:E103)
A112: TOTAL INGRESOS: | C112: =SUM(C108:C111)
A113: EGRESOS:
A114: EGRESOS: | C114: =SUMIF(B4:B103,"Egreso NT",F4:F103)
A115: Egreso NT: | C115: =SUMIF(B4:B103,"Egreso NT",F4:F103)
A116: Egreso Familiar: | C116: =SUMIF(B4:B103,"Egreso Familiar",F4:F103)
A117: Préstamo NT → Fam: | C117: =SUMIF(B4:B103,"Préstamo NT → Familia",F4:F103)
A118: TOTAL EGRESOS: | C118: =SUM(C115:C117)
A120: SALDO PRÉSTAMO NT → FAM: | C120: =C117-C111
A121: (Prestado - Devuelto)

Sheet Julio 2026
A1: 📊 CONTROL FINANCIERO - JULIO 2026
A3: TOTAL INGRESOS | D3: GASTOS PAGADOS | G3: GASTOS PENDIENTES | J3: BALANCE
A4: =D26+J12 | D4: =D65+I58 | G4: =D66+I59 | J4: =A4-D4-G4
A6: ⚠️ PRÉSTAMO NT → FAMILIA | D6: =SUMIF('Ing-Egr Julio 2026'!B4:B103,"Préstamo NT → Familia",'Ing-Egr Julio 2026'!F4:F103)-SUMIF('Ing-Egr Julio 2026'!B4:B103,"Devolución Familia → NT",'Ing-Egr Julio 2026'!E4:E103) | F6: Estado: | G6: =IF(D6=0,"🟢 SANO","🔴 FUGA") | I6: (Ideal = 0)
A8: 💵 INGRESOS FAMILIA | G8: 💵 INGRESOS NEUROTEA
A9: MARCO ITAIPU | C9: Fecha | D9: Monto | G9: Ingreso del Mes | J9: Monto
A10: Salario Mensual | D10: =SUMIFS('Ing-Egr Julio 2026'!E4:E103,'Ing-Egr Julio 2026'!B4:B103,"Ingreso Marco",'Ing-Egr Julio 2026'!C4:C103,A10) | G10: (Suma desde pestaña Ing-Egr Julio) | J10: =SUMIF('Ing-Egr Julio 2026'!B4:B103,"Ingreso NT",'Ing-Egr Julio 2026'!E4:E103)
A11: Vacaciones | D11: =SUMIFS('Ing-Egr Julio 2026'!E4:E103,'Ing-Egr Julio 2026'!B4:B103,"Ingreso Marco",'Ing-Egr Julio 2026'!C4:C103,A11)
A12: Aguinaldo | D12: =SUMIFS('Ing-Egr Julio 2026'!E4:E103,'Ing-Egr Julio 2026'!B4:B103,"Ingreso Marco",'Ing-Egr Julio 2026'!C4:C103,A12) | G12: ═══ TOTAL INGRESOS NT ═══ | J12: =J10
A13: Viático | D13: =SUMIFS('Ing-Egr Julio 2026'!E4:E103,'Ing-Egr Julio 2026'!B4:B103,"Ingreso Marco",'Ing-Egr Julio 2026'!C4:C103,A13)
A14: Animador Bíblico | D14: =SUMIFS('Ing-Egr Julio 2026'!E4:E103,'Ing-Egr Julio 2026'!B4:B103,"Ingreso Marco",'Ing-Egr Julio 2026'!C4:C103,A14)
A15: Otros Ocasionales | D15: =SUMIFS('Ing-Egr Julio 2026'!E4:E103,'Ing-Egr Julio 2026'!B4:B103,"Ingreso Marco",'Ing-Egr Julio 2026'!C4:C103,A15) | I15: =J12
A16: TOTAL MARCO | D16: =SUM(D10:D15)
A17: CLARA | C17: Fecha | D17: Monto
A18: Honorarios Diarios | D18: =SUMIF('Ing-Egr Julio 2026'!B4:B103,"Ingreso Clara",'Ing-Egr Julio 2026'!E4:E103)
A19: TOTAL CLARA | D19: =D18
A20: DESDE NEUROTEA | D20: Monto
A21: Salario Admin Marco | D21: 0
A22: Ganancia NT → Familia | D22: 0
A23: Préstamo NT (automático) | D23: =D6
A24: TOTAL DESDE NT | D24: =SUM(D21:D23)
A26: ═══ TOTAL INGRESOS FAMILIA ═══ | D26: =D16+D19+D24
A28: 📉 GASTOS FAMILIARES | G28: 📉 GASTOS NEUROTEA
A29: Detalle | B29: Estado | C29: Monto | D29: Venc. | G29: Detalle | H29: Estado | I29: Monto | J29: Venc.
A30: ► GASTOS FIJOS ✏️ | G30: ► GASTOS FIJOS ✏️
A31: Salario Lili Doméstico | B31: Ninguno | G31: Alquiler 1 (Principal) | H31: Ninguno | I31: 0
A32: Salario Laura Doméstico | B32: Ninguno | G32: Alquiler 2 (Secundario) | H32: Ninguno | I32: 0
A33: Escuela Fabián y Brenda | B33: Ninguno | G33: Limpieza NeuroTEA | H33: Ninguno | I33: 0
A34: Robótica Niños | B34: Ninguno | G34: ► SUELDOS Y HONORARIOS ✏️
A35: ANDE Casa | B35: Ninguno | G35: Sueldo Aracely | H35: Ninguno | I35: 0
A36: Expensa Casa | B36: Ninguno | G36: Sueldo Fátima | H36: Ninguno | I36: 0
A37: Cajubi Marco | B37: Ninguno | G37: Honorario Contador | H37: Ninguno | I37: 0
A38: Mutual Marco | B38: Ninguno | G38: Salario Administrador | H38: Ninguno | I38: 0
A39: Ña Luisa | B39: Ninguno | G39: Honorario Mant. Sistema | H39: Ninguno | I39: 0
A40: Seguro Médico Papá y Mamá | B40: Ninguno | G40: ► TELEFONÍA E INTERNET ✏️
A41: ► CUOTAS Y PRÉSTAMOS ✏️ | G41: Celular Tigo NeuroTEA | H41: Ninguno | I41: 0
A42: Auto Laura Cuota | B42: Ninguno | G42: Celular Tigo Sistema | H42: Ninguno | I42: 0
A43: Coop. Universitaria Clara | B43: Ninguno | G43: WhatsFlow | H43: Ninguno | I43: 0
A44: Coomecipar Clara | B44: Ninguno | G44: Internet NeuroTEA | H44: Ninguno | I44: 0
A45: Tarjeta Cred. Coomecipar | B45: Ninguno | G45: ► IMPUESTOS ✏️
A46: Solar Préstamo 1 | B46: Ninguno | G46: IVA | H46: Ninguno | I46: 0
A47: Solar Préstamo 2 | B47: Ninguno | G47: ► EVENTOS NT ✏️
A48: Préstamo Lizzi Sueldos | B48: Ninguno | G48: Día del Niño NT | H48: Ninguno | I48: 0
A49: Show Congelador | B49: Ninguno | G49: San Juan NT | H49: Ninguno | I49: 0
A50: Olier Heladera | B50: Ninguno | G50: Día del Autismo NT | H50: Ninguno | I50: 0
A51: ► SUSCRIPCIONES E INTERNET ✏️ | G51: Clausura Padres NT | H51: Ninguno | I51: 0
A52: Giganet | B52: Ninguno | G52: Navidad Papá Noel NT | H52: Ninguno | I52: 0
A53: Tigo Internet/Celulares | B53: Ninguno | G53: Cena Fin de Año NT | H53: Ninguno | I53: 0
A54: Tigo Familiar | B54: Ninguno | G54: ► GASTOS VARIABLES NT 🔗
A55: Google One | B55: Ninguno | G55: Insumos NT | H55: Ninguno | I55: =SUMIFS('Ing-Egr Julio 2026'!F4:F103,'Ing-Egr Julio 2026'!B4:B103,"Egreso NT",'Ing-Egr Julio 2026'!C4:C103,G55)
A56: ChatGPT | B56: Ninguno | G56: Papelería NT | H56: Ninguno | I56: =SUMIFS('Ing-Egr Julio 2026'!F4:F103,'Ing-Egr Julio 2026'!B4:B103,"Egreso NT",'Ing-Egr Julio 2026'!C4:C103,G56)
A57: Claude Marco | B57: Ninguno | G57: Mantenimiento NT | H57: Ninguno | I57: =SUMIFS('Ing-Egr Julio 2026'!F4:F103,'Ing-Egr Julio 2026'!B4:B103,"Egreso NT",'Ing-Egr Julio 2026'!C4:C103,G57)
A58: Claude Clara | B58: Ninguno | G58: Gastos Cursos NT | H58: Ninguno | I58: =SUMIFS('Ing-Egr Julio 2026'!F4:F103,'Ing-Egr Julio 2026'!B4:B103,"Egreso NT",'Ing-Egr Julio 2026'!C4:C103,G58)
A59: iLovePDF | B59: Ninguno | G59: Gastos Varios NT | H59: Ninguno | I59: =SUMIFS('Ing-Egr Julio 2026'!F4:F103,'Ing-Egr Julio 2026'!B4:B103,"Egreso NT",'Ing-Egr Julio 2026'!C4:C103,G59)
A60: Scribd | B60: Ninguno | G60: Reserva NT 1 | H60: Ninguno | I60: =SUMIFS('Ing-Egr Julio 2026'!F4:F103,'Ing-Egr Julio 2026'!B4:B103,"Egreso NT",'Ing-Egr Julio 2026'!C4:C103,G60)
A61: Netflix | B61: Ninguno | G61: Reserva NT 2 | H61: Ninguno | I61: =SUMIFS('Ing-Egr Julio 2026'!F4:F103,'Ing-Egr Julio 2026'!B4:B103,"Egreso NT",'Ing-Egr Julio 2026'!C4:C103,G61)
A62: ► GASTOS VARIABLES 🔗 | G62: Reserva NT 3 | H62: Ninguno | I62: =SUMIFS('Ing-Egr Julio 2026'!F4:F103,'Ing-Egr Julio 2026'!B4:B103,"Egreso NT",'Ing-Egr Julio 2026'!C4:C103,G62)
A63: Combustible | B63: Ninguno | C63: =SUMIFS('Ing-Egr Julio 2026'!F4:F103,'Ing-Egr Julio 2026'!B4:B103,"Egreso Familiar",'Ing-Egr Julio 2026'!C4:C103,A63)
A64: Supermercado | B64: Ninguno | C64: =SUMIFS('Ing-Egr Julio 2026'!F4:F103,'Ing-Egr Julio 2026'!B4:B103,"Egreso Familiar",'Ing-Egr Julio 2026'!C4:C103,A64) | G64: TOTAL NT PAGADOS | I64: =SUMIF(H30:H62,"Pagado",I30:I62)
A65: Farmacia | B65: Ninguno | C65: =SUMIFS('Ing-Egr Julio 2026'!F4:F103,'Ing-Egr Julio 2026'!B4:B103,"Egreso Familiar",'Ing-Egr Julio 2026'!C4:C103,A65) | D65: =C72 | G65: TOTAL NT PENDIENTES | I65: =SUMIF(H30:H62,"Pendiente",I30:I62)
A66: Recreación | B66: Ninguno | C66: =SUMIFS('Ing-Egr Julio 2026'!F4:F103,'Ing-Egr Julio 2026'!B4:B103,"Egreso Familiar",'Ing-Egr Julio 2026'!C4:C103,A66) | D66: =C73
A67: Gastos Varios | B67: Ninguno | C67: =SUMIFS('Ing-Egr Julio 2026'!F4:F103,'Ing-Egr Julio 2026'!B4:B103,"Egreso Familiar",'Ing-Egr Julio 2026'!C4:C103,A67) | G67: 📊 SALUD FINANCIERA NEUROTEA
A68: Reserva Fam 1 | B68: Ninguno | C68: =SUMIFS('Ing-Egr Julio 2026'!F4:F103,'Ing-Egr Julio 2026'!B4:B103,"Egreso Familiar",'Ing-Egr Julio 2026'!C4:C103,A68) | G68: Concepto | H68: % Ideal | I68: Monto Ideal | J68: Monto Real | K68: Estado
A69: Reserva Fam 2 | B69: Ninguno | C69: =SUMIFS('Ing-Egr Julio 2026'!F4:F103,'Ing-Egr Julio 2026'!B4:B103,"Egreso Familiar",'Ing-Egr Julio 2026'!C4:C103,A69) | G69: Gastos Operativos (máx 75%) | H69: 0.75 | I69: =J12*0.75 | J69: =I64+I65 | K69: =IF(J12=0,"-",IF(J69/J12<=0.75,"🟢 OK",IF(J69/J12<=0.9,"🟡 PRECAUCIÓN","🔴 ALARMA")))
A70: Reserva Fam 3 | B70: Ninguno | C70: =SUMIFS('Ing-Egr Julio 2026'!F4:F103,'Ing-Egr Julio 2026'!B4:B103,"Egreso Familiar",'Ing-Egr Julio 2026'!C4:C103,A70) | G70: Ganancia (10%) | H70: 0.1 | I70: =J12*0.1 | J70: =D22 | K70: =IF(J70>=I70,"🟢","🔴")
G71: Inversiones (5%) | H71: 0.05 | I71: =J12*0.05 | J71: 0 | K71: =IF(J71>=I71,"🟢","🔴")
A72: TOTAL FAM. PAGADOS | C72: =SUMIF(B30:B70,"Pagado",C30:C70) | G72: Imprevistos (5%) | H72: 0.05 | I72: =J12*0.05 | J72: 0 | K72: =IF(J72>=I72,"🟢","🔴")
A73: TOTAL FAM. PENDIENTES | C73: =SUMIF(B30:B70,"Pendiente",C30:C70) | G73: Desvío Imprevisto (5%) | H73: 0.05 | I73: =J12*0.05 | J73: 0 | K73: =IF(J73>=I73,"🟢","🔴")
G74: TOTAL | H74: =SUM(H69:H73) | I74: =SUM(I69:I73) | J74: =SUM(J69:J73)
G76: % GASTOS SOBRE INGRESO: | J76: =IF(J12=0,0,J69/J12)
G77: DIAGNÓSTICO: | J77: =IF(J12=0,"Sin datos",IF(J69/J12<=0.75,"🟢 CLÍNICA SANA",IF(J69/J12<=0.9,"🟡 REVISAR GASTOS","🔴 SITUACIÓN CRÍTICA")))

Sheet Ing-Egr Agosto 2026
A1: 📋 REGISTRO DE MOVIMIENTOS - AGOSTO 2026
A3: Fecha | B3: Tipo | C3: Categoría | D3: Descripción | E3: Ingreso | F3: Egreso | G3: Cuenta | H3: Notas
A104: TOTALES | E104: =SUM(E4:E103) | F104: =SUM(F4:F103)
A106: 📊 RESUMEN DEL MES
A107: INGRESOS: | C107: =SUMIF(B4:B103,"Ingreso NT",E4:E103)
A108: Ingreso NT: | C108: =SUMIF(B4:B103,"Ingreso NT",E4:E103)
A109: Ingreso Marco: | C109: =SUMIF(B4:B103,"Ingreso Marco",E4:E103)
A110: Ingreso Clara: | C110: =SUMIF(B4:B103,"Ingreso Clara",E4:E103)
A111: Devolución Fam → NT: | C111: =SUMIF(B4:B103,"Devolución Familia → NT",E4:E103)
A112: TOTAL INGRESOS: | C112: =SUM(C108:C111)
A113: EGRESOS:
A114: EGRESOS: | C114: =SUMIF(B4:B103,"Egreso NT",F4:F103)
A115: Egreso NT: | C115: =SUMIF(B4:B103,"Egreso NT",F4:F103)
A116: Egreso Familiar: | C116: =SUMIF(B4:B103,"Egreso Familiar",F4:F103)
A117: Préstamo NT → Fam: | C117: =SUMIF(B4:B103,"Préstamo NT → Familia",F4:F103)
A118: TOTAL EGRESOS: | C118: =SUM(C115:C117)
A120: SALDO PRÉSTAMO NT → FAM: | C120: =C117-C111
A121: (Prestado - Devuelto)

Sheet Agosto 2026
A1: 📊 CONTROL FINANCIERO - AGOSTO 2026
A3: TOTAL INGRESOS | D3: GASTOS PAGADOS | G3: GASTOS PENDIENTES | J3: BALANCE
A4: =D26+J12 | D4: =D65+I58 | G4: =D66+I59 | J4: =A4-D4-G4
A6: ⚠️ PRÉSTAMO NT → FAMILIA | D6: =SUMIF('Ing-Egr Agosto 2026'!B4:B103,"Préstamo NT → Familia",'Ing-Egr Agosto 2026'!F4:F103)-SUMIF('Ing-Egr Agosto 2026'!B4:B103,"Devolución Familia → NT",'Ing-Egr Agosto 2026'!E4:E103) | F6: Estado: | G6: =IF(D6=0,"🟢 SANO","🔴 FUGA") | I6: (Ideal = 0)
A8: 💵 INGRESOS FAMILIA | G8: 💵 INGRESOS NEUROTEA
A9: MARCO ITAIPU | C9: Fecha | D9: Monto | G9: Ingreso del Mes | J9: Monto
A10: Salario Mensual | D10: =SUMIFS('Ing-Egr Agosto 2026'!E4:E103,'Ing-Egr Agosto 2026'!B4:B103,"Ingreso Marco",'Ing-Egr Agosto 2026'!C4:C103,A10) | G10: (Suma desde pestaña Ing-Egr Agosto) | J10: =SUMIF('Ing-Egr Agosto 2026'!B4:B103,"Ingreso NT",'Ing-Egr Agosto 2026'!E4:E103)
A11: Vacaciones | D11: =SUMIFS('Ing-Egr Agosto 2026'!E4:E103,'Ing-Egr Agosto 2026'!B4:B103,"Ingreso Marco",'Ing-Egr Agosto 2026'!C4:C103,A11)
A12: Aguinaldo | D12: =SUMIFS('Ing-Egr Agosto 2026'!E4:E103,'Ing-Egr Agosto 2026'!B4:B103,"Ingreso Marco",'Ing-Egr Agosto 2026'!C4:C103,A12) | G12: ═══ TOTAL INGRESOS NT ═══ | J12: =J10
A13: Viático | D13: =SUMIFS('Ing-Egr Agosto 2026'!E4:E103,'Ing-Egr Agosto 2026'!B4:B103,"Ingreso Marco",'Ing-Egr Agosto 2026'!C4:C103,A13)
A14: Animador Bíblico | D14: =SUMIFS('Ing-Egr Agosto 2026'!E4:E103,'Ing-Egr Agosto 2026'!B4:B103,"Ingreso Marco",'Ing-Egr Agosto 2026'!C4:C103,A14)
A15: Otros Ocasionales | D15: =SUMIFS('Ing-Egr Agosto 2026'!E4:E103,'Ing-Egr Agosto 2026'!B4:B103,"Ingreso Marco",'Ing-Egr Agosto 2026'!C4:C103,A15) | I15: =J12
A16: TOTAL MARCO | D16: =SUM(D10:D15)
A17: CLARA | C17: Fecha | D17: Monto
A18: Honorarios Diarios | D18: =SUMIF('Ing-Egr Agosto 2026'!B4:B103,"Ingreso Clara",'Ing-Egr Agosto 2026'!E4:E103)
A19: TOTAL CLARA | D19: =D18
A20: DESDE NEUROTEA | D20: Monto
A21: Salario Admin Marco | D21: 0
A22: Ganancia NT → Familia | D22: 0
A23: Préstamo NT (automático) | D23: =D6
A24: TOTAL DESDE NT | D24: =SUM(D21:D23)
A26: ═══ TOTAL INGRESOS FAMILIA ═══ | D26: =D16+D19+D24
A28: 📉 GASTOS FAMILIARES | G28: 📉 GASTOS NEUROTEA
A29: Detalle | B29: Estado | C29: Monto | D29: Venc. | G29: Detalle | H29: Estado | I29: Monto | J29: Venc.
A30: ► GASTOS FIJOS ✏️ | G30: ► GASTOS FIJOS ✏️
A31: Salario Lili Doméstico | B31: Ninguno | G31: Alquiler 1 (Principal) | H31: Ninguno | I31: 0
A32: Salario Laura Doméstico | B32: Ninguno | G32: Alquiler 2 (Secundario) | H32: Ninguno | I32: 0
A33: Escuela Fabián y Brenda | B33: Ninguno | G33: Limpieza NeuroTEA | H33: Ninguno | I33: 0
A34: Robótica Niños | B34: Ninguno | G34: ► SUELDOS Y HONORARIOS ✏️
A35: ANDE Casa | B35: Ninguno | G35: Sueldo Aracely | H35: Ninguno | I35: 0
A36: Expensa Casa | B36: Ninguno | G36: Sueldo Fátima | H36: Ninguno | I36: 0
A37: Cajubi Marco | B37: Ninguno | G37: Honorario Contador | H37: Ninguno | I37: 0
A38: Mutual Marco | B38: Ninguno | G38: Salario Administrador | H38: Ninguno | I38: 0
A39: Ña Luisa | B39: Ninguno | G39: Honorario Mant. Sistema | H39: Ninguno | I39: 0
A40: Seguro Médico Papá y Mamá | B40: Ninguno | G40: ► TELEFONÍA E INTERNET ✏️
A41: ► CUOTAS Y PRÉSTAMOS ✏️ | G41: Celular Tigo NeuroTEA | H41: Ninguno | I41: 0
A42: Auto Laura Cuota | B42: Ninguno | G42: Celular Tigo Sistema | H42: Ninguno | I42: 0
A43: Coop. Universitaria Clara | B43: Ninguno | G43: WhatsFlow | H43: Ninguno | I43: 0
A44: Coomecipar Clara | B44: Ninguno | G44: Internet NeuroTEA | H44: Ninguno | I44: 0
A45: Tarjeta Cred. Coomecipar | B45: Ninguno | G45: ► IMPUESTOS ✏️
A46: Solar Préstamo 1 | B46: Ninguno | G46: IVA | H46: Ninguno | I46: 0
A47: Solar Préstamo 2 | B47: Ninguno | G47: ► EVENTOS NT ✏️
A48: Préstamo Lizzi Sueldos | B48: Ninguno | G48: Día del Niño NT | H48: Ninguno | I48: 0
A49: Show Congelador | B49: Ninguno | G49: San Juan NT | H49: Ninguno | I49: 0
A50: Olier Heladera | B50: Ninguno | G50: Día del Autismo NT | H50: Ninguno | I50: 0
A51: ► SUSCRIPCIONES E INTERNET ✏️ | G51: Clausura Padres NT | H51: Ninguno | I51: 0
A52: Giganet | B52: Ninguno | G52: Navidad Papá Noel NT | H52: Ninguno | I52: 0
A53: Tigo Internet/Celulares | B53: Ninguno | G53: Cena Fin de Año NT | H53: Ninguno | I53: 0
A54: Tigo Familiar | B54: Ninguno | G54: ► GASTOS VARIABLES NT 🔗
A55: Google One | B55: Ninguno | G55: Insumos NT | H55: Ninguno | I55: =SUMIFS('Ing-Egr Agosto 2026'!F4:F103,'Ing-Egr Agosto 2026'!B4:B103,"Egreso NT",'Ing-Egr Agosto 2026'!C4:C103,G55)
A56: ChatGPT | B56: Ninguno | G56: Papelería NT | H56: Ninguno | I56: =SUMIFS('Ing-Egr Agosto 2026'!F4:F103,'Ing-Egr Agosto 2026'!B4:B103,"Egreso NT",'Ing-Egr Agosto 2026'!C4:C103,G56)
A57: Claude Marco | B57: Ninguno | G57: Mantenimiento NT | H57: Ninguno | I57: =SUMIFS('Ing-Egr Agosto 2026'!F4:F103,'Ing-Egr Agosto 2026'!B4:B103,"Egreso NT",'Ing-Egr Agosto 2026'!C4:C103,G57)
A58: Claude Clara | B58: Ninguno | G58: Gastos Cursos NT | H58: Ninguno | I58: =SUMIFS('Ing-Egr Agosto 2026'!F4:F103,'Ing-Egr Agosto 2026'!B4:B103,"Egreso NT",'Ing-Egr Agosto 2026'!C4:C103,G58)
A59: iLovePDF | B59: Ninguno | G59: Gastos Varios NT | H59: Ninguno | I59: =SUMIFS('Ing-Egr Agosto 2026'!F4:F103,'Ing-Egr Agosto 2026'!B4:B103,"Egreso NT",'Ing-Egr Agosto 2026'!C4:C103,G59)
A60: Scribd | B60: Ninguno | G60: Reserva NT 1 | H60: Ninguno | I60: =SUMIFS('Ing-Egr Agosto 2026'!F4:F103,'Ing-Egr Agosto 2026'!B4:B103,"Egreso NT",'Ing-Egr Agosto 2026'!C4:C103,G60)
A61: Netflix | B61: Ninguno | G61: Reserva NT 2 | H61: Ninguno | I61: =SUMIFS('Ing-Egr Agosto 2026'!F4:F103,'Ing-Egr Agosto 2026'!B4:B103,"Egreso NT",'Ing-Egr Agosto 2026'!C4:C103,G61)
A62: ► GASTOS VARIABLES 🔗 | G62: Reserva NT 3 | H62: Ninguno | I62: =SUMIFS('Ing-Egr Agosto 2026'!F4:F103,'Ing-Egr Agosto 2026'!B4:B103,"Egreso NT",'Ing-Egr Agosto 2026'!C4:C103,G62)
A63: Combustible | B63: Ninguno | C63: =SUMIFS('Ing-Egr Agosto 2026'!F4:F103,'Ing-Egr Agosto 2026'!B4:B103,"Egreso Familiar",'Ing-Egr Agosto 2026'!C4:C103,A63)
A64: Supermercado | B64: Ninguno | C64: =SUMIFS('Ing-Egr Agosto 2026'!F4:F103,'Ing-Egr Agosto 2026'!B4:B103,"Egreso Familiar",'Ing-Egr Agosto 2026'!C4:C103,A64) | G64: TOTAL NT PAGADOS | I64: =SUMIF(H30:H62,"Pagado",I30:I62)
A65: Farmacia | B65: Ninguno | C65: =SUMIFS('Ing-Egr Agosto 2026'!F4:F103,'Ing-Egr Agosto 2026'!B4:B103,"Egreso Familiar",'Ing-Egr Agosto 2026'!C4:C103,A65) | D65: =C72 | G65: TOTAL NT PENDIENTES | I65: =SUMIF(H30:H62,"Pendiente",I30:I62)
A66: Recreación | B66: Ninguno | C66: =SUMIFS('Ing-Egr Agosto 2026'!F4:F103,'Ing-Egr Agosto 2026'!B4:B103,"Egreso Familiar",'Ing-Egr Agosto 2026'!C4:C103,A66) | D66: =C73
A67: Gastos Varios | B67: Ninguno | C67: =SUMIFS('Ing-Egr Agosto 2026'!F4:F103,'Ing-Egr Agosto 2026'!B4:B103,"Egreso Familiar",'Ing-Egr Agosto 2026'!C4:C103,A67) | G67: 📊 SALUD FINANCIERA NEUROTEA
A68: Reserva Fam 1 | B68: Ninguno | C68: =SUMIFS('Ing-Egr Agosto 2026'!F4:F103,'Ing-Egr Agosto 2026'!B4:B103,"Egreso Familiar",'Ing-Egr Agosto 2026'!C4:C103,A68) | G68: Concepto | H68: % Ideal | I68: Monto Ideal | J68: Monto Real | K68: Estado
A69: Reserva Fam 2 | B69: Ninguno | C69: =SUMIFS('Ing-Egr Agosto 2026'!F4:F103,'Ing-Egr Agosto 2026'!B4:B103,"Egreso Familiar",'Ing-Egr Agosto 2026'!C4:C103,A69) | G69: Gastos Operativos (máx 75%) | H69: 0.75 | I69: =J12*0.75 | J69: =I64+I65 | K69: =IF(J12=0,"-",IF(J69/J12<=0.75,"🟢 OK",IF(J69/J12<=0.9,"🟡 PRECAUCIÓN","🔴 ALARMA")))
A70: Reserva Fam 3 | B70: Ninguno | C70: =SUMIFS('Ing-Egr Agosto 2026'!F4:F103,'Ing-Egr Agosto 2026'!B4:B103,"Egreso Familiar",'Ing-Egr Agosto 2026'!C4:C103,A70) | G70: Ganancia (10%) | H70: 0.1 | I70: =J12*0.1 | J70: =D22 | K70: =IF(J70>=I70,"🟢","🔴")
G71: Inversiones (5%) | H71: 0.05 | I71: =J12*0.05 | J71: 0 | K71: =IF(J71>=I71,"🟢","🔴")
A72: TOTAL FAM. PAGADOS | C72: =SUMIF(B30:B70,"Pagado",C30:C70) | G72: Imprevistos (5%) | H72: 0.05 | I72: =J12*0.05 | J72: 0 | K72: =IF(J72>=I72,"🟢","🔴")
A73: TOTAL FAM. PENDIENTES | C73: =SUMIF(B30:B70,"Pendiente",C30:C70) | G73: Desvío Imprevisto (5%) | H73: 0.05 | I73: =J12*0.05 | J73: 0 | K73: =IF(J73>=I73,"🟢","🔴")
G74: TOTAL | H74: =SUM(H69:H73) | I74: =SUM(I69:I73) | J74: =SUM(J69:J73)
G76: % GASTOS SOBRE INGRESO: | J76: =IF(J12=0,0,J69/J12)
G77: DIAGNÓSTICO: | J77: =IF(J12=0,"Sin datos",IF(J69/J12<=0.75,"🟢 CLÍNICA SANA",IF(J69/J12<=0.9,"🟡 REVISAR GASTOS","🔴 SITUACIÓN CRÍTICA")))

Sheet Ing-Egr Septiembre 2026
A1: 📋 REGISTRO DE MOVIMIENTOS - SEPTIEMBRE 2026
A3: Fecha | B3: Tipo | C3: Categoría | D3: Descripción | E3: Ingreso | F3: Egreso | G3: Cuenta | H3: Notas
A104: TOTALES | E104: =SUM(E4:E103) | F104: =SUM(F4:F103)
A106: 📊 RESUMEN DEL MES
A107: INGRESOS: | C107: =SUMIF(B4:B103,"Ingreso NT",E4:E103)
A108: Ingreso NT: | C108: =SUMIF(B4:B103,"Ingreso NT",E4:E103)
A109: Ingreso Marco: | C109: =SUMIF(B4:B103,"Ingreso Marco",E4:E103)
A110: Ingreso Clara: | C110: =SUMIF(B4:B103,"Ingreso Clara",E4:E103)
A111: Devolución Fam → NT: | C111: =SUMIF(B4:B103,"Devolución Familia → NT",E4:E103)
A112: TOTAL INGRESOS: | C112: =SUM(C108:C111)
A113: EGRESOS:
A114: EGRESOS: | C114: =SUMIF(B4:B103,"Egreso NT",F4:F103)
A115: Egreso NT: | C115: =SUMIF(B4:B103,"Egreso NT",F4:F103)
A116: Egreso Familiar: | C116: =SUMIF(B4:B103,"Egreso Familiar",F4:F103)
A117: Préstamo NT → Fam: | C117: =SUMIF(B4:B103,"Préstamo NT → Familia",F4:F103)
A118: TOTAL EGRESOS: | C118: =SUM(C115:C117)
A120: SALDO PRÉSTAMO NT → FAM: | C120: =C117-C111
A121: (Prestado - Devuelto)

Sheet Septiembre 2026
A1: 📊 CONTROL FINANCIERO - SEPTIEMBRE 2026
A3: TOTAL INGRESOS | D3: GASTOS PAGADOS | G3: GASTOS PENDIENTES | J3: BALANCE
A4: =D26+J12 | D4: =D65+I58 | G4: =D66+I59 | J4: =A4-D4-G4
A6: ⚠️ PRÉSTAMO NT → FAMILIA | D6: =SUMIF('Ing-Egr Septiembre 2026'!B4:B103,"Préstamo NT → Familia",'Ing-Egr Septiembre 2026'!F4:F103)-SUMIF('Ing-Egr Septiembre 2026'!B4:B103,"Devolución Familia → NT",'Ing-Egr Septiembre 2026'!E4:E103) | F6: Estado: | G6: =IF(D6=0,"🟢 SANO","🔴 FUGA") | I6: (Ideal = 0)
A8: 💵 INGRESOS FAMILIA | G8: 💵 INGRESOS NEUROTEA
A9: MARCO ITAIPU | C9: Fecha | D9: Monto | G9: Ingreso del Mes | J9: Monto
A10: Salario Mensual | D10: =SUMIFS('Ing-Egr Septiembre 2026'!E4:E103,'Ing-Egr Septiembre 2026'!B4:B103,"Ingreso Marco",'Ing-Egr Septiembre 2026'!C4:C103,A10) | G10: (Suma desde pestaña Ing-Egr Septiembre) | J10: =SUMIF('Ing-Egr Septiembre 2026'!B4:B103,"Ingreso NT",'Ing-Egr Septiembre 2026'!E4:E103)
A11: Vacaciones | D11: =SUMIFS('Ing-Egr Septiembre 2026'!E4:E103,'Ing-Egr Septiembre 2026'!B4:B103,"Ingreso Marco",'Ing-Egr Septiembre 2026'!C4:C103,A11)
A12: Aguinaldo | D12: =SUMIFS('Ing-Egr Septiembre 2026'!E4:E103,'Ing-Egr Septiembre 2026'!B4:B103,"Ingreso Marco",'Ing-Egr Septiembre 2026'!C4:C103,A12) | G12: ═══ TOTAL INGRESOS NT ═══ | J12: =J10
A13: Viático | D13: =SUMIFS('Ing-Egr Septiembre 2026'!E4:E103,'Ing-Egr Septiembre 2026'!B4:B103,"Ingreso Marco",'Ing-Egr Septiembre 2026'!C4:C103,A13)
A14: Animador Bíblico | D14: =SUMIFS('Ing-Egr Septiembre 2026'!E4:E103,'Ing-Egr Septiembre 2026'!B4:B103,"Ingreso Marco",'Ing-Egr Septiembre 2026'!C4:C103,A14)
A15: Otros Ocasionales | D15: =SUMIFS('Ing-Egr Septiembre 2026'!E4:E103,'Ing-Egr Septiembre 2026'!B4:B103,"Ingreso Marco",'Ing-Egr Septiembre 2026'!C4:C103,A15) | I15: =J12
A16: TOTAL MARCO | D16: =SUM(D10:D15)
A17: CLARA | C17: Fecha | D17: Monto
A18: Honorarios Diarios | D18: =SUMIF('Ing-Egr Septiembre 2026'!B4:B103,"Ingreso Clara",'Ing-Egr Septiembre 2026'!E4:E103)
A19: TOTAL CLARA | D19: =D18
A20: DESDE NEUROTEA | D20: Monto
A21: Salario Admin Marco | D21: 0
A22: Ganancia NT → Familia | D22: 0
A23: Préstamo NT (automático) | D23: =D6
A24: TOTAL DESDE NT | D24: =SUM(D21:D23)
A26: ═══ TOTAL INGRESOS FAMILIA ═══ | D26: =D16+D19+D24
A28: 📉 GASTOS FAMILIARES | G28: 📉 GASTOS NEUROTEA
A29: Detalle | B29: Estado | C29: Monto | D29: Venc. | G29: Detalle | H29: Estado | I29: Monto | J29: Venc.
A30: ► GASTOS FIJOS ✏️ | G30: ► GASTOS FIJOS ✏️
A31: Salario Lili Doméstico | B31: Ninguno | G31: Alquiler 1 (Principal) | H31: Ninguno | I31: 0
A32: Salario Laura Doméstico | B32: Ninguno | G32: Alquiler 2 (Secundario) | H32: Ninguno | I32: 0
A33: Escuela Fabián y Brenda | B33: Ninguno | G33: Limpieza NeuroTEA | H33: Ninguno | I33: 0
A34: Robótica Niños | B34: Ninguno | G34: ► SUELDOS Y HONORARIOS ✏️
A35: ANDE Casa | B35: Ninguno | G35: Sueldo Aracely | H35: Ninguno | I35: 0
A36: Expensa Casa | B36: Ninguno | G36: Sueldo Fátima | H36: Ninguno | I36: 0
A37: Cajubi Marco | B37: Ninguno | G37: Honorario Contador | H37: Ninguno | I37: 0
A38: Mutual Marco | B38: Ninguno | G38: Salario Administrador | H38: Ninguno | I38: 0
A39: Ña Luisa | B39: Ninguno | G39: Honorario Mant. Sistema | H39: Ninguno | I39: 0
A40: Seguro Médico Papá y Mamá | B40: Ninguno | G40: ► TELEFONÍA E INTERNET ✏️
A41: ► CUOTAS Y PRÉSTAMOS ✏️ | G41: Celular Tigo NeuroTEA | H41: Ninguno | I41: 0
A42: Auto Laura Cuota | B42: Ninguno | G42: Celular Tigo Sistema | H42: Ninguno | I42: 0
A43: Coop. Universitaria Clara | B43: Ninguno | G43: WhatsFlow | H43: Ninguno | I43: 0
A44: Coomecipar Clara | B44: Ninguno | G44: Internet NeuroTEA | H44: Ninguno | I44: 0
A45: Tarjeta Cred. Coomecipar | B45: Ninguno | G45: ► IMPUESTOS ✏️
A46: Solar Préstamo 1 | B46: Ninguno | G46: IVA | H46: Ninguno | I46: 0
A47: Solar Préstamo 2 | B47: Ninguno | G47: ► EVENTOS NT ✏️
A48: Préstamo Lizzi Sueldos | B48: Ninguno | G48: Día del Niño NT | H48: Ninguno | I48: 0
A49: Show Congelador | B49: Ninguno | G49: San Juan NT | H49: Ninguno | I49: 0
A50: Olier Heladera | B50: Ninguno | G50: Día del Autismo NT | H50: Ninguno | I50: 0
A51: ► SUSCRIPCIONES E INTERNET ✏️ | G51: Clausura Padres NT | H51: Ninguno | I51: 0
A52: Giganet | B52: Ninguno | G52: Navidad Papá Noel NT | H52: Ninguno | I52: 0
A53: Tigo Internet/Celulares | B53: Ninguno | G53: Cena Fin de Año NT | H53: Ninguno | I53: 0
A54: Tigo Familiar | B54: Ninguno | G54: ► GASTOS VARIABLES NT 🔗
A55: Google One | B55: Ninguno | G55: Insumos NT | H55: Ninguno | I55: =SUMIFS('Ing-Egr Septiembre 2026'!F4:F103,'Ing-Egr Septiembre 2026'!B4:B103,"Egreso NT",'Ing-Egr Septiembre 2026'!C4:C103,G55)
A56: ChatGPT | B56: Ninguno | G56: Papelería NT | H56: Ninguno | I56: =SUMIFS('Ing-Egr Septiembre 2026'!F4:F103,'Ing-Egr Septiembre 2026'!B4:B103,"Egreso NT",'Ing-Egr Septiembre 2026'!C4:C103,G56)
A57: Claude Marco | B57: Ninguno | G57: Mantenimiento NT | H57: Ninguno | I57: =SUMIFS('Ing-Egr Septiembre 2026'!F4:F103,'Ing-Egr Septiembre 2026'!B4:B103,"Egreso NT",'Ing-Egr Septiembre 2026'!C4:C103,G57)
A58: Claude Clara | B58: Ninguno | G58: Gastos Cursos NT | H58: Ninguno | I58: =SUMIFS('Ing-Egr Septiembre 2026'!F4:F103,'Ing-Egr Septiembre 2026'!B4:B103,"Egreso NT",'Ing-Egr Septiembre 2026'!C4:C103,G58)
A59: iLovePDF | B59: Ninguno | G59: Gastos Varios NT | H59: Ninguno | I59: =SUMIFS('Ing-Egr Septiembre 2026'!F4:F103,'Ing-Egr Septiembre 2026'!B4:B103,"Egreso NT",'Ing-Egr Septiembre 2026'!C4:C103,G59)
A60: Scribd | B60: Ninguno | G60: Reserva NT 1 | H60: Ninguno | I60: =SUMIFS('Ing-Egr Septiembre 2026'!F4:F103,'Ing-Egr Septiembre 2026'!B4:B103,"Egreso NT",'Ing-Egr Septiembre 2026'!C4:C103,G60)
A61: Netflix | B61: Ninguno | G61: Reserva NT 2 | H61: Ninguno | I61: =SUMIFS('Ing-Egr Septiembre 2026'!F4:F103,'Ing-Egr Septiembre 2026'!B4:B103,"Egreso NT",'Ing-Egr Septiembre 2026'!C4:C103,G61)
A62: ► GASTOS VARIABLES 🔗 | G62: Reserva NT 3 | H62: Ninguno | I62: =SUMIFS('Ing-Egr Septiembre 2026'!F4:F103,'Ing-Egr Septiembre 2026'!B4:B103,"Egreso NT",'Ing-Egr Septiembre 2026'!C4:C103,G62)
A63: Combustible | B63: Ninguno | C63: =SUMIFS('Ing-Egr Septiembre 2026'!F4:F103,'Ing-Egr Septiembre 2026'!B4:B103,"Egreso Familiar",'Ing-Egr Septiembre 2026'!C4:C103,A63)
A64: Supermercado | B64: Ninguno | C64: =SUMIFS('Ing-Egr Septiembre 2026'!F4:F103,'Ing-Egr Septiembre 2026'!B4:B103,"Egreso Familiar",'Ing-Egr Septiembre 2026'!C4:C103,A64) | G64: TOTAL NT PAGADOS | I64: =SUMIF(H30:H62,"Pagado",I30:I62)
A65: Farmacia | B65: Ninguno | C65: =SUMIFS('Ing-Egr Septiembre 2026'!F4:F103,'Ing-Egr Septiembre 2026'!B4:B103,"Egreso Familiar",'Ing-Egr Septiembre 2026'!C4:C103,A65) | D65: =C72 | G65: TOTAL NT PENDIENTES | I65: =SUMIF(H30:H62,"Pendiente",I30:I62)
A66: Recreación | B66: Ninguno | C66: =SUMIFS('Ing-Egr Septiembre 2026'!F4:F103,'Ing-Egr Septiembre 2026'!B4:B103,"Egreso Familiar",'Ing-Egr Septiembre 2026'!C4:C103,A66) | D66: =C73
A67: Gastos Varios | B67: Ninguno | C67: =SUMIFS('Ing-Egr Septiembre 2026'!F4:F103,'Ing-Egr Septiembre 2026'!B4:B103,"Egreso Familiar",'Ing-Egr Septiembre 2026'!C4:C103,A67) | G67: 📊 SALUD FINANCIERA NEUROTEA
A68: Reserva Fam 1 | B68: Ninguno | C68: =SUMIFS('Ing-Egr Septiembre 2026'!F4:F103,'Ing-Egr Septiembre 2026'!B4:B103,"Egreso Familiar",'Ing-Egr Septiembre 2026'!C4:C103,A68) | G68: Concepto | H68: % Ideal | I68: Monto Ideal | J68: Monto Real | K68: Estado
A69: Reserva Fam 2 | B69: Ninguno | C69: =SUMIFS('Ing-Egr Septiembre 2026'!F4:F103,'Ing-Egr Septiembre 2026'!B4:B103,"Egreso Familiar",'Ing-Egr Septiembre 2026'!C4:C103,A69) | G69: Gastos Operativos (máx 75%) | H69: 0.75 | I69: =J12*0.75 | J69: =I64+I65 | K69: =IF(J12=0,"-",IF(J69/J12<=0.75,"🟢 OK",IF(J69/J12<=0.9,"🟡 PRECAUCIÓN","🔴 ALARMA")))
A70: Reserva Fam 3 | B70: Ninguno | C70: =SUMIFS('Ing-Egr Septiembre 2026'!F4:F103,'Ing-Egr Septiembre 2026'!B4:B103,"Egreso Familiar",'Ing-Egr Septiembre 2026'!C4:C103,A70) | G70: Ganancia (10%) | H70: 0.1 | I70: =J12*0.1 | J70: =D22 | K70: =IF(J70>=I70,"🟢","🔴")
G71: Inversiones (5%) | H71: 0.05 | I71: =J12*0.05 | J71: 0 | K71: =IF(J71>=I71,"🟢","🔴")
A72: TOTAL FAM. PAGADOS | C72: =SUMIF(B30:B70,"Pagado",C30:C70) | G72: Imprevistos (5%) | H72: 0.05 | I72: =J12*0.05 | J72: 0 | K72: =IF(J72>=I72,"🟢","🔴")
A73: TOTAL FAM. PENDIENTES | C73: =SUMIF(B30:B70,"Pendiente",C30:C70) | G73: Desvío Imprevisto (5%) | H73: 0.05 | I73: =J12*0.05 | J73: 0 | K73: =IF(J73>=I73,"🟢","🔴")
G74: TOTAL | H74: =SUM(H69:H73) | I74: =SUM(I69:I73) | J74: =SUM(J69:J73)
G76: % GASTOS SOBRE INGRESO: | J76: =IF(J12=0,0,J69/J12)
G77: DIAGNÓSTICO: | J77: =IF(J12=0,"Sin datos",IF(J69/J12<=0.75,"🟢 CLÍNICA SANA",IF(J69/J12<=0.9,"🟡 REVISAR GASTOS","🔴 SITUACIÓN CRÍTICA")))

Sheet Ing-Egr Octubre 2026
A1: 📋 REGISTRO DE MOVIMIENTOS - OCTUBRE 2026
A3: Fecha | B3: Tipo | C3: Categoría | D3: Descripción | E3: Ingreso | F3: Egreso | G3: Cuenta | H3: Notas
A104: TOTALES | E104: =SUM(E4:E103) | F104: =SUM(F4:F103)
A106: 📊 RESUMEN DEL MES
A107: INGRESOS: | C107: =SUMIF(B4:B103,"Ingreso NT",E4:E103)
A108: Ingreso NT: | C108: =SUMIF(B4:B103,"Ingreso NT",E4:E103)
A109: Ingreso Marco: | C109: =SUMIF(B4:B103,"Ingreso Marco",E4:E103)
A110: Ingreso Clara: | C110: =SUMIF(B4:B103,"Ingreso Clara",E4:E103)
A111: Devolución Fam → NT: | C111: =SUMIF(B4:B103,"Devolución Familia → NT",E4:E103)
A112: TOTAL INGRESOS: | C112: =SUM(C108:C111)
A113: EGRESOS:
A114: EGRESOS: | C114: =SUMIF(B4:B103,"Egreso NT",F4:F103)
A115: Egreso NT: | C115: =SUMIF(B4:B103,"Egreso NT",F4:F103)
A116: Egreso Familiar: | C116: =SUMIF(B4:B103,"Egreso Familiar",F4:F103)
A117: Préstamo NT → Fam: | C117: =SUMIF(B4:B103,"Préstamo NT → Familia",F4:F103)
A118: TOTAL EGRESOS: | C118: =SUM(C115:C117)
A120: SALDO PRÉSTAMO NT → FAM: | C120: =C117-C111
A121: (Prestado - Devuelto)

Sheet Octubre 2026
A1: 📊 CONTROL FINANCIERO - OCTUBRE 2026
A3: TOTAL INGRESOS | D3: GASTOS PAGADOS | G3: GASTOS PENDIENTES | J3: BALANCE
A4: =D26+J12 | D4: =D65+I58 | G4: =D66+I59 | J4: =A4-D4-G4
A6: ⚠️ PRÉSTAMO NT → FAMILIA | D6: =SUMIF('Ing-Egr Octubre 2026'!B4:B103,"Préstamo NT → Familia",'Ing-Egr Octubre 2026'!F4:F103)-SUMIF('Ing-Egr Octubre 2026'!B4:B103,"Devolución Familia → NT",'Ing-Egr Octubre 2026'!E4:E103) | F6: Estado: | G6: =IF(D6=0,"🟢 SANO","🔴 FUGA") | I6: (Ideal = 0)
A8: 💵 INGRESOS FAMILIA | G8: 💵 INGRESOS NEUROTEA
A9: MARCO ITAIPU | C9: Fecha | D9: Monto | G9: Ingreso del Mes | J9: Monto
A10: Salario Mensual | D10: =SUMIFS('Ing-Egr Octubre 2026'!E4:E103,'Ing-Egr Octubre 2026'!B4:B103,"Ingreso Marco",'Ing-Egr Octubre 2026'!C4:C103,A10) | G10: (Suma desde pestaña Ing-Egr Octubre) | J10: =SUMIF('Ing-Egr Octubre 2026'!B4:B103,"Ingreso NT",'Ing-Egr Octubre 2026'!E4:E103)
A11: Vacaciones | D11: =SUMIFS('Ing-Egr Octubre 2026'!E4:E103,'Ing-Egr Octubre 2026'!B4:B103,"Ingreso Marco",'Ing-Egr Octubre 2026'!C4:C103,A11)
A12: Aguinaldo | D12: =SUMIFS('Ing-Egr Octubre 2026'!E4:E103,'Ing-Egr Octubre 2026'!B4:B103,"Ingreso Marco",'Ing-Egr Octubre 2026'!C4:C103,A12) | G12: ═══ TOTAL INGRESOS NT ═══ | J12: =J10
A13: Viático | D13: =SUMIFS('Ing-Egr Octubre 2026'!E4:E103,'Ing-Egr Octubre 2026'!B4:B103,"Ingreso Marco",'Ing-Egr Octubre 2026'!C4:C103,A13)
A14: Animador Bíblico | D14: =SUMIFS('Ing-Egr Octubre 2026'!E4:E103,'Ing-Egr Octubre 2026'!B4:B103,"Ingreso Marco",'Ing-Egr Octubre 2026'!C4:C103,A14)
A15: Otros Ocasionales | D15: =SUMIFS('Ing-Egr Octubre 2026'!E4:E103,'Ing-Egr Octubre 2026'!B4:B103,"Ingreso Marco",'Ing-Egr Octubre 2026'!C4:C103,A15) | I15: =J12
A16: TOTAL MARCO | D16: =SUM(D10:D15)
A17: CLARA | C17: Fecha | D17: Monto
A18: Honorarios Diarios | D18: =SUMIF('Ing-Egr Octubre 2026'!B4:B103,"Ingreso Clara",'Ing-Egr Octubre 2026'!E4:E103)
A19: TOTAL CLARA | D19: =D18
A20: DESDE NEUROTEA | D20: Monto
A21: Salario Admin Marco | D21: 0
A22: Ganancia NT → Familia | D22: 0
A23: Préstamo NT (automático) | D23: =D6
A24: TOTAL DESDE NT | D24: =SUM(D21:D23)
A26: ═══ TOTAL INGRESOS FAMILIA ═══ | D26: =D16+D19+D24
A28: 📉 GASTOS FAMILIARES | G28: 📉 GASTOS NEUROTEA
A29: Detalle | B29: Estado | C29: Monto | D29: Venc. | G29: Detalle | H29: Estado | I29: Monto | J29: Venc.
A30: ► GASTOS FIJOS ✏️ | G30: ► GASTOS FIJOS ✏️
A31: Salario Lili Doméstico | B31: Ninguno | G31: Alquiler 1 (Principal) | H31: Ninguno | I31: 0
A32: Salario Laura Doméstico | B32: Ninguno | G32: Alquiler 2 (Secundario) | H32: Ninguno | I32: 0
A33: Escuela Fabián y Brenda | B33: Ninguno | G33: Limpieza NeuroTEA | H33: Ninguno | I33: 0
A34: Robótica Niños | B34: Ninguno | G34: ► SUELDOS Y HONORARIOS ✏️
A35: ANDE Casa | B35: Ninguno | G35: Sueldo Aracely | H35: Ninguno | I35: 0
A36: Expensa Casa | B36: Ninguno | G36: Sueldo Fátima | H36: Ninguno | I36: 0
A37: Cajubi Marco | B37: Ninguno | G37: Honorario Contador | H37: Ninguno | I37: 0
A38: Mutual Marco | B38: Ninguno | G38: Salario Administrador | H38: Ninguno | I38: 0
A39: Ña Luisa | B39: Ninguno | G39: Honorario Mant. Sistema | H39: Ninguno | I39: 0
A40: Seguro Médico Papá y Mamá | B40: Ninguno | G40: ► TELEFONÍA E INTERNET ✏️
A41: ► CUOTAS Y PRÉSTAMOS ✏️ | G41: Celular Tigo NeuroTEA | H41: Ninguno | I41: 0
A42: Auto Laura Cuota | B42: Ninguno | G42: Celular Tigo Sistema | H42: Ninguno | I42: 0
A43: Coop. Universitaria Clara | B43: Ninguno | G43: WhatsFlow | H43: Ninguno | I43: 0
A44: Coomecipar Clara | B44: Ninguno | G44: Internet NeuroTEA | H44: Ninguno | I44: 0
A45: Tarjeta Cred. Coomecipar | B45: Ninguno | G45: ► IMPUESTOS ✏️
A46: Solar Préstamo 1 | B46: Ninguno | G46: IVA | H46: Ninguno | I46: 0
A47: Solar Préstamo 2 | B47: Ninguno | G47: ► EVENTOS NT ✏️
A48: Préstamo Lizzi Sueldos | B48: Ninguno | G48: Día del Niño NT | H48: Ninguno | I48: 0
A49: Show Congelador | B49: Ninguno | G49: San Juan NT | H49: Ninguno | I49: 0
A50: Olier Heladera | B50: Ninguno | G50: Día del Autismo NT | H50: Ninguno | I50: 0
A51: ► SUSCRIPCIONES E INTERNET ✏️ | G51: Clausura Padres NT | H51: Ninguno | I51: 0
A52: Giganet | B52: Ninguno | G52: Navidad Papá Noel NT | H52: Ninguno | I52: 0
A53: Tigo Internet/Celulares | B53: Ninguno | G53: Cena Fin de Año NT | H53: Ninguno | I53: 0
A54: Tigo Familiar | B54: Ninguno | G54: ► GASTOS VARIABLES NT 🔗
A55: Google One | B55: Ninguno | G55: Insumos NT | H55: Ninguno | I55: =SUMIFS('Ing-Egr Octubre 2026'!F4:F103,'Ing-Egr Octubre 2026'!B4:B103,"Egreso NT",'Ing-Egr Octubre 2026'!C4:C103,G55)
A56: ChatGPT | B56: Ninguno | G56: Papelería NT | H56: Ninguno | I56: =SUMIFS('Ing-Egr Octubre 2026'!F4:F103,'Ing-Egr Octubre 2026'!B4:B103,"Egreso NT",'Ing-Egr Octubre 2026'!C4:C103,G56)
A57: Claude Marco | B57: Ninguno | G57: Mantenimiento NT | H57: Ninguno | I57: =SUMIFS('Ing-Egr Octubre 2026'!F4:F103,'Ing-Egr Octubre 2026'!B4:B103,"Egreso NT",'Ing-Egr Octubre 2026'!C4:C103,G57)
A58: Claude Clara | B58: Ninguno | G58: Gastos Cursos NT | H58: Ninguno | I58: =SUMIFS('Ing-Egr Octubre 2026'!F4:F103,'Ing-Egr Octubre 2026'!B4:B103,"Egreso NT",'Ing-Egr Octubre 2026'!C4:C103,G58)
A59: iLovePDF | B59: Ninguno | G59: Gastos Varios NT | H59: Ninguno | I59: =SUMIFS('Ing-Egr Octubre 2026'!F4:F103,'Ing-Egr Octubre 2026'!B4:B103,"Egreso NT",'Ing-Egr Octubre 2026'!C4:C103,G59)
A60: Scribd | B60: Ninguno | G60: Reserva NT 1 | H60: Ninguno | I60: =SUMIFS('Ing-Egr Octubre 2026'!F4:F103,'Ing-Egr Octubre 2026'!B4:B103,"Egreso NT",'Ing-Egr Octubre 2026'!C4:C103,G60)
A61: Netflix | B61: Ninguno | G61: Reserva NT 2 | H61: Ninguno | I61: =SUMIFS('Ing-Egr Octubre 2026'!F4:F103,'Ing-Egr Octubre 2026'!B4:B103,"Egreso NT",'Ing-Egr Octubre 2026'!C4:C103,G61)
A62: ► GASTOS VARIABLES 🔗 | G62: Reserva NT 3 | H62: Ninguno | I62: =SUMIFS('Ing-Egr Octubre 2026'!F4:F103,'Ing-Egr Octubre 2026'!B4:B103,"Egreso NT",'Ing-Egr Octubre 2026'!C4:C103,G62)
A63: Combustible | B63: Ninguno | C63: =SUMIFS('Ing-Egr Octubre 2026'!F4:F103,'Ing-Egr Octubre 2026'!B4:B103,"Egreso Familiar",'Ing-Egr Octubre 2026'!C4:C103,A63)
A64: Supermercado | B64: Ninguno | C64: =SUMIFS('Ing-Egr Octubre 2026'!F4:F103,'Ing-Egr Octubre 2026'!B4:B103,"Egreso Familiar",'Ing-Egr Octubre 2026'!C4:C103,A64) | G64: TOTAL NT PAGADOS | I64: =SUMIF(H30:H62,"Pagado",I30:I62)
A65: Farmacia | B65: Ninguno | C65: =SUMIFS('Ing-Egr Octubre 2026'!F4:F103,'Ing-Egr Octubre 2026'!B4:B103,"Egreso Familiar",'Ing-Egr Octubre 2026'!C4:C103,A65) | D65: =C72 | G65: TOTAL NT PENDIENTES | I65: =SUMIF(H30:H62,"Pendiente",I30:I62)
A66: Recreación | B66: Ninguno | C66: =SUMIFS('Ing-Egr Octubre 2026'!F4:F103,'Ing-Egr Octubre 2026'!B4:B103,"Egreso Familiar",'Ing-Egr Octubre 2026'!C4:C103,A66) | D66: =C73
A67: Gastos Varios | B67: Ninguno | C67: =SUMIFS('Ing-Egr Octubre 2026'!F4:F103,'Ing-Egr Octubre 2026'!B4:B103,"Egreso Familiar",'Ing-Egr Octubre 2026'!C4:C103,A67) | G67: 📊 SALUD FINANCIERA NEUROTEA
A68: Reserva Fam 1 | B68: Ninguno | C68: =SUMIFS('Ing-Egr Octubre 2026'!F4:F103,'Ing-Egr Octubre 2026'!B4:B103,"Egreso Familiar",'Ing-Egr Octubre 2026'!C4:C103,A68) | G68: Concepto | H68: % Ideal | I68: Monto Ideal | J68: Monto Real | K68: Estado
A69: Reserva Fam 2 | B69: Ninguno | C69: =SUMIFS('Ing-Egr Octubre 2026'!F4:F103,'Ing-Egr Octubre 2026'!B4:B103,"Egreso Familiar",'Ing-Egr Octubre 2026'!C4:C103,A69) | G69: Gastos Operativos (máx 75%) | H69: 0.75 | I69: =J12*0.75 | J69: =I64+I65 | K69: =IF(J12=0,"-",IF(J69/J12<=0.75,"🟢 OK",IF(J69/J12<=0.9,"🟡 PRECAUCIÓN","🔴 ALARMA")))
A70: Reserva Fam 3 | B70: Ninguno | C70: =SUMIFS('Ing-Egr Octubre 2026'!F4:F103,'Ing-Egr Octubre 2026'!B4:B103,"Egreso Familiar",'Ing-Egr Octubre 2026'!C4:C103,A70) | G70: Ganancia (10%) | H70: 0.1 | I70: =J12*0.1 | J70: =D22 | K70: =IF(J70>=I70,"🟢","🔴")
G71: Inversiones (5%) | H71: 0.05 | I71: =J12*0.05 | J71: 0 | K71: =IF(J71>=I71,"🟢","🔴")
A72: TOTAL FAM. PAGADOS | C72: =SUMIF(B30:B70,"Pagado",C30:C70) | G72: Imprevistos (5%) | H72: 0.05 | I72: =J12*0.05 | J72: 0 | K72: =IF(J72>=I72,"🟢","🔴")
A73: TOTAL FAM. PENDIENTES | C73: =SUMIF(B30:B70,"Pendiente",C30:C70) | G73: Desvío Imprevisto (5%) | H73: 0.05 | I73: =J12*0.05 | J73: 0 | K73: =IF(J73>=I73,"🟢","🔴")
G74: TOTAL | H74: =SUM(H69:H73) | I74: =SUM(I69:I73) | J74: =SUM(J69:J73)
G76: % GASTOS SOBRE INGRESO: | J76: =IF(J12=0,0,J69/J12)
G77: DIAGNÓSTICO: | J77: =IF(J12=0,"Sin datos",IF(J69/J12<=0.75,"🟢 CLÍNICA SANA",IF(J69/J12<=0.9,"🟡 REVISAR GASTOS","🔴 SITUACIÓN CRÍTICA")))

Sheet Ing-Egr Noviembre 2026
A1: 📋 REGISTRO DE MOVIMIENTOS - NOVIEMBRE 2026
A3: Fecha | B3: Tipo | C3: Categoría | D3: Descripción | E3: Ingreso | F3: Egreso | G3: Cuenta | H3: Notas
A104: TOTALES | E104: =SUM(E4:E103) | F104: =SUM(F4:F103)
A106: 📊 RESUMEN DEL MES
A107: INGRESOS: | C107: =SUMIF(B4:B103,"Ingreso NT",E4:E103)
A108: Ingreso NT: | C108: =SUMIF(B4:B103,"Ingreso NT",E4:E103)
A109: Ingreso Marco: | C109: =SUMIF(B4:B103,"Ingreso Marco",E4:E103)
A110: Ingreso Clara: | C110: =SUMIF(B4:B103,"Ingreso Clara",E4:E103)
A111: Devolución Fam → NT: | C111: =SUMIF(B4:B103,"Devolución Familia → NT",E4:E103)
A112: TOTAL INGRESOS: | C112: =SUM(C108:C111)
A113: EGRESOS:
A114: EGRESOS: | C114: =SUMIF(B4:B103,"Egreso NT",F4:F103)
A115: Egreso NT: | C115: =SUMIF(B4:B103,"Egreso NT",F4:F103)
A116: Egreso Familiar: | C116: =SUMIF(B4:B103,"Egreso Familiar",F4:F103)
A117: Préstamo NT → Fam: | C117: =SUMIF(B4:B103,"Préstamo NT → Familia",F4:F103)
A118: TOTAL EGRESOS: | C118: =SUM(C115:C117)
A120: SALDO PRÉSTAMO NT → FAM: | C120: =C117-C111
A121: (Prestado - Devuelto)

Sheet Noviembre 2026
A1: 📊 CONTROL FINANCIERO - NOVIEMBRE 2026
A3: TOTAL INGRESOS | D3: GASTOS PAGADOS | G3: GASTOS PENDIENTES | J3: BALANCE
A4: =D26+J12 | D4: =D65+I58 | G4: =D66+I59 | J4: =A4-D4-G4
A6: ⚠️ PRÉSTAMO NT → FAMILIA | D6: =SUMIF('Ing-Egr Noviembre 2026'!B4:B103,"Préstamo NT → Familia",'Ing-Egr Noviembre 2026'!F4:F103)-SUMIF('Ing-Egr Noviembre 2026'!B4:B103,"Devolución Familia → NT",'Ing-Egr Noviembre 2026'!E4:E103) | F6: Estado: | G6: =IF(D6=0,"🟢 SANO","🔴 FUGA") | I6: (Ideal = 0)
A8: 💵 INGRESOS FAMILIA | G8: 💵 INGRESOS NEUROTEA
A9: MARCO ITAIPU | C9: Fecha | D9: Monto | G9: Ingreso del Mes | J9: Monto
A10: Salario Mensual | D10: =SUMIFS('Ing-Egr Noviembre 2026'!E4:E103,'Ing-Egr Noviembre 2026'!B4:B103,"Ingreso Marco",'Ing-Egr Noviembre 2026'!C4:C103,A10) | G10: (Suma desde pestaña Ing-Egr Noviembre) | J10: =SUMIF('Ing-Egr Noviembre 2026'!B4:B103,"Ingreso NT",'Ing-Egr Noviembre 2026'!E4:E103)
A11: Vacaciones | D11: =SUMIFS('Ing-Egr Noviembre 2026'!E4:E103,'Ing-Egr Noviembre 2026'!B4:B103,"Ingreso Marco",'Ing-Egr Noviembre 2026'!C4:C103,A11)
A12: Aguinaldo | D12: =SUMIFS('Ing-Egr Noviembre 2026'!E4:E103,'Ing-Egr Noviembre 2026'!B4:B103,"Ingreso Marco",'Ing-Egr Noviembre 2026'!C4:C103,A12) | G12: ═══ TOTAL INGRESOS NT ═══ | J12: =J10
A13: Viático | D13: =SUMIFS('Ing-Egr Noviembre 2026'!E4:E103,'Ing-Egr Noviembre 2026'!B4:B103,"Ingreso Marco",'Ing-Egr Noviembre 2026'!C4:C103,A13)
A14: Animador Bíblico | D14: =SUMIFS('Ing-Egr Noviembre 2026'!E4:E103,'Ing-Egr Noviembre 2026'!B4:B103,"Ingreso Marco",'Ing-Egr Noviembre 2026'!C4:C103,A14)
A15: Otros Ocasionales | D15: =SUMIFS('Ing-Egr Noviembre 2026'!E4:E103,'Ing-Egr Noviembre 2026'!B4:B103,"Ingreso Marco",'Ing-Egr Noviembre 2026'!C4:C103,A15) | I15: =J12
A16: TOTAL MARCO | D16: =SUM(D10:D15)
A17: CLARA | C17: Fecha | D17: Monto
A18: Honorarios Diarios | D18: =SUMIF('Ing-Egr Noviembre 2026'!B4:B103,"Ingreso Clara",'Ing-Egr Noviembre 2026'!E4:E103)
A19: TOTAL CLARA | D19: =D18
A20: DESDE NEUROTEA | D20: Monto
A21: Salario Admin Marco | D21: 0
A22: Ganancia NT → Familia | D22: 0
A23: Préstamo NT (automático) | D23: =D6
A24: TOTAL DESDE NT | D24: =SUM(D21:D23)
A26: ═══ TOTAL INGRESOS FAMILIA ═══ | D26: =D16+D19+D24
A28: 📉 GASTOS FAMILIARES | G28: 📉 GASTOS NEUROTEA
A29: Detalle | B29: Estado | C29: Monto | D29: Venc. | G29: Detalle | H29: Estado | I29: Monto | J29: Venc.
A30: ► GASTOS FIJOS ✏️ | G30: ► GASTOS FIJOS ✏️
A31: Salario Lili Doméstico | B31: Ninguno | G31: Alquiler 1 (Principal) | H31: Ninguno | I31: 0
A32: Salario Laura Doméstico | B32: Ninguno | G32: Alquiler 2 (Secundario) | H32: Ninguno | I32: 0
A33: Escuela Fabián y Brenda | B33: Ninguno | G33: Limpieza NeuroTEA | H33: Ninguno | I33: 0
A34: Robótica Niños | B34: Ninguno | G34: ► SUELDOS Y HONORARIOS ✏️
A35: ANDE Casa | B35: Ninguno | G35: Sueldo Aracely | H35: Ninguno | I35: 0
A36: Expensa Casa | B36: Ninguno | G36: Sueldo Fátima | H36: Ninguno | I36: 0
A37: Cajubi Marco | B37: Ninguno | G37: Honorario Contador | H37: Ninguno | I37: 0
A38: Mutual Marco | B38: Ninguno | G38: Salario Administrador | H38: Ninguno | I38: 0
A39: Ña Luisa | B39: Ninguno | G39: Honorario Mant. Sistema | H39: Ninguno | I39: 0
A40: Seguro Médico Papá y Mamá | B40: Ninguno | G40: ► TELEFONÍA E INTERNET ✏️
A41: ► CUOTAS Y PRÉSTAMOS ✏️ | G41: Celular Tigo NeuroTEA | H41: Ninguno | I41: 0
A42: Auto Laura Cuota | B42: Ninguno | G42: Celular Tigo Sistema | H42: Ninguno | I42: 0
A43: Coop. Universitaria Clara | B43: Ninguno | G43: WhatsFlow | H43: Ninguno | I43: 0
A44: Coomecipar Clara | B44: Ninguno | G44: Internet NeuroTEA | H44: Ninguno | I44: 0
A45: Tarjeta Cred. Coomecipar | B45: Ninguno | G45: ► IMPUESTOS ✏️
A46: Solar Préstamo 1 | B46: Ninguno | G46: IVA | H46: Ninguno | I46: 0
A47: Solar Préstamo 2 | B47: Ninguno | G47: ► EVENTOS NT ✏️
A48: Préstamo Lizzi Sueldos | B48: Ninguno | G48: Día del Niño NT | H48: Ninguno | I48: 0
A49: Show Congelador | B49: Ninguno | G49: San Juan NT | H49: Ninguno | I49: 0
A50: Olier Heladera | B50: Ninguno | G50: Día del Autismo NT | H50: Ninguno | I50: 0
A51: ► SUSCRIPCIONES E INTERNET ✏️ | G51: Clausura Padres NT | H51: Ninguno | I51: 0
A52: Giganet | B52: Ninguno | G52: Navidad Papá Noel NT | H52: Ninguno | I52: 0
A53: Tigo Internet/Celulares | B53: Ninguno | G53: Cena Fin de Año NT | H53: Ninguno | I53: 0
A54: Tigo Familiar | B54: Ninguno | G54: ► GASTOS VARIABLES NT 🔗
A55: Google One | B55: Ninguno | G55: Insumos NT | H55: Ninguno | I55: =SUMIFS('Ing-Egr Noviembre 2026'!F4:F103,'Ing-Egr Noviembre 2026'!B4:B103,"Egreso NT",'Ing-Egr Noviembre 2026'!C4:C103,G55)
A56: ChatGPT | B56: Ninguno | G56: Papelería NT | H56: Ninguno | I56: =SUMIFS('Ing-Egr Noviembre 2026'!F4:F103,'Ing-Egr Noviembre 2026'!B4:B103,"Egreso NT",'Ing-Egr Noviembre 2026'!C4:C103,G56)
A57: Claude Marco | B57: Ninguno | G57: Mantenimiento NT | H57: Ninguno | I57: =SUMIFS('Ing-Egr Noviembre 2026'!F4:F103,'Ing-Egr Noviembre 2026'!B4:B103,"Egreso NT",'Ing-Egr Noviembre 2026'!C4:C103,G57)
A58: Claude Clara | B58: Ninguno | G58: Gastos Cursos NT | H58: Ninguno | I58: =SUMIFS('Ing-Egr Noviembre 2026'!F4:F103,'Ing-Egr Noviembre 2026'!B4:B103,"Egreso NT",'Ing-Egr Noviembre 2026'!C4:C103,G58)
A59: iLovePDF | B59: Ninguno | G59: Gastos Varios NT | H59: Ninguno | I59: =SUMIFS('Ing-Egr Noviembre 2026'!F4:F103,'Ing-Egr Noviembre 2026'!B4:B103,"Egreso NT",'Ing-Egr Noviembre 2026'!C4:C103,G59)
A60: Scribd | B60: Ninguno | G60: Reserva NT 1 | H60: Ninguno | I60: =SUMIFS('Ing-Egr Noviembre 2026'!F4:F103,'Ing-Egr Noviembre 2026'!B4:B103,"Egreso NT",'Ing-Egr Noviembre 2026'!C4:C103,G60)
A61: Netflix | B61: Ninguno | G61: Reserva NT 2 | H61: Ninguno | I61: =SUMIFS('Ing-Egr Noviembre 2026'!F4:F103,'Ing-Egr Noviembre 2026'!B4:B103,"Egreso NT",'Ing-Egr Noviembre 2026'!C4:C103,G61)
A62: ► GASTOS VARIABLES 🔗 | G62: Reserva NT 3 | H62: Ninguno | I62: =SUMIFS('Ing-Egr Noviembre 2026'!F4:F103,'Ing-Egr Noviembre 2026'!B4:B103,"Egreso NT",'Ing-Egr Noviembre 2026'!C4:C103,G62)
A63: Combustible | B63: Ninguno | C63: =SUMIFS('Ing-Egr Noviembre 2026'!F4:F103,'Ing-Egr Noviembre 2026'!B4:B103,"Egreso Familiar",'Ing-Egr Noviembre 2026'!C4:C103,A63)
A64: Supermercado | B64: Ninguno | C64: =SUMIFS('Ing-Egr Noviembre 2026'!F4:F103,'Ing-Egr Noviembre 2026'!B4:B103,"Egreso Familiar",'Ing-Egr Noviembre 2026'!C4:C103,A64) | G64: TOTAL NT PAGADOS | I64: =SUMIF(H30:H62,"Pagado",I30:I62)
A65: Farmacia | B65: Ninguno | C65: =SUMIFS('Ing-Egr Noviembre 2026'!F4:F103,'Ing-Egr Noviembre 2026'!B4:B103,"Egreso Familiar",'Ing-Egr Noviembre 2026'!C4:C103,A65) | D65: =C72 | G65: TOTAL NT PENDIENTES | I65: =SUMIF(H30:H62,"Pendiente",I30:I62)
A66: Recreación | B66: Ninguno | C66: =SUMIFS('Ing-Egr Noviembre 2026'!F4:F103,'Ing-Egr Noviembre 2026'!B4:B103,"Egreso Familiar",'Ing-Egr Noviembre 2026'!C4:C103,A66) | D66: =C73
A67: Gastos Varios | B67: Ninguno | C67: =SUMIFS('Ing-Egr Noviembre 2026'!F4:F103,'Ing-Egr Noviembre 2026'!B4:B103,"Egreso Familiar",'Ing-Egr Noviembre 2026'!C4:C103,A67) | G67: 📊 SALUD FINANCIERA NEUROTEA
A68: Reserva Fam 1 | B68: Ninguno | C68: =SUMIFS('Ing-Egr Noviembre 2026'!F4:F103,'Ing-Egr Noviembre 2026'!B4:B103,"Egreso Familiar",'Ing-Egr Noviembre 2026'!C4:C103,A68) | G68: Concepto | H68: % Ideal | I68: Monto Ideal | J68: Monto Real | K68: Estado
A69: Reserva Fam 2 | B69: Ninguno | C69: =SUMIFS('Ing-Egr Noviembre 2026'!F4:F103,'Ing-Egr Noviembre 2026'!B4:B103,"Egreso Familiar",'Ing-Egr Noviembre 2026'!C4:C103,A69) | G69: Gastos Operativos (máx 75%) | H69: 0.75 | I69: =J12*0.75 | J69: =I64+I65 | K69: =IF(J12=0,"-",IF(J69/J12<=0.75,"🟢 OK",IF(J69/J12<=0.9,"🟡 PRECAUCIÓN","🔴 ALARMA")))
A70: Reserva Fam 3 | B70: Ninguno | C70: =SUMIFS('Ing-Egr Noviembre 2026'!F4:F103,'Ing-Egr Noviembre 2026'!B4:B103,"Egreso Familiar",'Ing-Egr Noviembre 2026'!C4:C103,A70) | G70: Ganancia (10%) | H70: 0.1 | I70: =J12*0.1 | J70: =D22 | K70: =IF(J70>=I70,"🟢","🔴")
G71: Inversiones (5%) | H71: 0.05 | I71: =J12*0.05 | J71: 0 | K71: =IF(J71>=I71,"🟢","🔴")
A72: TOTAL FAM. PAGADOS | C72: =SUMIF(B30:B70,"Pagado",C30:C70) | G72: Imprevistos (5%) | H72: 0.05 | I72: =J12*0.05 | J72: 0 | K72: =IF(J72>=I72,"🟢","🔴")
A73: TOTAL FAM. PENDIENTES | C73: =SUMIF(B30:B70,"Pendiente",C30:C70) | G73: Desvío Imprevisto (5%) | H73: 0.05 | I73: =J12*0.05 | J73: 0 | K73: =IF(J73>=I73,"🟢","🔴")
G74: TOTAL | H74: =SUM(H69:H73) | I74: =SUM(I69:I73) | J74: =SUM(J69:J73)
G76: % GASTOS SOBRE INGRESO: | J76: =IF(J12=0,0,J69/J12)
G77: DIAGNÓSTICO: | J77: =IF(J12=0,"Sin datos",IF(J69/J12<=0.75,"🟢 CLÍNICA SANA",IF(J69/J12<=0.9,"🟡 REVISAR GASTOS","🔴 SITUACIÓN CRÍTICA")))

Sheet Ing-Egr Diciembre 2026
A1: 📋 REGISTRO DE MOVIMIENTOS - DICIEMBRE 2026
A3: Fecha | B3: Tipo | C3: Categoría | D3: Descripción | E3: Ingreso | F3: Egreso | G3: Cuenta | H3: Notas
A104: TOTALES | E104: =SUM(E4:E103) | F104: =SUM(F4:F103)
A106: 📊 RESUMEN DEL MES
A107: INGRESOS: | C107: =SUMIF(B4:B103,"Ingreso NT",E4:E103)
A108: Ingreso NT: | C108: =SUMIF(B4:B103,"Ingreso NT",E4:E103)
A109: Ingreso Marco: | C109: =SUMIF(B4:B103,"Ingreso Marco",E4:E103)
A110: Ingreso Clara: | C110: =SUMIF(B4:B103,"Ingreso Clara",E4:E103)
A111: Devolución Fam → NT: | C111: =SUMIF(B4:B103,"Devolución Familia → NT",E4:E103)
A112: TOTAL INGRESOS: | C112: =SUM(C108:C111)
A113: EGRESOS:
A114: EGRESOS: | C114: =SUMIF(B4:B103,"Egreso NT",F4:F103)
A115: Egreso NT: | C115: =SUMIF(B4:B103,"Egreso NT",F4:F103)
A116: Egreso Familiar: | C116: =SUMIF(B4:B103,"Egreso Familiar",F4:F103)
A117: Préstamo NT → Fam: | C117: =SUMIF(B4:B103,"Préstamo NT → Familia",F4:F103)
A118: TOTAL EGRESOS: | C118: =SUM(C115:C117)
A120: SALDO PRÉSTAMO NT → FAM: | C120: =C117-C111
A121: (Prestado - Devuelto)

Sheet Diciembre 2026
A1: 📊 CONTROL FINANCIERO - DICIEMBRE 2026
A3: TOTAL INGRESOS | D3: GASTOS PAGADOS | G3: GASTOS PENDIENTES | J3: BALANCE
A4: =D26+J12 | D4: =D65+I58 | G4: =D66+I59 | J4: =A4-D4-G4
A6: ⚠️ PRÉSTAMO NT → FAMILIA | D6: =SUMIF('Ing-Egr Diciembre 2026'!B4:B103,"Préstamo NT → Familia",'Ing-Egr Diciembre 2026'!F4:F103)-SUMIF('Ing-Egr Diciembre 2026'!B4:B103,"Devolución Familia → NT",'Ing-Egr Diciembre 2026'!E4:E103) | F6: Estado: | G6: =IF(D6=0,"🟢 SANO","🔴 FUGA") | I6: (Ideal = 0)
A8: 💵 INGRESOS FAMILIA | G8: 💵 INGRESOS NEUROTEA
A9: MARCO ITAIPU | C9: Fecha | D9: Monto | G9: Ingreso del Mes | J9: Monto
A10: Salario Mensual | D10: =SUMIFS('Ing-Egr Diciembre 2026'!E4:E103,'Ing-Egr Diciembre 2026'!B4:B103,"Ingreso Marco",'Ing-Egr Diciembre 2026'!C4:C103,A10) | G10: (Suma desde pestaña Ing-Egr Diciembre) | J10: =SUMIF('Ing-Egr Diciembre 2026'!B4:B103,"Ingreso NT",'Ing-Egr Diciembre 2026'!E4:E103)
A11: Vacaciones | D11: =SUMIFS('Ing-Egr Diciembre 2026'!E4:E103,'Ing-Egr Diciembre 2026'!B4:B103,"Ingreso Marco",'Ing-Egr Diciembre 2026'!C4:C103,A11)
A12: Aguinaldo | D12: =SUMIFS('Ing-Egr Diciembre 2026'!E4:E103,'Ing-Egr Diciembre 2026'!B4:B103,"Ingreso Marco",'Ing-Egr Diciembre 2026'!C4:C103,A12) | G12: ═══ TOTAL INGRESOS NT ═══ | J12: =J10
A13: Viático | D13: =SUMIFS('Ing-Egr Diciembre 2026'!E4:E103,'Ing-Egr Diciembre 2026'!B4:B103,"Ingreso Marco",'Ing-Egr Diciembre 2026'!C4:C103,A13)
A14: Animador Bíblico | D14: =SUMIFS('Ing-Egr Diciembre 2026'!E4:E103,'Ing-Egr Diciembre 2026'!B4:B103,"Ingreso Marco",'Ing-Egr Diciembre 2026'!C4:C103,A14)
A15: Otros Ocasionales | D15: =SUMIFS('Ing-Egr Diciembre 2026'!E4:E103,'Ing-Egr Diciembre 2026'!B4:B103,"Ingreso Marco",'Ing-Egr Diciembre 2026'!C4:C103,A15) | I15: =J12
A16: TOTAL MARCO | D16: =SUM(D10:D15)
A17: CLARA | C17: Fecha | D17: Monto
A18: Honorarios Diarios | D18: =SUMIF('Ing-Egr Diciembre 2026'!B4:B103,"Ingreso Clara",'Ing-Egr Diciembre 2026'!E4:E103)
A19: TOTAL CLARA | D19: =D18
A20: DESDE NEUROTEA | D20: Monto
A21: Salario Admin Marco | D21: 0
A22: Ganancia NT → Familia | D22: 0
A23: Préstamo NT (automático) | D23: =D6
A24: TOTAL DESDE NT | D24: =SUM(D21:D23)
A26: ═══ TOTAL INGRESOS FAMILIA ═══ | D26: =D16+D19+D24
A28: 📉 GASTOS FAMILIARES | G28: 📉 GASTOS NEUROTEA
A29: Detalle | B29: Estado | C29: Monto | D29: Venc. | G29: Detalle | H29: Estado | I29: Monto | J29: Venc.
A30: ► GASTOS FIJOS ✏️ | G30: ► GASTOS FIJOS ✏️
A31: Salario Lili Doméstico | B31: Ninguno | G31: Alquiler 1 (Principal) | H31: Ninguno | I31: 0
A32: Salario Laura Doméstico | B32: Ninguno | G32: Alquiler 2 (Secundario) | H32: Ninguno | I32: 0
A33: Escuela Fabián y Brenda | B33: Ninguno | G33: Limpieza NeuroTEA | H33: Ninguno | I33: 0
A34: Robótica Niños | B34: Ninguno | G34: ► SUELDOS Y HONORARIOS ✏️
A35: ANDE Casa | B35: Ninguno | G35: Sueldo Aracely | H35: Ninguno | I35: 0
A36: Expensa Casa | B36: Ninguno | G36: Sueldo Fátima | H36: Ninguno | I36: 0
A37: Cajubi Marco | B37: Ninguno | G37: Honorario Contador | H37: Ninguno | I37: 0
A38: Mutual Marco | B38: Ninguno | G38: Salario Administrador | H38: Ninguno | I38: 0
A39: Ña Luisa | B39: Ninguno | G39: Honorario Mant. Sistema | H39: Ninguno | I39: 0
A40: Seguro Médico Papá y Mamá | B40: Ninguno | G40: ► TELEFONÍA E INTERNET ✏️
A41: ► CUOTAS Y PRÉSTAMOS ✏️ | G41: Celular Tigo NeuroTEA | H41: Ninguno | I41: 0
A42: Auto Laura Cuota | B42: Ninguno | G42: Celular Tigo Sistema | H42: Ninguno | I42: 0
A43: Coop. Universitaria Clara | B43: Ninguno | G43: WhatsFlow | H43: Ninguno | I43: 0
A44: Coomecipar Clara | B44: Ninguno | G44: Internet NeuroTEA | H44: Ninguno | I44: 0
A45: Tarjeta Cred. Coomecipar | B45: Ninguno | G45: ► IMPUESTOS ✏️
A46: Solar Préstamo 1 | B46: Ninguno | G46: IVA | H46: Ninguno | I46: 0
A47: Solar Préstamo 2 | B47: Ninguno | G47: ► EVENTOS NT ✏️
A48: Préstamo Lizzi Sueldos | B48: Ninguno | G48: Día del Niño NT | H48: Ninguno | I48: 0
A49: Show Congelador | B49: Ninguno | G49: San Juan NT | H49: Ninguno | I49: 0
A50: Olier Heladera | B50: Ninguno | G50: Día del Autismo NT | H50: Ninguno | I50: 0
A51: ► SUSCRIPCIONES E INTERNET ✏️ | G51: Clausura Padres NT | H51: Ninguno | I51: 0
A52: Giganet | B52: Ninguno | G52: Navidad Papá Noel NT | H52: Ninguno | I52: 0
A53: Tigo Internet/Celulares | B53: Ninguno | G53: Cena Fin de Año NT | H53: Ninguno | I53: 0
A54: Tigo Familiar | B54: Ninguno | G54: ► GASTOS VARIABLES NT 🔗
A55: Google One | B55: Ninguno | G55: Insumos NT | H55: Ninguno | I55: =SUMIFS('Ing-Egr Diciembre 2026'!F4:F103,'Ing-Egr Diciembre 2026'!B4:B103,"Egreso NT",'Ing-Egr Diciembre 2026'!C4:C103,G55)
A56: ChatGPT | B56: Ninguno | G56: Papelería NT | H56: Ninguno | I56: =SUMIFS('Ing-Egr Diciembre 2026'!F4:F103,'Ing-Egr Diciembre 2026'!B4:B103,"Egreso NT",'Ing-Egr Diciembre 2026'!C4:C103,G56)
A57: Claude Marco | B57: Ninguno | G57: Mantenimiento NT | H57: Ninguno | I57: =SUMIFS('Ing-Egr Diciembre 2026'!F4:F103,'Ing-Egr Diciembre 2026'!B4:B103,"Egreso NT",'Ing-Egr Diciembre 2026'!C4:C103,G57)
A58: Claude Clara | B58: Ninguno | G58: Gastos Cursos NT | H58: Ninguno | I58: =SUMIFS('Ing-Egr Diciembre 2026'!F4:F103,'Ing-Egr Diciembre 2026'!B4:B103,"Egreso NT",'Ing-Egr Diciembre 2026'!C4:C103,G58)
A59: iLovePDF | B59: Ninguno | G59: Gastos Varios NT | H59: Ninguno | I59: =SUMIFS('Ing-Egr Diciembre 2026'!F4:F103,'Ing-Egr Diciembre 2026'!B4:B103,"Egreso NT",'Ing-Egr Diciembre 2026'!C4:C103,G59)
A60: Scribd | B60: Ninguno | G60: Reserva NT 1 | H60: Ninguno | I60: =SUMIFS('Ing-Egr Diciembre 2026'!F4:F103,'Ing-Egr Diciembre 2026'!B4:B103,"Egreso NT",'Ing-Egr Diciembre 2026'!C4:C103,G60)
A61: Netflix | B61: Ninguno | G61: Reserva NT 2 | H61: Ninguno | I61: =SUMIFS('Ing-Egr Diciembre 2026'!F4:F103,'Ing-Egr Diciembre 2026'!B4:B103,"Egreso NT",'Ing-Egr Diciembre 2026'!C4:C103,G61)
A62: ► GASTOS VARIABLES 🔗 | G62: Reserva NT 3 | H62: Ninguno | I62: =SUMIFS('Ing-Egr Diciembre 2026'!F4:F103,'Ing-Egr Diciembre 2026'!B4:B103,"Egreso NT",'Ing-Egr Diciembre 2026'!C4:C103,G62)
A63: Combustible | B63: Ninguno | C63: =SUMIFS('Ing-Egr Diciembre 2026'!F4:F103,'Ing-Egr Diciembre 2026'!B4:B103,"Egreso Familiar",'Ing-Egr Diciembre 2026'!C4:C103,A63)
A64: Supermercado | B64: Ninguno | C64: =SUMIFS('Ing-Egr Diciembre 2026'!F4:F103,'Ing-Egr Diciembre 2026'!B4:B103,"Egreso Familiar",'Ing-Egr Diciembre 2026'!C4:C103,A64) | G64: TOTAL NT PAGADOS | I64: =SUMIF(H30:H62,"Pagado",I30:I62)
A65: Farmacia | B65: Ninguno | C65: =SUMIFS('Ing-Egr Diciembre 2026'!F4:F103,'Ing-Egr Diciembre 2026'!B4:B103,"Egreso Familiar",'Ing-Egr Diciembre 2026'!C4:C103,A65) | D65: =C72 | G65: TOTAL NT PENDIENTES | I65: =SUMIF(H30:H62,"Pendiente",I30:I62)
A66: Recreación | B66: Ninguno | C66: =SUMIFS('Ing-Egr Diciembre 2026'!F4:F103,'Ing-Egr Diciembre 2026'!B4:B103,"Egreso Familiar",'Ing-Egr Diciembre 2026'!C4:C103,A66) | D66: =C73
A67: Gastos Varios | B67: Ninguno | C67: =SUMIFS('Ing-Egr Diciembre 2026'!F4:F103,'Ing-Egr Diciembre 2026'!B4:B103,"Egreso Familiar",'Ing-Egr Diciembre 2026'!C4:C103,A67) | G67: 📊 SALUD FINANCIERA NEUROTEA
A68: Reserva Fam 1 | B68: Ninguno | C68: =SUMIFS('Ing-Egr Diciembre 2026'!F4:F103,'Ing-Egr Diciembre 2026'!B4:B103,"Egreso Familiar",'Ing-Egr Diciembre 2026'!C4:C103,A68) | G68: Concepto | H68: % Ideal | I68: Monto Ideal | J68: Monto Real | K68: Estado
A69: Reserva Fam 2 | B69: Ninguno | C69: =SUMIFS('Ing-Egr Diciembre 2026'!F4:F103,'Ing-Egr Diciembre 2026'!B4:B103,"Egreso Familiar",'Ing-Egr Diciembre 2026'!C4:C103,A69) | G69: Gastos Operativos (máx 75%) | H69: 0.75 | I69: =J12*0.75 | J69: =I64+I65 | K69: =IF(J12=0,"-",IF(J69/J12<=0.75,"🟢 OK",IF(J69/J12<=0.9,"🟡 PRECAUCIÓN","🔴 ALARMA")))
A70: Reserva Fam 3 | B70: Ninguno | C70: =SUMIFS('Ing-Egr Diciembre 2026'!F4:F103,'Ing-Egr Diciembre 2026'!B4:B103,"Egreso Familiar",'Ing-Egr Diciembre 2026'!C4:C103,A70) | G70: Ganancia (10%) | H70: 0.1 | I70: =J12*0.1 | J70: =D22 | K70: =IF(J70>=I70,"🟢","🔴")
G71: Inversiones (5%) | H71: 0.05 | I71: =J12*0.05 | J71: 0 | K71: =IF(J71>=I71,"🟢","🔴")
A72: TOTAL FAM. PAGADOS | C72: =SUMIF(B30:B70,"Pagado",C30:C70) | G72: Imprevistos (5%) | H72: 0.05 | I72: =J12*0.05 | J72: 0 | K72: =IF(J72>=I72,"🟢","🔴")
A73: TOTAL FAM. PENDIENTES | C73: =SUMIF(B30:B70,"Pendiente",C30:C70) | G73: Desvío Imprevisto (5%) | H73: 0.05 | I73: =J12*0.05 | J73: 0 | K73: =IF(J73>=I73,"🟢","🔴")
G74: TOTAL | H74: =SUM(H69:H73) | I74: =SUM(I69:I73) | J74: =SUM(J69:J73)
G76: % GASTOS SOBRE INGRESO: | J76: =IF(J12=0,0,J69/J12)
G77: DIAGNÓSTICO: | J77: =IF(J12=0,"Sin datos",IF(J69/J12<=0.75,"🟢 CLÍNICA SANA",IF(J69/J12<=0.9,"🟡 REVISAR GASTOS","🔴 SITUACIÓN CRÍTICA")))
